Workbook
Name conn_p1: Scenarios!$B$29
Name conn_p2: Scenarios!$B$30
Name conn_p3: Scenarios!$B$31
Name conn_p4: Scenarios!$B$32
Name conn_p5: Scenarios!$B$33
Name mult_act: Forecast!$B$27
Name mult_avg: Forecast!$B$26
Name mult_cons: Forecast!$B$25
Name naph_yield: HVN!$D$23
Name ref_intake: HVN!$D$24

Sheet What's Changed
A1: What's Changed: rolling MoM & WoW (as of Jun 29, 2026)
A2: Month-over-month is live off Data -- the balance that prices. Week-over-week compares your weekly pulls (source is monthly, so the rolling log grows one row per build).
A4: Month-over-month (live off Data -- this is the balance that prices)
A5: As-of month (edit year / month) | B5: 2026 | C5: 6
A6: Prior month | B6: =IF(C5=1,B5-1,B5) -> 2026 | C6: =IF(C5=1,12,C5-1) -> 5
A8: Metric | B8: This month | C8: Prior month | D8: Δ | E8: Δ%
A9: Total offline | B9: =SUMIFS(Data!$K:$K,Data!$A:$A,$B$5,Data!$B:$B,$C$5) -> 1349.6757 | C9: =SUMIFS(Data!$K:$K,Data!$A:$A,$B$6,Data!$B:$B,$C$6) -> 2203.7437 | D9: =B9-C9 -> -854.068 | E9: =IFERROR(D9/C9,"") -> -0.38755323
A10: Planned | B10: =SUMIFS(Data!$K:$K,Data!$A:$A,$B$5,Data!$B:$B,$C$5,Data!$J:$J,"PLANNED") -> 182.45 | C10: =SUMIFS(Data!$K:$K,Data!$A:$A,$B$6,Data!$B:$B,$C$6,Data!$J:$J,"PLANNED") -> 1001.3308 | D10: =B10-C10 -> -818.8808 | E10: =IFERROR(D10/C10,"") -> -0.81779248
A11: Unplanned | B11: =SUMIFS(Data!$K:$K,Data!$A:$A,$B$5,Data!$B:$B,$C$5,Data!$J:$J,"UNPLANNED") -> 1167.2257 | C11: =SUMIFS(Data!$K:$K,Data!$A:$A,$B$6,Data!$B:$B,$C$6,Data!$J:$J,"UNPLANNED") -> 1202.4129 | D11: =B11-C11 -> -35.1872 | E11: =IFERROR(D11/C11,"") -> -0.029263824
A12: CDU | B12: =SUMIFS(Data!$K:$K,Data!$A:$A,$B$5,Data!$B:$B,$C$5,Data!$G:$G,"CDU") -> 435.03 | C12: =SUMIFS(Data!$K:$K,Data!$A:$A,$B$6,Data!$B:$B,$C$6,Data!$G:$G,"CDU") -> 841.202 | D12: =B12-C12 -> -406.172 | E12: =IFERROR(D12/C12,"") -> -0.48284716
A13: FCC | B13: =SUMIFS(Data!$K:$K,Data!$A:$A,$B$5,Data!$B:$B,$C$5,Data!$G:$G,"FCC") -> 147.405 | C13: =SUMIFS(Data!$K:$K,Data!$A:$A,$B$6,Data!$B:$B,$C$6,Data!$G:$G,"FCC") -> 360.0815 | D13: =B13-C13 -> -212.6765 | E13: =IFERROR(D13/C13,"") -> -0.59063434
A14: Hydrocracker | B14: =SUMIFS(Data!$K:$K,Data!$A:$A,$B$5,Data!$B:$B,$C$5,Data!$G:$G,"Hydrocracker") -> 21.38 | C14: =SUMIFS(Data!$K:$K,Data!$A:$A,$B$6,Data!$B:$B,$C$6,Data!$G:$G,"Hydrocracker") -> 92.77 | D14: =B14-C14 -> -71.39 | E14: =IFERROR(D14/C14,"") -> -0.76953757
A15: Reformer | B15: =SUMIFS(Data!$K:$K,Data!$A:$A,$B$5,Data!$B:$B,$C$5,Data!$G:$G,"Reformer") -> 130.51 | C15: =SUMIFS(Data!$K:$K,Data!$A:$A,$B$6,Data!$B:$B,$C$6,Data!$G:$G,"Reformer") -> 157.769 | D15: =B15-C15 -> -27.259 | E15: =IFERROR(D15/C15,"") -> -0.17277792
A17: Rolling: trailing 6 months (live)
A18: Month | B18: Total | C18: Planned | D18: Unplanned
A19: Jan 2026 | B19: =SUMIFS(Data!$K:$K,Data!$A:$A,2026,Data!$B:$B,1) -> 1849.6688 | C19: =SUMIFS(Data!$K:$K,Data!$A:$A,2026,Data!$B:$B,1,Data!$J:$J,"PLANNED") -> 1062.6823 | D19: =SUMIFS(Data!$K:$K,Data!$A:$A,2026,Data!$B:$B,1,Data!$J:$J,"UNPLANNED") -> 786.9865
A20: Feb 2026 | B20: =SUMIFS(Data!$K:$K,Data!$A:$A,2026,Data!$B:$B,2) -> 3739.2241 | C20: =SUMIFS(Data!$K:$K,Data!$A:$A,2026,Data!$B:$B,2,Data!$J:$J,"PLANNED") -> 1946.2561 | D20: =SUMIFS(Data!$K:$K,Data!$A:$A,2026,Data!$B:$B,2,Data!$J:$J,"UNPLANNED") -> 1792.968
A21: Mar 2026 | B21: =SUMIFS(Data!$K:$K,Data!$A:$A,2026,Data!$B:$B,3) -> 3152.1816 | C21: =SUMIFS(Data!$K:$K,Data!$A:$A,2026,Data!$B:$B,3,Data!$J:$J,"PLANNED") -> 2033.7659 | D21: =SUMIFS(Data!$K:$K,Data!$A:$A,2026,Data!$B:$B,3,Data!$J:$J,"UNPLANNED") -> 1118.4157
A22: Apr 2026 | B22: =SUMIFS(Data!$K:$K,Data!$A:$A,2026,Data!$B:$B,4) -> 3982.502 | C22: =SUMIFS(Data!$K:$K,Data!$A:$A,2026,Data!$B:$B,4,Data!$J:$J,"PLANNED") -> 1938.51 | D22: =SUMIFS(Data!$K:$K,Data!$A:$A,2026,Data!$B:$B,4,Data!$J:$J,"UNPLANNED") -> 2043.992
A23: May 2026 | B23: =SUMIFS(Data!$K:$K,Data!$A:$A,2026,Data!$B:$B,5) -> 2203.7437 | C23: =SUMIFS(Data!$K:$K,Data!$A:$A,2026,Data!$B:$B,5,Data!$J:$J,"PLANNED") -> 1001.3308 | D23: =SUMIFS(Data!$K:$K,Data!$A:$A,2026,Data!$B:$B,5,Data!$J:$J,"UNPLANNED") -> 1202.4129
A24: Jun 2026 | B24: =SUMIFS(Data!$K:$K,Data!$A:$A,2026,Data!$B:$B,6) -> 1349.6757 | C24: =SUMIFS(Data!$K:$K,Data!$A:$A,2026,Data!$B:$B,6,Data!$J:$J,"PLANNED") -> 182.45 | D24: =SUMIFS(Data!$K:$K,Data!$A:$A,2026,Data!$B:$B,6,Data!$J:$J,"UNPLANNED") -> 1167.2257
A26: Week-over-week: your weekly pulls (rolling; one row per build)
A27: Pull date | B27: Jun 2026 | C27: Δ vs prior pull | D27: 2026-07 next mo
A28: 2026-06-27 | B28: 1349.7 | D28: 1075
A29: 2026-06-29 | B29: 1349.7 | C29: 0 | D29: 1075
A30: Each build appends today's snapshot (current + next 6 months' offline) to data/whatschanged_log.csv. Run it weekly after refreshing the Snowflake and the Δ shows what the vendor added/pulled since last week. Δ on the current month is the contract-relevant move.
A32: New this month (Jun 2026) -- not down the prior month
A33: Plant | B33: Unit | C33: PADD | D33: kbd
A34: Corpus Christi Refinery | B34: ATMOS DISTILLATION | C34: PADD 3 | D34: 104
A35: Trainer Refinery | B35: ATMOS DISTILLATION | C35: PADD 1 | D35: 52
A36: Texas City Refinery | B36: HYDROTREATING | C36: PADD 3 | D36: 51.7
A37: Trainer Refinery | B37: ATMOS DISTILLATION | C37: PADD 1 | D37: 48.9
A38: Par East Refinery | B38: ATMOS DISTILLATION | C38: PADD 5 | D38: 45
A39: Port Arthur Refinery (To | B39: ATMOS DISTILLATION | C39: PADD 3 | D39: 40.5
A41: Back online this month -- down the prior month, not now
A42: Plant | B42: Unit | C42: PADD | D42: kbd
A43: Robinson Refinery | B43: ATMOS DISTILLATION | C43: PADD 2 | D43: 180.7
A44: Baytown Refinery | B44: ATMOS DISTILLATION | C44: PADD 3 | D44: 113.4
A45: El Segundo Refinery | B45: HYDROTREATING | C45: PADD 5 | D45: 58.8
A46: Kenai Refinery | B46: ATMOS DISTILLATION | C46: PADD 5 | D46: 53.3
A47: Cherry Point Refinery | B47: ATMOS DISTILLATION | C47: PADD 5 | D47: 47.5
A48: Valdez Refinery | B48: ATMOS DISTILLATION | C48: PADD 5 | D48: 34.8

Sheet Per-Unit
A1: Per-Unit Concurrent Capacity Offline (kbd, day-weighted) = SUMIFS over Data
A2: Each focus unit on its own, by month and year. Never summed across units.
A4: Crude (CDU)
A5: Year | B5: Jan | C5: Feb | D5: Mar | E5: Apr | F5: May | G5: Jun | H5: Jul | I5: Aug | J5: Sep | K5: Oct | L5: Nov | M5: Dec
A6: 2023 | B6: =SUMIFS(Data!$K:$K,Data!$A:$A,2023,Data!$B:$B,1,Data!$G:$G,"CDU") -> 1739.545 | C6: =SUMIFS(Data!$K:$K,Data!$A:$A,2023,Data!$B:$B,2,Data!$G:$G,"CDU") -> 2180.255 | D6: =SUMIFS(Data!$K:$K,Data!$A:$A,2023,Data!$B:$B,3,Data!$G:$G,"CDU") -> 2060.202 | E6: =SUMIFS(Data!$K:$K,Data!$A:$A,2023,Data!$B:$B,4,Data!$G:$G,"CDU") -> 1806.215 | F6: =SUMIFS(Data!$K:$K,Data!$A:$A,2023,Data!$B:$B,5,Data!$G:$G,"CDU") -> 1061.1038 | G6: =SUMIFS(Data!$K:$K,Data!$A:$A,2023,Data!$B:$B,6,Data!$G:$G,"CDU") -> 794.9545 | H6: =SUMIFS(Data!$K:$K,Data!$A:$A,2023,Data!$B:$B,7,Data!$G:$G,"CDU") -> 510.65 | I6: =SUMIFS(Data!$K:$K,Data!$A:$A,2023,Data!$B:$B,8,Data!$G:$G,"CDU") -> 510.13 | J6: =SUMIFS(Data!$K:$K,Data!$A:$A,2023,Data!$B:$B,9,Data!$G:$G,"CDU") -> 1099.23 | K6: =SUMIFS(Data!$K:$K,Data!$A:$A,2023,Data!$B:$B,10,Data!$G:$G,"CDU") -> 2033.6085 | L6: =SUMIFS(Data!$K:$K,Data!$A:$A,2023,Data!$B:$B,11,Data!$G:$G,"CDU") -> 881.06 | M6: =SUMIFS(Data!$K:$K,Data!$A:$A,2023,Data!$B:$B,12,Data!$G:$G,"CDU") -> 256.08
A7: 2024 | B7: =SUMIFS(Data!$K:$K,Data!$A:$A,2024,Data!$B:$B,1,Data!$G:$G,"CDU") -> 1313.892 | C7: =SUMIFS(Data!$K:$K,Data!$A:$A,2024,Data!$B:$B,2,Data!$G:$G,"CDU") -> 2142.5348 | D7: =SUMIFS(Data!$K:$K,Data!$A:$A,2024,Data!$B:$B,3,Data!$G:$G,"CDU") -> 1268.1126 | E7: =SUMIFS(Data!$K:$K,Data!$A:$A,2024,Data!$B:$B,4,Data!$G:$G,"CDU") -> 1440.7505 | F7: =SUMIFS(Data!$K:$K,Data!$A:$A,2024,Data!$B:$B,5,Data!$G:$G,"CDU") -> 501.391 | G7: =SUMIFS(Data!$K:$K,Data!$A:$A,2024,Data!$B:$B,6,Data!$G:$G,"CDU") -> 455.03 | H7: =SUMIFS(Data!$K:$K,Data!$A:$A,2024,Data!$B:$B,7,Data!$G:$G,"CDU") -> 646.83 | I7: =SUMIFS(Data!$K:$K,Data!$A:$A,2024,Data!$B:$B,8,Data!$G:$G,"CDU") -> 550.098 | J7: =SUMIFS(Data!$K:$K,Data!$A:$A,2024,Data!$B:$B,9,Data!$G:$G,"CDU") -> 1090.8784 | K7: =SUMIFS(Data!$K:$K,Data!$A:$A,2024,Data!$B:$B,10,Data!$G:$G,"CDU") -> 1122.32 | L7: =SUMIFS(Data!$K:$K,Data!$A:$A,2024,Data!$B:$B,11,Data!$G:$G,"CDU") -> 715.6 | M7: =SUMIFS(Data!$K:$K,Data!$A:$A,2024,Data!$B:$B,12,Data!$G:$G,"CDU") -> 288.8526
A8: 2025 | B8: =SUMIFS(Data!$K:$K,Data!$A:$A,2025,Data!$B:$B,1,Data!$G:$G,"CDU") -> 1256.145 | C8: =SUMIFS(Data!$K:$K,Data!$A:$A,2025,Data!$B:$B,2,Data!$G:$G,"CDU") -> 1649.407 | D8: =SUMIFS(Data!$K:$K,Data!$A:$A,2025,Data!$B:$B,3,Data!$G:$G,"CDU") -> 1632.123 | E8: =SUMIFS(Data!$K:$K,Data!$A:$A,2025,Data!$B:$B,4,Data!$G:$G,"CDU") -> 1850.1686 | F8: =SUMIFS(Data!$K:$K,Data!$A:$A,2025,Data!$B:$B,5,Data!$G:$G,"CDU") -> 956.3466 | G8: =SUMIFS(Data!$K:$K,Data!$A:$A,2025,Data!$B:$B,6,Data!$G:$G,"CDU") -> 488.1771 | H8: =SUMIFS(Data!$K:$K,Data!$A:$A,2025,Data!$B:$B,7,Data!$G:$G,"CDU") -> 349.903 | I8: =SUMIFS(Data!$K:$K,Data!$A:$A,2025,Data!$B:$B,8,Data!$G:$G,"CDU") -> 393.8658 | J8: =SUMIFS(Data!$K:$K,Data!$A:$A,2025,Data!$B:$B,9,Data!$G:$G,"CDU") -> 1152.71 | K8: =SUMIFS(Data!$K:$K,Data!$A:$A,2025,Data!$B:$B,10,Data!$G:$G,"CDU") -> 1864.885 | L8: =SUMIFS(Data!$K:$K,Data!$A:$A,2025,Data!$B:$B,11,Data!$G:$G,"CDU") -> 989.6356 | M8: =SUMIFS(Data!$K:$K,Data!$A:$A,2025,Data!$B:$B,12,Data!$G:$G,"CDU") -> 313.306
A9: 2026 | B9: =SUMIFS(Data!$K:$K,Data!$A:$A,2026,Data!$B:$B,1,Data!$G:$G,"CDU") -> 531.3 | C9: =SUMIFS(Data!$K:$K,Data!$A:$A,2026,Data!$B:$B,2,Data!$G:$G,"CDU") -> 1246.845 | D9: =SUMIFS(Data!$K:$K,Data!$A:$A,2026,Data!$B:$B,3,Data!$G:$G,"CDU") -> 968.521 | E9: =SUMIFS(Data!$K:$K,Data!$A:$A,2026,Data!$B:$B,4,Data!$G:$G,"CDU") -> 1411.605 | F9: =SUMIFS(Data!$K:$K,Data!$A:$A,2026,Data!$B:$B,5,Data!$G:$G,"CDU") -> 841.202 | G9: =SUMIFS(Data!$K:$K,Data!$A:$A,2026,Data!$B:$B,6,Data!$G:$G,"CDU") -> 435.03 | H9: =SUMIFS(Data!$K:$K,Data!$A:$A,2026,Data!$B:$B,7,Data!$G:$G,"CDU") -> 378.602 | I9: =SUMIFS(Data!$K:$K,Data!$A:$A,2026,Data!$B:$B,8,Data!$G:$G,"CDU") -> 126 | J9: =SUMIFS(Data!$K:$K,Data!$A:$A,2026,Data!$B:$B,9,Data!$G:$G,"CDU") -> 448.14 | K9: =SUMIFS(Data!$K:$K,Data!$A:$A,2026,Data!$B:$B,10,Data!$G:$G,"CDU") -> 661.633 | L9: =SUMIFS(Data!$K:$K,Data!$A:$A,2026,Data!$B:$B,11,Data!$G:$G,"CDU") -> 214.3 | M9: =SUMIFS(Data!$K:$K,Data!$A:$A,2026,Data!$B:$B,12,Data!$G:$G,"CDU") -> 0
A10: 2027 | B10: =SUMIFS(Data!$K:$K,Data!$A:$A,2027,Data!$B:$B,1,Data!$G:$G,"CDU") -> 365.125 | C10: =SUMIFS(Data!$K:$K,Data!$A:$A,2027,Data!$B:$B,2,Data!$G:$G,"CDU") -> 683.258 | D10: =SUMIFS(Data!$K:$K,Data!$A:$A,2027,Data!$B:$B,3,Data!$G:$G,"CDU") -> 1062.14 | E10: =SUMIFS(Data!$K:$K,Data!$A:$A,2027,Data!$B:$B,4,Data!$G:$G,"CDU") -> 663.255 | F10: =SUMIFS(Data!$K:$K,Data!$A:$A,2027,Data!$B:$B,5,Data!$G:$G,"CDU") -> 320.192 | G10: =SUMIFS(Data!$K:$K,Data!$A:$A,2027,Data!$B:$B,6,Data!$G:$G,"CDU") -> 96 | H10: =SUMIFS(Data!$K:$K,Data!$A:$A,2027,Data!$B:$B,7,Data!$G:$G,"CDU") -> 96 | I10: =SUMIFS(Data!$K:$K,Data!$A:$A,2027,Data!$B:$B,8,Data!$G:$G,"CDU") -> 27.84 | J10: =SUMIFS(Data!$K:$K,Data!$A:$A,2027,Data!$B:$B,9,Data!$G:$G,"CDU") -> 976.735 | K10: =SUMIFS(Data!$K:$K,Data!$A:$A,2027,Data!$B:$B,10,Data!$G:$G,"CDU") -> 1307.315 | L10: =SUMIFS(Data!$K:$K,Data!$A:$A,2027,Data!$B:$B,11,Data!$G:$G,"CDU") -> 283.9 | M10: =SUMIFS(Data!$K:$K,Data!$A:$A,2027,Data!$B:$B,12,Data!$G:$G,"CDU") -> 0
A13: FCC (cat cracker)
A14: Year | B14: Jan | C14: Feb | D14: Mar | E14: Apr | F14: May | G14: Jun | H14: Jul | I14: Aug | J14: Sep | K14: Oct | L14: Nov | M14: Dec
A15: 2023 | B15: =SUMIFS(Data!$K:$K,Data!$A:$A,2023,Data!$B:$B,1,Data!$G:$G,"FCC") -> 810.943 | C15: =SUMIFS(Data!$K:$K,Data!$A:$A,2023,Data!$B:$B,2,Data!$G:$G,"FCC") -> 1025.05 | D15: =SUMIFS(Data!$K:$K,Data!$A:$A,2023,Data!$B:$B,3,Data!$G:$G,"FCC") -> 880.265 | E15: =SUMIFS(Data!$K:$K,Data!$A:$A,2023,Data!$B:$B,4,Data!$G:$G,"FCC") -> 615.626 | F15: =SUMIFS(Data!$K:$K,Data!$A:$A,2023,Data!$B:$B,5,Data!$G:$G,"FCC") -> 530.395 | G15: =SUMIFS(Data!$K:$K,Data!$A:$A,2023,Data!$B:$B,6,Data!$G:$G,"FCC") -> 406.9475 | H15: =SUMIFS(Data!$K:$K,Data!$A:$A,2023,Data!$B:$B,7,Data!$G:$G,"FCC") -> 232.66 | I15: =SUMIFS(Data!$K:$K,Data!$A:$A,2023,Data!$B:$B,8,Data!$G:$G,"FCC") -> 161.055 | J15: =SUMIFS(Data!$K:$K,Data!$A:$A,2023,Data!$B:$B,9,Data!$G:$G,"FCC") -> 407.94 | K15: =SUMIFS(Data!$K:$K,Data!$A:$A,2023,Data!$B:$B,10,Data!$G:$G,"FCC") -> 590.53 | L15: =SUMIFS(Data!$K:$K,Data!$A:$A,2023,Data!$B:$B,11,Data!$G:$G,"FCC") -> 347.605 | M15: =SUMIFS(Data!$K:$K,Data!$A:$A,2023,Data!$B:$B,12,Data!$G:$G,"FCC") -> 152.404
A16: 2024 | B16: =SUMIFS(Data!$K:$K,Data!$A:$A,2024,Data!$B:$B,1,Data!$G:$G,"FCC") -> 313.199 | C16: =SUMIFS(Data!$K:$K,Data!$A:$A,2024,Data!$B:$B,2,Data!$G:$G,"FCC") -> 1054.9718 | D16: =SUMIFS(Data!$K:$K,Data!$A:$A,2024,Data!$B:$B,3,Data!$G:$G,"FCC") -> 579.138 | E16: =SUMIFS(Data!$K:$K,Data!$A:$A,2024,Data!$B:$B,4,Data!$G:$G,"FCC") -> 489.937 | F16: =SUMIFS(Data!$K:$K,Data!$A:$A,2024,Data!$B:$B,5,Data!$G:$G,"FCC") -> 277.135 | G16: =SUMIFS(Data!$K:$K,Data!$A:$A,2024,Data!$B:$B,6,Data!$G:$G,"FCC") -> 334.165 | H16: =SUMIFS(Data!$K:$K,Data!$A:$A,2024,Data!$B:$B,7,Data!$G:$G,"FCC") -> 356.206 | I16: =SUMIFS(Data!$K:$K,Data!$A:$A,2024,Data!$B:$B,8,Data!$G:$G,"FCC") -> 309.4394 | J16: =SUMIFS(Data!$K:$K,Data!$A:$A,2024,Data!$B:$B,9,Data!$G:$G,"FCC") -> 652.189 | K16: =SUMIFS(Data!$K:$K,Data!$A:$A,2024,Data!$B:$B,10,Data!$G:$G,"FCC") -> 453.501 | L16: =SUMIFS(Data!$K:$K,Data!$A:$A,2024,Data!$B:$B,11,Data!$G:$G,"FCC") -> 153.011 | M16: =SUMIFS(Data!$K:$K,Data!$A:$A,2024,Data!$B:$B,12,Data!$G:$G,"FCC") -> 59.754
A17: 2025 | B17: =SUMIFS(Data!$K:$K,Data!$A:$A,2025,Data!$B:$B,1,Data!$G:$G,"FCC") -> 297.316 | C17: =SUMIFS(Data!$K:$K,Data!$A:$A,2025,Data!$B:$B,2,Data!$G:$G,"FCC") -> 403.831 | D17: =SUMIFS(Data!$K:$K,Data!$A:$A,2025,Data!$B:$B,3,Data!$G:$G,"FCC") -> 472.933 | E17: =SUMIFS(Data!$K:$K,Data!$A:$A,2025,Data!$B:$B,4,Data!$G:$G,"FCC") -> 576.225 | F17: =SUMIFS(Data!$K:$K,Data!$A:$A,2025,Data!$B:$B,5,Data!$G:$G,"FCC") -> 393.455 | G17: =SUMIFS(Data!$K:$K,Data!$A:$A,2025,Data!$B:$B,6,Data!$G:$G,"FCC") -> 215.541 | H17: =SUMIFS(Data!$K:$K,Data!$A:$A,2025,Data!$B:$B,7,Data!$G:$G,"FCC") -> 183.557 | I17: =SUMIFS(Data!$K:$K,Data!$A:$A,2025,Data!$B:$B,8,Data!$G:$G,"FCC") -> 235.215 | J17: =SUMIFS(Data!$K:$K,Data!$A:$A,2025,Data!$B:$B,9,Data!$G:$G,"FCC") -> 364.325 | K17: =SUMIFS(Data!$K:$K,Data!$A:$A,2025,Data!$B:$B,10,Data!$G:$G,"FCC") -> 702.5715 | L17: =SUMIFS(Data!$K:$K,Data!$A:$A,2025,Data!$B:$B,11,Data!$G:$G,"FCC") -> 409.0129 | M17: =SUMIFS(Data!$K:$K,Data!$A:$A,2025,Data!$B:$B,12,Data!$G:$G,"FCC") -> 75.961
A18: 2026 | B18: =SUMIFS(Data!$K:$K,Data!$A:$A,2026,Data!$B:$B,1,Data!$G:$G,"FCC") -> 299.98 | C18: =SUMIFS(Data!$K:$K,Data!$A:$A,2026,Data!$B:$B,2,Data!$G:$G,"FCC") -> 559.7625 | D18: =SUMIFS(Data!$K:$K,Data!$A:$A,2026,Data!$B:$B,3,Data!$G:$G,"FCC") -> 331.375 | E18: =SUMIFS(Data!$K:$K,Data!$A:$A,2026,Data!$B:$B,4,Data!$G:$G,"FCC") -> 558.008 | F18: =SUMIFS(Data!$K:$K,Data!$A:$A,2026,Data!$B:$B,5,Data!$G:$G,"FCC") -> 360.0815 | G18: =SUMIFS(Data!$K:$K,Data!$A:$A,2026,Data!$B:$B,6,Data!$G:$G,"FCC") -> 147.405 | H18: =SUMIFS(Data!$K:$K,Data!$A:$A,2026,Data!$B:$B,7,Data!$G:$G,"FCC") -> 69.8 | I18: =SUMIFS(Data!$K:$K,Data!$A:$A,2026,Data!$B:$B,8,Data!$G:$G,"FCC") -> 30.6 | J18: =SUMIFS(Data!$K:$K,Data!$A:$A,2026,Data!$B:$B,9,Data!$G:$G,"FCC") -> 68.93 | K18: =SUMIFS(Data!$K:$K,Data!$A:$A,2026,Data!$B:$B,10,Data!$G:$G,"FCC") -> 189.01 | L18: =SUMIFS(Data!$K:$K,Data!$A:$A,2026,Data!$B:$B,11,Data!$G:$G,"FCC") -> 127.225 | M18: =SUMIFS(Data!$K:$K,Data!$A:$A,2026,Data!$B:$B,12,Data!$G:$G,"FCC") -> 4.8
A19: 2027 | B19: =SUMIFS(Data!$K:$K,Data!$A:$A,2027,Data!$B:$B,1,Data!$G:$G,"FCC") -> 250.98 | C19: =SUMIFS(Data!$K:$K,Data!$A:$A,2027,Data!$B:$B,2,Data!$G:$G,"FCC") -> 450.5215 | D19: =SUMIFS(Data!$K:$K,Data!$A:$A,2027,Data!$B:$B,3,Data!$G:$G,"FCC") -> 447.892 | E19: =SUMIFS(Data!$K:$K,Data!$A:$A,2027,Data!$B:$B,4,Data!$G:$G,"FCC") -> 150.455 | F19: =SUMIFS(Data!$K:$K,Data!$A:$A,2027,Data!$B:$B,5,Data!$G:$G,"FCC") -> 23.3 | G19: =SUMIFS(Data!$K:$K,Data!$A:$A,2027,Data!$B:$B,6,Data!$G:$G,"FCC") -> 68.255 | H19: =SUMIFS(Data!$K:$K,Data!$A:$A,2027,Data!$B:$B,7,Data!$G:$G,"FCC") -> 68 | I19: =SUMIFS(Data!$K:$K,Data!$A:$A,2027,Data!$B:$B,8,Data!$G:$G,"FCC") -> 19.72 | J19: =SUMIFS(Data!$K:$K,Data!$A:$A,2027,Data!$B:$B,9,Data!$G:$G,"FCC") -> 176.274 | K19: =SUMIFS(Data!$K:$K,Data!$A:$A,2027,Data!$B:$B,10,Data!$G:$G,"FCC") -> 189.624 | L19: =SUMIFS(Data!$K:$K,Data!$A:$A,2027,Data!$B:$B,11,Data!$G:$G,"FCC") -> 54.87 | M19: =SUMIFS(Data!$K:$K,Data!$A:$A,2027,Data!$B:$B,12,Data!$G:$G,"FCC") -> 0
A22: Hydrocracker
A23: Year | B23: Jan | C23: Feb | D23: Mar | E23: Apr | F23: May | G23: Jun | H23: Jul | I23: Aug | J23: Sep | K23: Oct | L23: Nov | M23: Dec
A24: 2023 | B24: =SUMIFS(Data!$K:$K,Data!$A:$A,2023,Data!$B:$B,1,Data!$G:$G,"Hydrocracker") -> 281.7 | C24: =SUMIFS(Data!$K:$K,Data!$A:$A,2023,Data!$B:$B,2,Data!$G:$G,"Hydrocracker") -> 420.495 | D24: =SUMIFS(Data!$K:$K,Data!$A:$A,2023,Data!$B:$B,3,Data!$G:$G,"Hydrocracker") -> 492.643 | E24: =SUMIFS(Data!$K:$K,Data!$A:$A,2023,Data!$B:$B,4,Data!$G:$G,"Hydrocracker") -> 424.371 | F24: =SUMIFS(Data!$K:$K,Data!$A:$A,2023,Data!$B:$B,5,Data!$G:$G,"Hydrocracker") -> 158.444 | G24: =SUMIFS(Data!$K:$K,Data!$A:$A,2023,Data!$B:$B,6,Data!$G:$G,"Hydrocracker") -> 11.7462 | H24: =SUMIFS(Data!$K:$K,Data!$A:$A,2023,Data!$B:$B,7,Data!$G:$G,"Hydrocracker") -> 40.6884 | I24: =SUMIFS(Data!$K:$K,Data!$A:$A,2023,Data!$B:$B,8,Data!$G:$G,"Hydrocracker") -> 64.313 | J24: =SUMIFS(Data!$K:$K,Data!$A:$A,2023,Data!$B:$B,9,Data!$G:$G,"Hydrocracker") -> 85.565 | K24: =SUMIFS(Data!$K:$K,Data!$A:$A,2023,Data!$B:$B,10,Data!$G:$G,"Hydrocracker") -> 169.43 | L24: =SUMIFS(Data!$K:$K,Data!$A:$A,2023,Data!$B:$B,11,Data!$G:$G,"Hydrocracker") -> 66.22 | M24: =SUMIFS(Data!$K:$K,Data!$A:$A,2023,Data!$B:$B,12,Data!$G:$G,"Hydrocracker") -> 60.28
A25: 2024 | B25: =SUMIFS(Data!$K:$K,Data!$A:$A,2024,Data!$B:$B,1,Data!$G:$G,"Hydrocracker") -> 248.172 | C25: =SUMIFS(Data!$K:$K,Data!$A:$A,2024,Data!$B:$B,2,Data!$G:$G,"Hydrocracker") -> 429.613 | D25: =SUMIFS(Data!$K:$K,Data!$A:$A,2024,Data!$B:$B,3,Data!$G:$G,"Hydrocracker") -> 305.265 | E25: =SUMIFS(Data!$K:$K,Data!$A:$A,2024,Data!$B:$B,4,Data!$G:$G,"Hydrocracker") -> 142.443 | F25: =SUMIFS(Data!$K:$K,Data!$A:$A,2024,Data!$B:$B,5,Data!$G:$G,"Hydrocracker") -> 153.69 | G25: =SUMIFS(Data!$K:$K,Data!$A:$A,2024,Data!$B:$B,6,Data!$G:$G,"Hydrocracker") -> 81.81 | H25: =SUMIFS(Data!$K:$K,Data!$A:$A,2024,Data!$B:$B,7,Data!$G:$G,"Hydrocracker") -> 44.115 | I25: =SUMIFS(Data!$K:$K,Data!$A:$A,2024,Data!$B:$B,8,Data!$G:$G,"Hydrocracker") -> 39.24 | J25: =SUMIFS(Data!$K:$K,Data!$A:$A,2024,Data!$B:$B,9,Data!$G:$G,"Hydrocracker") -> 212.99 | K25: =SUMIFS(Data!$K:$K,Data!$A:$A,2024,Data!$B:$B,10,Data!$G:$G,"Hydrocracker") -> 245.08 | L25: =SUMIFS(Data!$K:$K,Data!$A:$A,2024,Data!$B:$B,11,Data!$G:$G,"Hydrocracker") -> 91.11 | M25: =SUMIFS(Data!$K:$K,Data!$A:$A,2024,Data!$B:$B,12,Data!$G:$G,"Hydrocracker") -> 64.27
A26: 2025 | B26: =SUMIFS(Data!$K:$K,Data!$A:$A,2025,Data!$B:$B,1,Data!$G:$G,"Hydrocracker") -> 158.245 | C26: =SUMIFS(Data!$K:$K,Data!$A:$A,2025,Data!$B:$B,2,Data!$G:$G,"Hydrocracker") -> 255.94 | D26: =SUMIFS(Data!$K:$K,Data!$A:$A,2025,Data!$B:$B,3,Data!$G:$G,"Hydrocracker") -> 219.599 | E26: =SUMIFS(Data!$K:$K,Data!$A:$A,2025,Data!$B:$B,4,Data!$G:$G,"Hydrocracker") -> 244.39 | F26: =SUMIFS(Data!$K:$K,Data!$A:$A,2025,Data!$B:$B,5,Data!$G:$G,"Hydrocracker") -> 128.7 | G26: =SUMIFS(Data!$K:$K,Data!$A:$A,2025,Data!$B:$B,6,Data!$G:$G,"Hydrocracker") -> 149.126 | H26: =SUMIFS(Data!$K:$K,Data!$A:$A,2025,Data!$B:$B,7,Data!$G:$G,"Hydrocracker") -> 155.395 | I26: =SUMIFS(Data!$K:$K,Data!$A:$A,2025,Data!$B:$B,8,Data!$G:$G,"Hydrocracker") -> 201.5 | J26: =SUMIFS(Data!$K:$K,Data!$A:$A,2025,Data!$B:$B,9,Data!$G:$G,"Hydrocracker") -> 144.05 | K26: =SUMIFS(Data!$K:$K,Data!$A:$A,2025,Data!$B:$B,10,Data!$G:$G,"Hydrocracker") -> 242.68 | L26: =SUMIFS(Data!$K:$K,Data!$A:$A,2025,Data!$B:$B,11,Data!$G:$G,"Hydrocracker") -> 146.955 | M26: =SUMIFS(Data!$K:$K,Data!$A:$A,2025,Data!$B:$B,12,Data!$G:$G,"Hydrocracker") -> 84.29
A27: 2026 | B27: =SUMIFS(Data!$K:$K,Data!$A:$A,2026,Data!$B:$B,1,Data!$G:$G,"Hydrocracker") -> 50.92 | C27: =SUMIFS(Data!$K:$K,Data!$A:$A,2026,Data!$B:$B,2,Data!$G:$G,"Hydrocracker") -> 68.32 | D27: =SUMIFS(Data!$K:$K,Data!$A:$A,2026,Data!$B:$B,3,Data!$G:$G,"Hydrocracker") -> 145.776 | E27: =SUMIFS(Data!$K:$K,Data!$A:$A,2026,Data!$B:$B,4,Data!$G:$G,"Hydrocracker") -> 172.765 | F27: =SUMIFS(Data!$K:$K,Data!$A:$A,2026,Data!$B:$B,5,Data!$G:$G,"Hydrocracker") -> 92.77 | G27: =SUMIFS(Data!$K:$K,Data!$A:$A,2026,Data!$B:$B,6,Data!$G:$G,"Hydrocracker") -> 21.38 | H27: =SUMIFS(Data!$K:$K,Data!$A:$A,2026,Data!$B:$B,7,Data!$G:$G,"Hydrocracker") -> 30.24 | I27: =SUMIFS(Data!$K:$K,Data!$A:$A,2026,Data!$B:$B,8,Data!$G:$G,"Hydrocracker") -> 69.66 | J27: =SUMIFS(Data!$K:$K,Data!$A:$A,2026,Data!$B:$B,9,Data!$G:$G,"Hydrocracker") -> 149.15 | K27: =SUMIFS(Data!$K:$K,Data!$A:$A,2026,Data!$B:$B,10,Data!$G:$G,"Hydrocracker") -> 73.98 | L27: =SUMIFS(Data!$K:$K,Data!$A:$A,2026,Data!$B:$B,11,Data!$G:$G,"Hydrocracker") -> 17.296 | M27: =SUMIFS(Data!$K:$K,Data!$A:$A,2026,Data!$B:$B,12,Data!$G:$G,"Hydrocracker") -> 0
A28: 2027 | B28: =SUMIFS(Data!$K:$K,Data!$A:$A,2027,Data!$B:$B,1,Data!$G:$G,"Hydrocracker") -> 121.41 | C28: =SUMIFS(Data!$K:$K,Data!$A:$A,2027,Data!$B:$B,2,Data!$G:$G,"Hydrocracker") -> 141.67 | D28: =SUMIFS(Data!$K:$K,Data!$A:$A,2027,Data!$B:$B,3,Data!$G:$G,"Hydrocracker") -> 75.53 | E28: =SUMIFS(Data!$K:$K,Data!$A:$A,2027,Data!$B:$B,4,Data!$G:$G,"Hydrocracker") -> 39.15 | F28: =SUMIFS(Data!$K:$K,Data!$A:$A,2027,Data!$B:$B,5,Data!$G:$G,"Hydrocracker") -> 0 | G28: =SUMIFS(Data!$K:$K,Data!$A:$A,2027,Data!$B:$B,6,Data!$G:$G,"Hydrocracker") -> 0 | H28: =SUMIFS(Data!$K:$K,Data!$A:$A,2027,Data!$B:$B,7,Data!$G:$G,"Hydrocracker") -> 0 | I28: =SUMIFS(Data!$K:$K,Data!$A:$A,2027,Data!$B:$B,8,Data!$G:$G,"Hydrocracker") -> 0 | J28: =SUMIFS(Data!$K:$K,Data!$A:$A,2027,Data!$B:$B,9,Data!$G:$G,"Hydrocracker") -> 104.88 | K28: =SUMIFS(Data!$K:$K,Data!$A:$A,2027,Data!$B:$B,10,Data!$G:$G,"Hydrocracker") -> 63.94 | L28: =SUMIFS(Data!$K:$K,Data!$A:$A,2027,Data!$B:$B,11,Data!$G:$G,"Hydrocracker") -> 17.653 | M28: =SUMIFS(Data!$K:$K,Data!$A:$A,2027,Data!$B:$B,12,Data!$G:$G,"Hydrocracker") -> 0
A31: Reformer
A32: Year | B32: Jan | C32: Feb | D32: Mar | E32: Apr | F32: May | G32: Jun | H32: Jul | I32: Aug | J32: Sep | K32: Oct | L32: Nov | M32: Dec
A33: 2023 | B33: =SUMIFS(Data!$K:$K,Data!$A:$A,2023,Data!$B:$B,1,Data!$G:$G,"Reformer") -> 432.859 | C33: =SUMIFS(Data!$K:$K,Data!$A:$A,2023,Data!$B:$B,2,Data!$G:$G,"Reformer") -> 453.94 | D33: =SUMIFS(Data!$K:$K,Data!$A:$A,2023,Data!$B:$B,3,Data!$G:$G,"Reformer") -> 486.416 | E33: =SUMIFS(Data!$K:$K,Data!$A:$A,2023,Data!$B:$B,4,Data!$G:$G,"Reformer") -> 495.342 | F33: =SUMIFS(Data!$K:$K,Data!$A:$A,2023,Data!$B:$B,5,Data!$G:$G,"Reformer") -> 360.457 | G33: =SUMIFS(Data!$K:$K,Data!$A:$A,2023,Data!$B:$B,6,Data!$G:$G,"Reformer") -> 198.97 | H33: =SUMIFS(Data!$K:$K,Data!$A:$A,2023,Data!$B:$B,7,Data!$G:$G,"Reformer") -> 147.233 | I33: =SUMIFS(Data!$K:$K,Data!$A:$A,2023,Data!$B:$B,8,Data!$G:$G,"Reformer") -> 238.18 | J33: =SUMIFS(Data!$K:$K,Data!$A:$A,2023,Data!$B:$B,9,Data!$G:$G,"Reformer") -> 236.457 | K33: =SUMIFS(Data!$K:$K,Data!$A:$A,2023,Data!$B:$B,10,Data!$G:$G,"Reformer") -> 529.1175 | L33: =SUMIFS(Data!$K:$K,Data!$A:$A,2023,Data!$B:$B,11,Data!$G:$G,"Reformer") -> 371.958 | M33: =SUMIFS(Data!$K:$K,Data!$A:$A,2023,Data!$B:$B,12,Data!$G:$G,"Reformer") -> 67.175
A34: 2024 | B34: =SUMIFS(Data!$K:$K,Data!$A:$A,2024,Data!$B:$B,1,Data!$G:$G,"Reformer") -> 436.8612 | C34: =SUMIFS(Data!$K:$K,Data!$A:$A,2024,Data!$B:$B,2,Data!$G:$G,"Reformer") -> 843.04 | D34: =SUMIFS(Data!$K:$K,Data!$A:$A,2024,Data!$B:$B,3,Data!$G:$G,"Reformer") -> 439.2958 | E34: =SUMIFS(Data!$K:$K,Data!$A:$A,2024,Data!$B:$B,4,Data!$G:$G,"Reformer") -> 470.9954 | F34: =SUMIFS(Data!$K:$K,Data!$A:$A,2024,Data!$B:$B,5,Data!$G:$G,"Reformer") -> 285.8775 | G34: =SUMIFS(Data!$K:$K,Data!$A:$A,2024,Data!$B:$B,6,Data!$G:$G,"Reformer") -> 303.314 | H34: =SUMIFS(Data!$K:$K,Data!$A:$A,2024,Data!$B:$B,7,Data!$G:$G,"Reformer") -> 129.5725 | I34: =SUMIFS(Data!$K:$K,Data!$A:$A,2024,Data!$B:$B,8,Data!$G:$G,"Reformer") -> 149.935 | J34: =SUMIFS(Data!$K:$K,Data!$A:$A,2024,Data!$B:$B,9,Data!$G:$G,"Reformer") -> 319.02 | K34: =SUMIFS(Data!$K:$K,Data!$A:$A,2024,Data!$B:$B,10,Data!$G:$G,"Reformer") -> 587.828 | L34: =SUMIFS(Data!$K:$K,Data!$A:$A,2024,Data!$B:$B,11,Data!$G:$G,"Reformer") -> 228.1725 | M34: =SUMIFS(Data!$K:$K,Data!$A:$A,2024,Data!$B:$B,12,Data!$G:$G,"Reformer") -> 29.63
A35: 2025 | B35: =SUMIFS(Data!$K:$K,Data!$A:$A,2025,Data!$B:$B,1,Data!$G:$G,"Reformer") -> 160.3135 | C35: =SUMIFS(Data!$K:$K,Data!$A:$A,2025,Data!$B:$B,2,Data!$G:$G,"Reformer") -> 251.5285 | D35: =SUMIFS(Data!$K:$K,Data!$A:$A,2025,Data!$B:$B,3,Data!$G:$G,"Reformer") -> 301.84 | E35: =SUMIFS(Data!$K:$K,Data!$A:$A,2025,Data!$B:$B,4,Data!$G:$G,"Reformer") -> 443.2805 | F35: =SUMIFS(Data!$K:$K,Data!$A:$A,2025,Data!$B:$B,5,Data!$G:$G,"Reformer") -> 213.1394 | G35: =SUMIFS(Data!$K:$K,Data!$A:$A,2025,Data!$B:$B,6,Data!$G:$G,"Reformer") -> 90.0075 | H35: =SUMIFS(Data!$K:$K,Data!$A:$A,2025,Data!$B:$B,7,Data!$G:$G,"Reformer") -> 37.819 | I35: =SUMIFS(Data!$K:$K,Data!$A:$A,2025,Data!$B:$B,8,Data!$G:$G,"Reformer") -> 87.9 | J35: =SUMIFS(Data!$K:$K,Data!$A:$A,2025,Data!$B:$B,9,Data!$G:$G,"Reformer") -> 131.7565 | K35: =SUMIFS(Data!$K:$K,Data!$A:$A,2025,Data!$B:$B,10,Data!$G:$G,"Reformer") -> 379.416 | L35: =SUMIFS(Data!$K:$K,Data!$A:$A,2025,Data!$B:$B,11,Data!$G:$G,"Reformer") -> 227.8095 | M35: =SUMIFS(Data!$K:$K,Data!$A:$A,2025,Data!$B:$B,12,Data!$G:$G,"Reformer") -> 25.235
A36: 2026 | B36: =SUMIFS(Data!$K:$K,Data!$A:$A,2026,Data!$B:$B,1,Data!$G:$G,"Reformer") -> 95.4175 | C36: =SUMIFS(Data!$K:$K,Data!$A:$A,2026,Data!$B:$B,2,Data!$G:$G,"Reformer") -> 210.5685 | D36: =SUMIFS(Data!$K:$K,Data!$A:$A,2026,Data!$B:$B,3,Data!$G:$G,"Reformer") -> 159.17 | E36: =SUMIFS(Data!$K:$K,Data!$A:$A,2026,Data!$B:$B,4,Data!$G:$G,"Reformer") -> 154.283 | F36: =SUMIFS(Data!$K:$K,Data!$A:$A,2026,Data!$B:$B,5,Data!$G:$G,"Reformer") -> 157.769 | G36: =SUMIFS(Data!$K:$K,Data!$A:$A,2026,Data!$B:$B,6,Data!$G:$G,"Reformer") -> 130.51 | H36: =SUMIFS(Data!$K:$K,Data!$A:$A,2026,Data!$B:$B,7,Data!$G:$G,"Reformer") -> 98.204 | I36: =SUMIFS(Data!$K:$K,Data!$A:$A,2026,Data!$B:$B,8,Data!$G:$G,"Reformer") -> 44.905 | J36: =SUMIFS(Data!$K:$K,Data!$A:$A,2026,Data!$B:$B,9,Data!$G:$G,"Reformer") -> 137.55 | K36: =SUMIFS(Data!$K:$K,Data!$A:$A,2026,Data!$B:$B,10,Data!$G:$G,"Reformer") -> 166.385 | L36: =SUMIFS(Data!$K:$K,Data!$A:$A,2026,Data!$B:$B,11,Data!$G:$G,"Reformer") -> 68.1 | M36: =SUMIFS(Data!$K:$K,Data!$A:$A,2026,Data!$B:$B,12,Data!$G:$G,"Reformer") -> 0
A37: 2027 | B37: =SUMIFS(Data!$K:$K,Data!$A:$A,2027,Data!$B:$B,1,Data!$G:$G,"Reformer") -> 29.125 | C37: =SUMIFS(Data!$K:$K,Data!$A:$A,2027,Data!$B:$B,2,Data!$G:$G,"Reformer") -> 68.78 | D37: =SUMIFS(Data!$K:$K,Data!$A:$A,2027,Data!$B:$B,3,Data!$G:$G,"Reformer") -> 184.889 | E37: =SUMIFS(Data!$K:$K,Data!$A:$A,2027,Data!$B:$B,4,Data!$G:$G,"Reformer") -> 141.475 | F37: =SUMIFS(Data!$K:$K,Data!$A:$A,2027,Data!$B:$B,5,Data!$G:$G,"Reformer") -> 45.428 | G37: =SUMIFS(Data!$K:$K,Data!$A:$A,2027,Data!$B:$B,6,Data!$G:$G,"Reformer") -> 0.3 | H37: =SUMIFS(Data!$K:$K,Data!$A:$A,2027,Data!$B:$B,7,Data!$G:$G,"Reformer") -> 0 | I37: =SUMIFS(Data!$K:$K,Data!$A:$A,2027,Data!$B:$B,8,Data!$G:$G,"Reformer") -> 0 | J37: =SUMIFS(Data!$K:$K,Data!$A:$A,2027,Data!$B:$B,9,Data!$G:$G,"Reformer") -> 112.05 | K37: =SUMIFS(Data!$K:$K,Data!$A:$A,2027,Data!$B:$B,10,Data!$G:$G,"Reformer") -> 109.945 | L37: =SUMIFS(Data!$K:$K,Data!$A:$A,2027,Data!$B:$B,11,Data!$G:$G,"Reformer") -> 20.105 | M37: =SUMIFS(Data!$K:$K,Data!$A:$A,2027,Data!$B:$B,12,Data!$G:$G,"Reformer") -> 0
A40: Busiest-month concurrent offline (=MAX of the unit's months)
A41: Year | B41: Crude (CDU) | C41: FCC (cat cracker) | D41: Hydrocracker | E41: Reformer
A42: 2023 | B42: =MAX(B6:M6) -> 2180.255 | C42: =MAX(B15:M15) -> 1025.05 | D42: =MAX(B24:M24) -> 492.643 | E42: =MAX(B33:M33) -> 529.1175
A43: 2024 | B43: =MAX(B7:M7) -> 2142.5348 | C43: =MAX(B16:M16) -> 1054.9718 | D43: =MAX(B25:M25) -> 429.613 | E43: =MAX(B34:M34) -> 843.04
A44: 2025 | B44: =MAX(B8:M8) -> 1864.885 | C44: =MAX(B17:M17) -> 702.5715 | D44: =MAX(B26:M26) -> 255.94 | E44: =MAX(B35:M35) -> 443.2805
A45: 2026 | B45: =MAX(B9:M9) -> 1411.605 | C45: =MAX(B18:M18) -> 559.7625 | D45: =MAX(B27:M27) -> 172.765 | E45: =MAX(B36:M36) -> 210.5685
A46: 2027 | B46: =MAX(B10:M10) -> 1307.315 | C46: =MAX(B19:M19) -> 450.5215 | D46: =MAX(B28:M28) -> 141.67 | E46: =MAX(B37:M37) -> 184.889

Sheet Biggest
A1: Biggest 2027 Outages by Unit (nameplate kbd, from Data)
A2: Individual units, never added. PADD shows where the tonnage sits.
A4: Refinery | B4: Unit | C4: Class | D4: PADD | E4: kbd | F4: Window | G4: Type | H4: Status
A5: Joliet | B5: Crude | C5: CDU | D5: PADD 2 | E5: 250 | F5: Apr-May | G5: Planned | H5: confirmed
A6: Cherry Point | B6: Crude | C6: CDU | D6: PADD 5 | E6: 250 | F6: Mar | G6: Planned | H6: confirmed
A7: Norco | B7: DU-5 (Distilling Unit) (Sweet) | C7: CDU | D7: PADD 3 | E7: 240 | F7: Oct-Nov | G7: Planned | H7: indicative (H2)
A8: Richmond | B8: Crude | C8: CDU | D8: PADD 5 | E8: 240 | F8: Oct | G8: Planned | H8: indicative (H2)
A9: Lemont | B9: Crude Distillation 111 | C9: CDU | D9: PADD 2 | E9: 175 | F9: Apr-May | G9: Planned | H9: confirmed
A10: Martinez (PBF) | B10: DH Crude | C10: CDU | D10: PADD 5 | E10: 155 | F10: Jan-Mar | G10: Planned | H10: confirmed
A11: Garyville | B11: Crude 10 B-Train Sour/Sweet | C11: CDU | D11: PADD 3 | E11: 145 | F11: Sep-Nov | G11: Planned | H11: indicative (H2)
A12: Garyville | B12: Crude 10 A-Train/Sour | C12: CDU | D12: PADD 3 | E12: 145 | F12: Sep-Nov | G12: Planned | H12: indicative (H2)
A13: Garyville | B13: Crude 210 | C13: CDU | D13: PADD 3 | E13: 138 | F13: Jan-Feb | G13: Planned | H13: confirmed
A14: Baytown | B14: FCCU 3 (Fuels East) | C14: FCC | D14: PADD 3 | E14: 125 | F14: Feb-Apr | G14: Planned | H14: confirmed
A15: Beaumont | B15: FCCU | C15: FCC | D15: PADD 3 | E15: 120 | F15: Jan-Feb | G15: Planned | H15: confirmed
A16: Memphis | B16: Crude East | C16: CDU | D16: PADD 2 | E16: 110 | F16: Sep-Oct | G16: Planned | H16: indicative (H2)
... A34: Sweeny | B34: Heavy Oil Cracker 27-1 | C34: FCC | D34: PADD 3 | E34: 78 | F34: Jan-Mar | G34: Planned | H34: confirmed

Sheet H1 by Unit
A1: H1 (Jan-Jun) Planned Offline per Unit & Month = SUMIFS (type=Planned)
A2: Like-for-like cross-year read; 2027 is confirmed through H1. H1 avg = AVERAGE of the row.
A4: Crude (CDU)
A5: Year | B5: Jan | C5: Feb | D5: Mar | E5: Apr | F5: May | G5: Jun
A6: 2025 | B6: =SUMIFS(Data!$K:$K,Data!$A:$A,2025,Data!$B:$B,1,Data!$G:$G,"CDU",Data!$J:$J,"PLANNED") -> 757.195 | C6: =SUMIFS(Data!$K:$K,Data!$A:$A,2025,Data!$B:$B,2,Data!$G:$G,"CDU",Data!$J:$J,"PLANNED") -> 1058.991 | D6: =SUMIFS(Data!$K:$K,Data!$A:$A,2025,Data!$B:$B,3,Data!$G:$G,"CDU",Data!$J:$J,"PLANNED") -> 935.345 | E6: =SUMIFS(Data!$K:$K,Data!$A:$A,2025,Data!$B:$B,4,Data!$G:$G,"CDU",Data!$J:$J,"PLANNED") -> 1072.7975 | F6: =SUMIFS(Data!$K:$K,Data!$A:$A,2025,Data!$B:$B,5,Data!$G:$G,"CDU",Data!$J:$J,"PLANNED") -> 286.61 | G6: =SUMIFS(Data!$K:$K,Data!$A:$A,2025,Data!$B:$B,6,Data!$G:$G,"CDU",Data!$J:$J,"PLANNED") -> 118.65
A7: 2026 | B7: =SUMIFS(Data!$K:$K,Data!$A:$A,2026,Data!$B:$B,1,Data!$G:$G,"CDU",Data!$J:$J,"PLANNED") -> 284.73 | C7: =SUMIFS(Data!$K:$K,Data!$A:$A,2026,Data!$B:$B,2,Data!$G:$G,"CDU",Data!$J:$J,"PLANNED") -> 699.13 | D7: =SUMIFS(Data!$K:$K,Data!$A:$A,2026,Data!$B:$B,3,Data!$G:$G,"CDU",Data!$J:$J,"PLANNED") -> 638.401 | E7: =SUMIFS(Data!$K:$K,Data!$A:$A,2026,Data!$B:$B,4,Data!$G:$G,"CDU",Data!$J:$J,"PLANNED") -> 720.29 | F7: =SUMIFS(Data!$K:$K,Data!$A:$A,2026,Data!$B:$B,5,Data!$G:$G,"CDU",Data!$J:$J,"PLANNED") -> 516.362 | G7: =SUMIFS(Data!$K:$K,Data!$A:$A,2026,Data!$B:$B,6,Data!$G:$G,"CDU",Data!$J:$J,"PLANNED") -> 126.65
A8: 2027 | B8: =SUMIFS(Data!$K:$K,Data!$A:$A,2027,Data!$B:$B,1,Data!$G:$G,"CDU",Data!$J:$J,"PLANNED") -> 365.125 | C8: =SUMIFS(Data!$K:$K,Data!$A:$A,2027,Data!$B:$B,2,Data!$G:$G,"CDU",Data!$J:$J,"PLANNED") -> 683.258 | D8: =SUMIFS(Data!$K:$K,Data!$A:$A,2027,Data!$B:$B,3,Data!$G:$G,"CDU",Data!$J:$J,"PLANNED") -> 1062.14 | E8: =SUMIFS(Data!$K:$K,Data!$A:$A,2027,Data!$B:$B,4,Data!$G:$G,"CDU",Data!$J:$J,"PLANNED") -> 663.255 | F8: =SUMIFS(Data!$K:$K,Data!$A:$A,2027,Data!$B:$B,5,Data!$G:$G,"CDU",Data!$J:$J,"PLANNED") -> 320.192 | G8: =SUMIFS(Data!$K:$K,Data!$A:$A,2027,Data!$B:$B,6,Data!$G:$G,"CDU",Data!$J:$J,"PLANNED") -> 96
A11: FCC (cat cracker)
A12: Year | B12: Jan | C12: Feb | D12: Mar | E12: Apr | F12: May | G12: Jun
A13: 2025 | B13: =SUMIFS(Data!$K:$K,Data!$A:$A,2025,Data!$B:$B,1,Data!$G:$G,"FCC",Data!$J:$J,"PLANNED") -> 150.66 | C13: =SUMIFS(Data!$K:$K,Data!$A:$A,2025,Data!$B:$B,2,Data!$G:$G,"FCC",Data!$J:$J,"PLANNED") -> 209.57 | D13: =SUMIFS(Data!$K:$K,Data!$A:$A,2025,Data!$B:$B,3,Data!$G:$G,"FCC",Data!$J:$J,"PLANNED") -> 240.735 | E13: =SUMIFS(Data!$K:$K,Data!$A:$A,2025,Data!$B:$B,4,Data!$G:$G,"FCC",Data!$J:$J,"PLANNED") -> 331.825 | F13: =SUMIFS(Data!$K:$K,Data!$A:$A,2025,Data!$B:$B,5,Data!$G:$G,"FCC",Data!$J:$J,"PLANNED") -> 171.93 | G13: =SUMIFS(Data!$K:$K,Data!$A:$A,2025,Data!$B:$B,6,Data!$G:$G,"FCC",Data!$J:$J,"PLANNED") -> 20.97
A14: 2026 | B14: =SUMIFS(Data!$K:$K,Data!$A:$A,2026,Data!$B:$B,1,Data!$G:$G,"FCC",Data!$J:$J,"PLANNED") -> 168.25 | C14: =SUMIFS(Data!$K:$K,Data!$A:$A,2026,Data!$B:$B,2,Data!$G:$G,"FCC",Data!$J:$J,"PLANNED") -> 303.52 | D14: =SUMIFS(Data!$K:$K,Data!$A:$A,2026,Data!$B:$B,3,Data!$G:$G,"FCC",Data!$J:$J,"PLANNED") -> 199.243 | E14: =SUMIFS(Data!$K:$K,Data!$A:$A,2026,Data!$B:$B,4,Data!$G:$G,"FCC",Data!$J:$J,"PLANNED") -> 135.45 | F14: =SUMIFS(Data!$K:$K,Data!$A:$A,2026,Data!$B:$B,5,Data!$G:$G,"FCC",Data!$J:$J,"PLANNED") -> 32.069 | G14: =SUMIFS(Data!$K:$K,Data!$A:$A,2026,Data!$B:$B,6,Data!$G:$G,"FCC",Data!$J:$J,"PLANNED") -> 0
A15: 2027 | B15: =SUMIFS(Data!$K:$K,Data!$A:$A,2027,Data!$B:$B,1,Data!$G:$G,"FCC",Data!$J:$J,"PLANNED") -> 250.98 | C15: =SUMIFS(Data!$K:$K,Data!$A:$A,2027,Data!$B:$B,2,Data!$G:$G,"FCC",Data!$J:$J,"PLANNED") -> 450.5215 | D15: =SUMIFS(Data!$K:$K,Data!$A:$A,2027,Data!$B:$B,3,Data!$G:$G,"FCC",Data!$J:$J,"PLANNED") -> 447.892 | E15: =SUMIFS(Data!$K:$K,Data!$A:$A,2027,Data!$B:$B,4,Data!$G:$G,"FCC",Data!$J:$J,"PLANNED") -> 150.455 | F15: =SUMIFS(Data!$K:$K,Data!$A:$A,2027,Data!$B:$B,5,Data!$G:$G,"FCC",Data!$J:$J,"PLANNED") -> 23.3 | G15: =SUMIFS(Data!$K:$K,Data!$A:$A,2027,Data!$B:$B,6,Data!$G:$G,"FCC",Data!$J:$J,"PLANNED") -> 68.255
A18: Hydrocracker
A19: Year | B19: Jan | C19: Feb | D19: Mar | E19: Apr | F19: May | G19: Jun
A20: 2025 | B20: =SUMIFS(Data!$K:$K,Data!$A:$A,2025,Data!$B:$B,1,Data!$G:$G,"Hydrocracker",Data!$J:$J,"PLANNED") -> 84.48 | C20: =SUMIFS(Data!$K:$K,Data!$A:$A,2025,Data!$B:$B,2,Data!$G:$G,"Hydrocracker",Data!$J:$J,"PLANNED") -> 64.74 | D20: =SUMIFS(Data!$K:$K,Data!$A:$A,2025,Data!$B:$B,3,Data!$G:$G,"Hydrocracker",Data!$J:$J,"PLANNED") -> 9.669 | E20: =SUMIFS(Data!$K:$K,Data!$A:$A,2025,Data!$B:$B,4,Data!$G:$G,"Hydrocracker",Data!$J:$J,"PLANNED") -> 64.31 | F20: =SUMIFS(Data!$K:$K,Data!$A:$A,2025,Data!$B:$B,5,Data!$G:$G,"Hydrocracker",Data!$J:$J,"PLANNED") -> 45.6 | G20: =SUMIFS(Data!$K:$K,Data!$A:$A,2025,Data!$B:$B,6,Data!$G:$G,"Hydrocracker",Data!$J:$J,"PLANNED") -> 20.811
A21: 2026 | B21: =SUMIFS(Data!$K:$K,Data!$A:$A,2026,Data!$B:$B,1,Data!$G:$G,"Hydrocracker",Data!$J:$J,"PLANNED") -> 44.38 | C21: =SUMIFS(Data!$K:$K,Data!$A:$A,2026,Data!$B:$B,2,Data!$G:$G,"Hydrocracker",Data!$J:$J,"PLANNED") -> 49.32 | D21: =SUMIFS(Data!$K:$K,Data!$A:$A,2026,Data!$B:$B,3,Data!$G:$G,"Hydrocracker",Data!$J:$J,"PLANNED") -> 81.245 | E21: =SUMIFS(Data!$K:$K,Data!$A:$A,2026,Data!$B:$B,4,Data!$G:$G,"Hydrocracker",Data!$J:$J,"PLANNED") -> 106.25 | F21: =SUMIFS(Data!$K:$K,Data!$A:$A,2026,Data!$B:$B,5,Data!$G:$G,"Hydrocracker",Data!$J:$J,"PLANNED") -> 59.05 | G21: =SUMIFS(Data!$K:$K,Data!$A:$A,2026,Data!$B:$B,6,Data!$G:$G,"Hydrocracker",Data!$J:$J,"PLANNED") -> 6.5
A22: 2027 | B22: =SUMIFS(Data!$K:$K,Data!$A:$A,2027,Data!$B:$B,1,Data!$G:$G,"Hydrocracker",Data!$J:$J,"PLANNED") -> 121.41 | C22: =SUMIFS(Data!$K:$K,Data!$A:$A,2027,Data!$B:$B,2,Data!$G:$G,"Hydrocracker",Data!$J:$J,"PLANNED") -> 141.67 | D22: =SUMIFS(Data!$K:$K,Data!$A:$A,2027,Data!$B:$B,3,Data!$G:$G,"Hydrocracker",Data!$J:$J,"PLANNED") -> 75.53 | E22: =SUMIFS(Data!$K:$K,Data!$A:$A,2027,Data!$B:$B,4,Data!$G:$G,"Hydrocracker",Data!$J:$J,"PLANNED") -> 39.15 | F22: =SUMIFS(Data!$K:$K,Data!$A:$A,2027,Data!$B:$B,5,Data!$G:$G,"Hydrocracker",Data!$J:$J,"PLANNED") -> 0 | G22: =SUMIFS(Data!$K:$K,Data!$A:$A,2027,Data!$B:$B,6,Data!$G:$G,"Hydrocracker",Data!$J:$J,"PLANNED") -> 0
A25: Reformer
A26: Year | B26: Jan | C26: Feb | D26: Mar | E26: Apr | F26: May | G26: Jun
A27: 2025 | B27: =SUMIFS(Data!$K:$K,Data!$A:$A,2025,Data!$B:$B,1,Data!$G:$G,"Reformer",Data!$J:$J,"PLANNED") -> 78.466 | C27: =SUMIFS(Data!$K:$K,Data!$A:$A,2025,Data!$B:$B,2,Data!$G:$G,"Reformer",Data!$J:$J,"PLANNED") -> 145.75 | D27: =SUMIFS(Data!$K:$K,Data!$A:$A,2025,Data!$B:$B,3,Data!$G:$G,"Reformer",Data!$J:$J,"PLANNED") -> 160.432 | E27: =SUMIFS(Data!$K:$K,Data!$A:$A,2025,Data!$B:$B,4,Data!$G:$G,"Reformer",Data!$J:$J,"PLANNED") -> 202.358 | F27: =SUMIFS(Data!$K:$K,Data!$A:$A,2025,Data!$B:$B,5,Data!$G:$G,"Reformer",Data!$J:$J,"PLANNED") -> 113.691 | G27: =SUMIFS(Data!$K:$K,Data!$A:$A,2025,Data!$B:$B,6,Data!$G:$G,"Reformer",Data!$J:$J,"PLANNED") -> 43.806
A28: 2026 | B28: =SUMIFS(Data!$K:$K,Data!$A:$A,2026,Data!$B:$B,1,Data!$G:$G,"Reformer",Data!$J:$J,"PLANNED") -> 44.665 | C28: =SUMIFS(Data!$K:$K,Data!$A:$A,2026,Data!$B:$B,2,Data!$G:$G,"Reformer",Data!$J:$J,"PLANNED") -> 60.616 | D28: =SUMIFS(Data!$K:$K,Data!$A:$A,2026,Data!$B:$B,3,Data!$G:$G,"Reformer",Data!$J:$J,"PLANNED") -> 85.93 | E28: =SUMIFS(Data!$K:$K,Data!$A:$A,2026,Data!$B:$B,4,Data!$G:$G,"Reformer",Data!$J:$J,"PLANNED") -> 92.18 | F28: =SUMIFS(Data!$K:$K,Data!$A:$A,2026,Data!$B:$B,5,Data!$G:$G,"Reformer",Data!$J:$J,"PLANNED") -> 51.27 | G28: =SUMIFS(Data!$K:$K,Data!$A:$A,2026,Data!$B:$B,6,Data!$G:$G,"Reformer",Data!$J:$J,"PLANNED") -> 6.5
A29: 2027 | B29: =SUMIFS(Data!$K:$K,Data!$A:$A,2027,Data!$B:$B,1,Data!$G:$G,"Reformer",Data!$J:$J,"PLANNED") -> 29.125 | C29: =SUMIFS(Data!$K:$K,Data!$A:$A,2027,Data!$B:$B,2,Data!$G:$G,"Reformer",Data!$J:$J,"PLANNED") -> 68.78 | D29: =SUMIFS(Data!$K:$K,Data!$A:$A,2027,Data!$B:$B,3,Data!$G:$G,"Reformer",Data!$J:$J,"PLANNED") -> 184.889 | E29: =SUMIFS(Data!$K:$K,Data!$A:$A,2027,Data!$B:$B,4,Data!$G:$G,"Reformer",Data!$J:$J,"PLANNED") -> 141.475 | F29: =SUMIFS(Data!$K:$K,Data!$A:$A,2027,Data!$B:$B,5,Data!$G:$G,"Reformer",Data!$J:$J,"PLANNED") -> 45.428 | G29: =SUMIFS(Data!$K:$K,Data!$A:$A,2027,Data!$B:$B,6,Data!$G:$G,"Reformer",Data!$J:$J,"PLANNED") -> 0.3
A32: H1 average offline (=AVERAGE Jan:Jun)
A33: Unit | B33: 2025 | C33: 2026 | D33: 2027
A34: Crude (CDU) | B34: =AVERAGE(B6:G6) -> 704.93142 | C34: =AVERAGE(B7:G7) -> 497.59383 | D34: =AVERAGE(B8:G8) -> 531.66167
A35: FCC (cat cracker) | B35: =AVERAGE(B13:G13) -> 187.615 | C35: =AVERAGE(B14:G14) -> 139.75533 | D35: =AVERAGE(B15:G15) -> 231.90058
A36: Hydrocracker | B36: =AVERAGE(B20:G20) -> 48.268333 | C36: =AVERAGE(B21:G21) -> 57.790833 | D36: =AVERAGE(B22:G22) -> 62.96
A37: Reformer | B37: =AVERAGE(B27:G27) -> 124.08383 | C37: =AVERAGE(B28:G28) -> 56.860167 | D37: =AVERAGE(B29:G29) -> 78.332833

Sheet PADD by Unit
A1: Outages by PADD by Unit: full history with MoM% and YoY% = SUMIFS over Data
A2: CDU and FCC offline by PADD and month, 2023-2027: level, month-over-month % and year-over-year %.
A4: Unit | B4: PADD | C4: Year | D4: Mon | E4: Period | F4: kbd | G4: MoM % | H4: YoY %
A5: CDU | B5: P1 | C5: 2023 | D5: 1 | E5: Jan 23 | F5: =SUMIFS(Data!$K:$K,Data!$A:$A,2023,Data!$B:$B,1,Data!$G:$G,"CDU",Data!$F:$F,"PADD 1") -> 63.26
A6: CDU | B6: P1 | C6: 2023 | D6: 2 | E6: Feb 23 | F6: =SUMIFS(Data!$K:$K,Data!$A:$A,2023,Data!$B:$B,2,Data!$G:$G,"CDU",Data!$F:$F,"PADD 1") -> 129 | G6: =IFERROR(F6/F5-1,"") -> 1.0392033
A7: CDU | B7: P1 | C7: 2023 | D7: 3 | E7: Mar 23 | F7: =SUMIFS(Data!$K:$K,Data!$A:$A,2023,Data!$B:$B,3,Data!$G:$G,"CDU",Data!$F:$F,"PADD 1") -> 189.71 | G7: =IFERROR(F7/F6-1,"") -> 0.47062016
A8: CDU | B8: P1 | C8: 2023 | D8: 4 | E8: Apr 23 | F8: =SUMIFS(Data!$K:$K,Data!$A:$A,2023,Data!$B:$B,4,Data!$G:$G,"CDU",Data!$F:$F,"PADD 1") -> 22.31 | G8: =IFERROR(F8/F7-1,"") -> -0.88239945
A9: CDU | B9: P1 | C9: 2023 | D9: 5 | E9: May 23 | F9: =SUMIFS(Data!$K:$K,Data!$A:$A,2023,Data!$B:$B,5,Data!$G:$G,"CDU",Data!$F:$F,"PADD 1") -> 0 | G9: =IFERROR(F9/F8-1,"") -> -1
A10: CDU | B10: P1 | C10: 2023 | D10: 6 | E10: Jun 23 | F10: =SUMIFS(Data!$K:$K,Data!$A:$A,2023,Data!$B:$B,6,Data!$G:$G,"CDU",Data!$F:$F,"PADD 1") -> 99.5225 | G10: =IFERROR(F10/F9-1,"")
A11: CDU | B11: P1 | C11: 2023 | D11: 7 | E11: Jul 23 | F11: =SUMIFS(Data!$K:$K,Data!$A:$A,2023,Data!$B:$B,7,Data!$G:$G,"CDU",Data!$F:$F,"PADD 1") -> 87.89 | G11: =IFERROR(F11/F10-1,"") -> -0.11688312
A12: CDU | B12: P1 | C12: 2023 | D12: 8 | E12: Aug 23 | F12: =SUMIFS(Data!$K:$K,Data!$A:$A,2023,Data!$B:$B,8,Data!$G:$G,"CDU",Data!$F:$F,"PADD 1") -> 0 | G12: =IFERROR(F12/F11-1,"") -> -1
A13: CDU | B13: P1 | C13: 2023 | D13: 9 | E13: Sep 23 | F13: =SUMIFS(Data!$K:$K,Data!$A:$A,2023,Data!$B:$B,9,Data!$G:$G,"CDU",Data!$F:$F,"PADD 1") -> 100.725 | G13: =IFERROR(F13/F12-1,"")
A14: CDU | B14: P1 | C14: 2023 | D14: 10 | E14: Oct 23 | F14: =SUMIFS(Data!$K:$K,Data!$A:$A,2023,Data!$B:$B,10,Data!$G:$G,"CDU",Data!$F:$F,"PADD 1") -> 185 | G14: =IFERROR(F14/F13-1,"") -> 0.83668404
A15: CDU | B15: P1 | C15: 2023 | D15: 11 | E15: Nov 23 | F15: =SUMIFS(Data!$K:$K,Data!$A:$A,2023,Data!$B:$B,11,Data!$G:$G,"CDU",Data!$F:$F,"PADD 1") -> 55.5 | G15: =IFERROR(F15/F14-1,"") -> -0.7
A16: CDU | B16: P1 | C16: 2023 | D16: 12 | E16: Dec 23 | F16: =SUMIFS(Data!$K:$K,Data!$A:$A,2023,Data!$B:$B,12,Data!$G:$G,"CDU",Data!$F:$F,"PADD 1") -> 25.85 | G16: =IFERROR(F16/F15-1,"") -> -0.53423423
A17: CDU | B17: P1 | C17: 2024 | D17: 1 | E17: Jan 24 | F17: =SUMIFS(Data!$K:$K,Data!$A:$A,2024,Data!$B:$B,1,Data!$G:$G,"CDU",Data!$F:$F,"PADD 1") -> 39.56 | G17: =IFERROR(F17/F16-1,"") -> 0.5303675 | H17: =IFERROR(F17/F5-1,"") -> -0.37464433
A18: CDU | B18: P1 | C18: 2024 | D18: 2 | E18: Feb 24 | F18: =SUMIFS(Data!$K:$K,Data!$A:$A,2024,Data!$B:$B,2,Data!$G:$G,"CDU",Data!$F:$F,"PADD 1") -> 0 | G18: =IFERROR(F18/F17-1,"") -> -1 | H18: =IFERROR(F18/F6-1,"") -> -1
A19: CDU | B19: P1 | C19: 2024 | D19: 3 | E19: Mar 24 | F19: =SUMIFS(Data!$K:$K,Data!$A:$A,2024,Data!$B:$B,3,Data!$G:$G,"CDU",Data!$F:$F,"PADD 1") -> 60.55 | G19: =IFERROR(F19/F18-1,"") | H19: =IFERROR(F19/F7-1,"") -> -0.68082863
A20: CDU | B20: P1 | C20: 2024 | D20: 4 | E20: Apr 24 | F20: =SUMIFS(Data!$K:$K,Data!$A:$A,2024,Data!$B:$B,4,Data!$G:$G,"CDU",Data!$F:$F,"PADD 1") -> 47.775 | G20: =IFERROR(F20/F19-1,"") -> -0.21098266 | H20: =IFERROR(F20/F8-1,"") -> 1.1414164
A21: CDU | B21: P1 | C21: 2024 | D21: 5 | E21: May 24 | F21: =SUMIFS(Data!$K:$K,Data!$A:$A,2024,Data!$B:$B,5,Data!$G:$G,"CDU",Data!$F:$F,"PADD 1") -> 0 | G21: =IFERROR(F21/F20-1,"") -> -1 | H21: =IFERROR(F21/F9-1,"")
A22: CDU | B22: P1 | C22: 2024 | D22: 6 | E22: Jun 24 | F22: =SUMIFS(Data!$K:$K,Data!$A:$A,2024,Data!$B:$B,6,Data!$G:$G,"CDU",Data!$F:$F,"PADD 1") -> 0 | G22: =IFERROR(F22/F21-1,"") | H22: =IFERROR(F22/F10-1,"") -> -1
A23: CDU | B23: P1 | C23: 2024 | D23: 7 | E23: Jul 24 | F23: =SUMIFS(Data!$K:$K,Data!$A:$A,2024,Data!$B:$B,7,Data!$G:$G,"CDU",Data!$F:$F,"PADD 1") -> 11.25 | G23: =IFERROR(F23/F22-1,"") | H23: =IFERROR(F23/F11-1,"") -> -0.87199909
A24: CDU | B24: P1 | C24: 2024 | D24: 8 | E24: Aug 24 | F24: =SUMIFS(Data!$K:$K,Data!$A:$A,2024,Data!$B:$B,8,Data!$G:$G,"CDU",Data!$F:$F,"PADD 1") -> 0 | G24: =IFERROR(F24/F23-1,"") -> -1 | H24: =IFERROR(F24/F12-1,"")
A25: CDU | B25: P1 | C25: 2024 | D25: 9 | E25: Sep 24 | F25: =SUMIFS(Data!$K:$K,Data!$A:$A,2024,Data!$B:$B,9,Data!$G:$G,"CDU",Data!$F:$F,"PADD 1") -> 0 | G25: =IFERROR(F25/F24-1,"") | H25: =IFERROR(F25/F13-1,"") -> -1
A26: CDU | B26: P1 | C26: 2024 | D26: 10 | E26: Oct 24 | F26: =SUMIFS(Data!$K:$K,Data!$A:$A,2024,Data!$B:$B,10,Data!$G:$G,"CDU",Data!$F:$F,"PADD 1") -> 73.08 | G26: =IFERROR(F26/F25-1,"") | H26: =IFERROR(F26/F14-1,"") -> -0.60497297
A27: CDU | B27: P1 | C27: 2024 | D27: 11 | E27: Nov 24 | F27: =SUMIFS(Data!$K:$K,Data!$A:$A,2024,Data!$B:$B,11,Data!$G:$G,"CDU",Data!$F:$F,"PADD 1") -> 116.9 | G27: =IFERROR(F27/F26-1,"") -> 0.59961686 | H27: =IFERROR(F27/F15-1,"") -> 1.1063063
A28: CDU | B28: P1 | C28: 2024 | D28: 12 | E28: Dec 24 | F28: =SUMIFS(Data!$K:$K,Data!$A:$A,2024,Data!$B:$B,12,Data!$G:$G,"CDU",Data!$F:$F,"PADD 1") -> 159.85 | G28: =IFERROR(F28/F27-1,"") -> 0.36740804 | H28: =IFERROR(F28/F16-1,"") -> 5.1837524
A29: CDU | B29: P1 | C29: 2025 | D29: 1 | E29: Jan 25 | F29: =SUMIFS(Data!$K:$K,Data!$A:$A,2025,Data!$B:$B,1,Data!$G:$G,"CDU",Data!$F:$F,"PADD 1") -> 170.12 | G29: =IFERROR(F29/F28-1,"") -> 0.064247732 | H29: =IFERROR(F29/F17-1,"") -> 3.3003033
A30: CDU | B30: P1 | C30: 2025 | D30: 2 | E30: Feb 25 | F30: =SUMIFS(Data!$K:$K,Data!$A:$A,2025,Data!$B:$B,2,Data!$G:$G,"CDU",Data!$F:$F,"PADD 1") -> 306.59 | G30: =IFERROR(F30/F29-1,"") -> 0.80219845 | H30: =IFERROR(F30/F18-1,"")
A31: CDU | B31: P1 | C31: 2025 | D31: 3 | E31: Mar 25 | F31: =SUMIFS(Data!$K:$K,Data!$A:$A,2025,Data!$B:$B,3,Data!$G:$G,"CDU",Data!$F:$F,"PADD 1") -> 426.19 | G31: =IFERROR(F31/F30-1,"") -> 0.39009752 | H31: =IFERROR(F31/F19-1,"") -> 6.0386457
A32: CDU | B32: P1 | C32: 2025 | D32: 4 | E32: Apr 25 | F32: =SUMIFS(Data!$K:$K,Data!$A:$A,2025,Data!$B:$B,4,Data!$G:$G,"CDU",Data!$F:$F,"PADD 1") -> 128.3961 | G32: =IFERROR(F32/F31-1,"") -> -0.69873507 | H32: =IFERROR(F32/F20-1,"") -> 1.6875165
A33: CDU | B33: P1 | C33: 2025 | D33: 5 | E33: May 25 | F33: =SUMIFS(Data!$K:$K,Data!$A:$A,2025,Data!$B:$B,5,Data!$G:$G,"CDU",Data!$F:$F,"PADD 1") -> 87.63 | G33: =IFERROR(F33/F32-1,"") -> -0.31750263 | H33: =IFERROR(F33/F21-1,"")
A34: CDU | B34: P1 | C34: 2025 | D34: 6 | E34: Jun 25 | F34: =SUMIFS(Data!$K:$K,Data!$A:$A,2025,Data!$B:$B,6,Data!$G:$G,"CDU",Data!$F:$F,"PADD 1") -> 70.0371 | G34: =IFERROR(F34/F33-1,"") -> -0.20076344 | H34: =IFERROR(F34/F22-1,"")
A35: CDU | B35: P1 | C35: 2025 | D35: 7 | E35: Jul 25 | F35: =SUMIFS(Data!$K:$K,Data!$A:$A,2025,Data!$B:$B,7,Data!$G:$G,"CDU",Data!$F:$F,"PADD 1") -> 78.435 | G35: =IFERROR(F35/F34-1,"") -> 0.11990645 | H35: =IFERROR(F35/F23-1,"") -> 5.972
A36: CDU | B36: P1 | C36: 2025 | D36: 8 | E36: Aug 25 | F36: =SUMIFS(Data!$K:$K,Data!$A:$A,2025,Data!$B:$B,8,Data!$G:$G,"CDU",Data!$F:$F,"PADD 1") -> 0 | G36: =IFERROR(F36/F35-1,"") -> -1 | H36: =IFERROR(F36/F24-1,"")
A37: CDU | B37: P1 | C37: 2025 | D37: 9 | E37: Sep 25 | F37: =SUMIFS(Data!$K:$K,Data!$A:$A,2025,Data!$B:$B,9,Data!$G:$G,"CDU",Data!$F:$F,"PADD 1") -> 0 | G37: =IFERROR(F37/F36-1,"") | H37: =IFERROR(F37/F25-1,"")
A38: CDU | B38: P1 | C38: 2025 | D38: 10 | E38: Oct 25 | F38: =SUMIFS(Data!$K:$K,Data!$A:$A,2025,Data!$B:$B,10,Data!$G:$G,"CDU",Data!$F:$F,"PADD 1") -> 0 | G38: =IFERROR(F38/F37-1,"") | H38: =IFERROR(F38/F26-1,"") -> -1
A39: CDU | B39: P1 | C39: 2025 | D39: 11 | E39: Nov 25 | F39: =SUMIFS(Data!$K:$K,Data!$A:$A,2025,Data!$B:$B,11,Data!$G:$G,"CDU",Data!$F:$F,"PADD 1") -> 0 | G39: =IFERROR(F39/F38-1,"") | H39: =IFERROR(F39/F27-1,"") -> -1
A40: CDU | B40: P1 | C40: 2025 | D40: 12 | E40: Dec 25 | F40: =SUMIFS(Data!$K:$K,Data!$A:$A,2025,Data!$B:$B,12,Data!$G:$G,"CDU",Data!$F:$F,"PADD 1") -> 0 | G40: =IFERROR(F40/F39-1,"") | H40: =IFERROR(F40/F28-1,"") -> -1
A41: CDU | B41: P1 | C41: 2026 | D41: 1 | E41: Jan 26 | F41: =SUMIFS(Data!$K:$K,Data!$A:$A,2026,Data!$B:$B,1,Data!$G:$G,"CDU",Data!$F:$F,"PADD 1") -> 17.6 | G41: =IFERROR(F41/F40-1,"") | H41: =IFERROR(F41/F29-1,"") -> -0.89654362
A42: CDU | B42: P1 | C42: 2026 | D42: 2 | E42: Feb 26 | F42: =SUMIFS(Data!$K:$K,Data!$A:$A,2026,Data!$B:$B,2,Data!$G:$G,"CDU",Data!$F:$F,"PADD 1") -> 12.1 | G42: =IFERROR(F42/F41-1,"") -> -0.3125 | H42: =IFERROR(F42/F30-1,"") -> -0.96053361
A43: CDU | B43: P1 | C43: 2026 | D43: 3 | E43: Mar 26 | F43: =SUMIFS(Data!$K:$K,Data!$A:$A,2026,Data!$B:$B,3,Data!$G:$G,"CDU",Data!$F:$F,"PADD 1") -> 21.84 | G43: =IFERROR(F43/F42-1,"") -> 0.80495868 | H43: =IFERROR(F43/F31-1,"") -> -0.94875525
A44: CDU | B44: P1 | C44: 2026 | D44: 4 | E44: Apr 26 | F44: =SUMIFS(Data!$K:$K,Data!$A:$A,2026,Data!$B:$B,4,Data!$G:$G,"CDU",Data!$F:$F,"PADD 1") -> 0 | G44: =IFERROR(F44/F43-1,"") -> -1 | H44: =IFERROR(F44/F32-1,"") -> -1
A45: CDU | B45: P1 | C45: 2026 | D45: 5 | E45: May 26 | F45: =SUMIFS(Data!$K:$K,Data!$A:$A,2026,Data!$B:$B,5,Data!$G:$G,"CDU",Data!$F:$F,"PADD 1") -> 11 | G45: =IFERROR(F45/F44-1,"") | H45: =IFERROR(F45/F33-1,"") -> -0.87447221
A46: CDU | B46: P1 | C46: 2026 | D46: 6 | E46: Jun 26 | F46: =SUMIFS(Data!$K:$K,Data!$A:$A,2026,Data!$B:$B,6,Data!$G:$G,"CDU",Data!$F:$F,"PADD 1") -> 100.88 | G46: =IFERROR(F46/F45-1,"") -> 8.1709091 | H46: =IFERROR(F46/F34-1,"") -> 0.44037946
A47: CDU | B47: P1 | C47: 2026 | D47: 7 | E47: Jul 26 | F47: =SUMIFS(Data!$K:$K,Data!$A:$A,2026,Data!$B:$B,7,Data!$G:$G,"CDU",Data!$F:$F,"PADD 1") -> 208 | G47: =IFERROR(F47/F46-1,"") -> 1.0618557 | H47: =IFERROR(F47/F35-1,"") -> 1.6518774
A48: CDU | B48: P1 | C48: 2026 | D48: 8 | E48: Aug 26 | F48: =SUMIFS(Data!$K:$K,Data!$A:$A,2026,Data!$B:$B,8,Data!$G:$G,"CDU",Data!$F:$F,"PADD 1") -> 93.6 | G48: =IFERROR(F48/F47-1,"") -> -0.55 | H48: =IFERROR(F48/F36-1,"")
A49: CDU | B49: P1 | C49: 2026 | D49: 9 | E49: Sep 26 | F49: =SUMIFS(Data!$K:$K,Data!$A:$A,2026,Data!$B:$B,9,Data!$G:$G,"CDU",Data!$F:$F,"PADD 1") -> 51.7 | G49: =IFERROR(F49/F48-1,"") -> -0.44764957 | H49: =IFERROR(F49/F37-1,"")
A50: CDU | B50: P1 | C50: 2026 | D50: 10 | E50: Oct 26 | F50: =SUMIFS(Data!$K:$K,Data!$A:$A,2026,Data!$B:$B,10,Data!$G:$G,"CDU",Data!$F:$F,"PADD 1") -> 74.8 | G50: =IFERROR(F50/F49-1,"") -> 0.44680851 | H50: =IFERROR(F50/F38-1,"")
A51: CDU | B51: P1 | C51: 2026 | D51: 11 | E51: Nov 26 | F51: =SUMIFS(Data!$K:$K,Data!$A:$A,2026,Data!$B:$B,11,Data!$G:$G,"CDU",Data!$F:$F,"PADD 1") -> 0 | G51: =IFERROR(F51/F50-1,"") -> -1 | H51: =IFERROR(F51/F39-1,"")
A52: CDU | B52: P1 | C52: 2026 | D52: 12 | E52: Dec 26 | F52: =SUMIFS(Data!$K:$K,Data!$A:$A,2026,Data!$B:$B,12,Data!$G:$G,"CDU",Data!$F:$F,"PADD 1") -> 0 | G52: =IFERROR(F52/F51-1,"") | H52: =IFERROR(F52/F40-1,"")
A53: CDU | B53: P1 | C53: 2027 | D53: 1 | E53: Jan 27 | F53: =SUMIFS(Data!$K:$K,Data!$A:$A,2027,Data!$B:$B,1,Data!$G:$G,"CDU",Data!$F:$F,"PADD 1") -> 0 | G53: =IFERROR(F53/F52-1,"") | H53: =IFERROR(F53/F41-1,"") -> -1
A54: CDU | B54: P1 | C54: 2027 | D54: 2 | E54: Feb 27 | F54: =SUMIFS(Data!$K:$K,Data!$A:$A,2027,Data!$B:$B,2,Data!$G:$G,"CDU",Data!$F:$F,"PADD 1") -> 0 | G54: =IFERROR(F54/F53-1,"") | H54: =IFERROR(F54/F42-1,"") -> -1
A55: CDU | B55: P1 | C55: 2027 | D55: 3 | E55: Mar 27 | F55: =SUMIFS(Data!$K:$K,Data!$A:$A,2027,Data!$B:$B,3,Data!$G:$G,"CDU",Data!$F:$F,"PADD 1") -> 108.75 | G55: =IFERROR(F55/F54-1,"") | H55: =IFERROR(F55/F43-1,"") -> 3.9793956
A56: CDU | B56: P1 | C56: 2027 | D56: 4 | E56: Apr 27 | F56: =SUMIFS(Data!$K:$K,Data!$A:$A,2027,Data!$B:$B,4,Data!$G:$G,"CDU",Data!$F:$F,"PADD 1") -> 44.95 | G56: =IFERROR(F56/F55-1,"") -> -0.58666667 | H56: =IFERROR(F56/F44-1,"")
A57: CDU | B57: P1 | C57: 2027 | D57: 5 | E57: May 27 | F57: =SUMIFS(Data!$K:$K,Data!$A:$A,2027,Data!$B:$B,5,Data!$G:$G,"CDU",Data!$F:$F,"PADD 1") -> 0 | G57: =IFERROR(F57/F56-1,"") -> -1 | H57: =IFERROR(F57/F45-1,"") -> -1
A58: CDU | B58: P1 | C58: 2027 | D58: 6 | E58: Jun 27 | F58: =SUMIFS(Data!$K:$K,Data!$A:$A,2027,Data!$B:$B,6,Data!$G:$G,"CDU",Data!$F:$F,"PADD 1") -> 0 | G58: =IFERROR(F58/F57-1,"") | H58: =IFERROR(F58/F46-1,"") -> -1
A59: CDU | B59: P1 | C59: 2027 | D59: 7 | E59: Jul 27 | F59: =SUMIFS(Data!$K:$K,Data!$A:$A,2027,Data!$B:$B,7,Data!$G:$G,"CDU",Data!$F:$F,"PADD 1") -> 0 | G59: =IFERROR(F59/F58-1,"") | H59: =IFERROR(F59/F47-1,"") -> -1
A60: CDU | B60: P1 | C60: 2027 | D60: 8 | E60: Aug 27 | F60: =SUMIFS(Data!$K:$K,Data!$A:$A,2027,Data!$B:$B,8,Data!$G:$G,"CDU",Data!$F:$F,"PADD 1") -> 0 | G60: =IFERROR(F60/F59-1,"") | H60: =IFERROR(F60/F48-1,"") -> -1
A61: CDU | B61: P1 | C61: 2027 | D61: 9 | E61: Sep 27 | F61: =SUMIFS(Data!$K:$K,Data!$A:$A,2027,Data!$B:$B,9,Data!$G:$G,"CDU",Data!$F:$F,"PADD 1") -> 0 | G61: =IFERROR(F61/F60-1,"") | H61: =IFERROR(F61/F49-1,"") -> -1
A62: CDU | B62: P1 | C62: 2027 | D62: 10 | E62: Oct 27 | F62: =SUMIFS(Data!$K:$K,Data!$A:$A,2027,Data!$B:$B,10,Data!$G:$G,"CDU",Data!$F:$F,"PADD 1") -> 0 | G62: =IFERROR(F62/F61-1,"") | H62: =IFERROR(F62/F50-1,"") -> -1
A63: CDU | B63: P1 | C63: 2027 | D63: 11 | E63: Nov 27 | F63: =SUMIFS(Data!$K:$K,Data!$A:$A,2027,Data!$B:$B,11,Data!$G:$G,"CDU",Data!$F:$F,"PADD 1") -> 0 | G63: =IFERROR(F63/F62-1,"") | H63: =IFERROR(F63/F51-1,"")
A64: CDU | B64: P1 | C64: 2027 | D64: 12 | E64: Dec 27 | F64: =SUMIFS(Data!$K:$K,Data!$A:$A,2027,Data!$B:$B,12,Data!$G:$G,"CDU",Data!$F:$F,"PADD 1") -> 0 | G64: =IFERROR(F64/F63-1,"") | H64: =IFERROR(F64/F52-1,"")
A65: CDU | B65: P2 | C65: 2023 | D65: 1 | E65: Jan 23 | F65: =SUMIFS(Data!$K:$K,Data!$A:$A,2023,Data!$B:$B,1,Data!$G:$G,"CDU",Data!$F:$F,"PADD 2") -> 380.68
A66: CDU | B66: P2 | C66: 2023 | D66: 2 | E66: Feb 23 | F66: =SUMIFS(Data!$K:$K,Data!$A:$A,2023,Data!$B:$B,2,Data!$G:$G,"CDU",Data!$F:$F,"PADD 2") -> 366.59 | G66: =IFERROR(F66/F65-1,"") -> -0.037012714
A67: CDU | B67: P2 | C67: 2023 | D67: 3 | E67: Mar 23 | F67: =SUMIFS(Data!$K:$K,Data!$A:$A,2023,Data!$B:$B,3,Data!$G:$G,"CDU",Data!$F:$F,"PADD 2") -> 633.205 | G67: =IFERROR(F67/F66-1,"") -> 0.72728389
A68: CDU | B68: P2 | C68: 2023 | D68: 4 | E68: Apr 23 | F68: =SUMIFS(Data!$K:$K,Data!$A:$A,2023,Data!$B:$B,4,Data!$G:$G,"CDU",Data!$F:$F,"PADD 2") -> 738.695 | G68: =IFERROR(F68/F67-1,"") -> 0.16659692
A69: CDU | B69: P2 | C69: 2023 | D69: 5 | E69: May 23 | F69: =SUMIFS(Data!$K:$K,Data!$A:$A,2023,Data!$B:$B,5,Data!$G:$G,"CDU",Data!$F:$F,"PADD 2") -> 373.07 | G69: =IFERROR(F69/F68-1,"") -> -0.49496071
A70: CDU | B70: P2 | C70: 2023 | D70: 6 | E70: Jun 23 | F70: =SUMIFS(Data!$K:$K,Data!$A:$A,2023,Data!$B:$B,6,Data!$G:$G,"CDU",Data!$F:$F,"PADD 2") -> 173.55 | G70: =IFERROR(F70/F69-1,"") -> -0.5348058
A71: CDU | B71: P2 | C71: 2023 | D71: 7 | E71: Jul 23 | F71: =SUMIFS(Data!$K:$K,Data!$A:$A,2023,Data!$B:$B,7,Data!$G:$G,"CDU",Data!$F:$F,"PADD 2") -> 168.67 | G71: =IFERROR(F71/F70-1,"") -> -0.028118698
A72: CDU | B72: P2 | C72: 2023 | D72: 8 | E72: Aug 23 | F72: =SUMIFS(Data!$K:$K,Data!$A:$A,2023,Data!$B:$B,8,Data!$G:$G,"CDU",Data!$F:$F,"PADD 2") -> 60.55 | G72: =IFERROR(F72/F71-1,"") -> -0.641015
A73: CDU | B73: P2 | C73: 2023 | D73: 9 | E73: Sep 23 | F73: =SUMIFS(Data!$K:$K,Data!$A:$A,2023,Data!$B:$B,9,Data!$G:$G,"CDU",Data!$F:$F,"PADD 2") -> 369.5875 | G73: =IFERROR(F73/F72-1,"") -> 5.1038398
A74: CDU | B74: P2 | C74: 2023 | D74: 10 | E74: Oct 23 | F74: =SUMIFS(Data!$K:$K,Data!$A:$A,2023,Data!$B:$B,10,Data!$G:$G,"CDU",Data!$F:$F,"PADD 2") -> 495.6475 | G74: =IFERROR(F74/F73-1,"") -> 0.34108296
A75: CDU | B75: P2 | C75: 2023 | D75: 11 | E75: Nov 23 | F75: =SUMIFS(Data!$K:$K,Data!$A:$A,2023,Data!$B:$B,11,Data!$G:$G,"CDU",Data!$F:$F,"PADD 2") -> 162.85 | G75: =IFERROR(F75/F74-1,"") -> -0.67143988
A76: CDU | B76: P2 | C76: 2023 | D76: 12 | E76: Dec 23 | F76: =SUMIFS(Data!$K:$K,Data!$A:$A,2023,Data!$B:$B,12,Data!$G:$G,"CDU",Data!$F:$F,"PADD 2") -> 0 | G76: =IFERROR(F76/F75-1,"") -> -1
A77: CDU | B77: P2 | C77: 2024 | D77: 1 | E77: Jan 24 | F77: =SUMIFS(Data!$K:$K,Data!$A:$A,2024,Data!$B:$B,1,Data!$G:$G,"CDU",Data!$F:$F,"PADD 2") -> 10.9 | G77: =IFERROR(F77/F76-1,"") | H77: =IFERROR(F77/F65-1,"") -> -0.97136703
A78: CDU | B78: P2 | C78: 2024 | D78: 2 | E78: Feb 24 | F78: =SUMIFS(Data!$K:$K,Data!$A:$A,2024,Data!$B:$B,2,Data!$G:$G,"CDU",Data!$F:$F,"PADD 2") -> 454.5258 | G78: =IFERROR(F78/F77-1,"") -> 40.699615 | H78: =IFERROR(F78/F66-1,"") -> 0.23987506
A79: CDU | B79: P2 | C79: 2024 | D79: 3 | E79: Mar 24 | F79: =SUMIFS(Data!$K:$K,Data!$A:$A,2024,Data!$B:$B,3,Data!$G:$G,"CDU",Data!$F:$F,"PADD 2") -> 388.1406 | G79: =IFERROR(F79/F78-1,"") -> -0.14605376 | H79: =IFERROR(F79/F67-1,"") -> -0.38702221
A80: CDU | B80: P2 | C80: 2024 | D80: 4 | E80: Apr 24 | F80: =SUMIFS(Data!$K:$K,Data!$A:$A,2024,Data!$B:$B,4,Data!$G:$G,"CDU",Data!$F:$F,"PADD 2") -> 454.9725 | G80: =IFERROR(F80/F79-1,"") -> 0.17218477 | H80: =IFERROR(F80/F68-1,"") -> -0.38408612
A81: CDU | B81: P2 | C81: 2024 | D81: 5 | E81: May 24 | F81: =SUMIFS(Data!$K:$K,Data!$A:$A,2024,Data!$B:$B,5,Data!$G:$G,"CDU",Data!$F:$F,"PADD 2") -> 180.145 | G81: =IFERROR(F81/F80-1,"") -> -0.60405299 | H81: =IFERROR(F81/F69-1,"") -> -0.51712815
A82: CDU | B82: P2 | C82: 2024 | D82: 6 | E82: Jun 24 | F82: =SUMIFS(Data!$K:$K,Data!$A:$A,2024,Data!$B:$B,6,Data!$G:$G,"CDU",Data!$F:$F,"PADD 2") -> 95.82 | G82: =IFERROR(F82/F81-1,"") -> -0.46809515 | H82: =IFERROR(F82/F70-1,"") -> -0.44788245
A83: CDU | B83: P2 | C83: 2024 | D83: 7 | E83: Jul 24 | F83: =SUMIFS(Data!$K:$K,Data!$A:$A,2024,Data!$B:$B,7,Data!$G:$G,"CDU",Data!$F:$F,"PADD 2") -> 267.72 | G83: =IFERROR(F83/F82-1,"") -> 1.7939887 | H83: =IFERROR(F83/F71-1,"") -> 0.58724136
A84: CDU | B84: P2 | C84: 2024 | D84: 8 | E84: Aug 24 | F84: =SUMIFS(Data!$K:$K,Data!$A:$A,2024,Data!$B:$B,8,Data!$G:$G,"CDU",Data!$F:$F,"PADD 2") -> 185.56 | G84: =IFERROR(F84/F83-1,"") -> -0.30688779 | H84: =IFERROR(F84/F72-1,"") -> 2.0645747
A85: CDU | B85: P2 | C85: 2024 | D85: 9 | E85: Sep 24 | F85: =SUMIFS(Data!$K:$K,Data!$A:$A,2024,Data!$B:$B,9,Data!$G:$G,"CDU",Data!$F:$F,"PADD 2") -> 422.6804 | G85: =IFERROR(F85/F84-1,"") -> 1.2778638 | H85: =IFERROR(F85/F73-1,"") -> 0.14365448
A86: CDU | B86: P2 | C86: 2024 | D86: 10 | E86: Oct 24 | F86: =SUMIFS(Data!$K:$K,Data!$A:$A,2024,Data!$B:$B,10,Data!$G:$G,"CDU",Data!$F:$F,"PADD 2") -> 495.33 | G86: =IFERROR(F86/F85-1,"") -> 0.17187833 | H86: =IFERROR(F86/F74-1,"") -> -0.00064057622
A87: CDU | B87: P2 | C87: 2024 | D87: 11 | E87: Nov 24 | F87: =SUMIFS(Data!$K:$K,Data!$A:$A,2024,Data!$B:$B,11,Data!$G:$G,"CDU",Data!$F:$F,"PADD 2") -> 221.08 | G87: =IFERROR(F87/F86-1,"") -> -0.55367129 | H87: =IFERROR(F87/F75-1,"") -> 0.35756831
A88: CDU | B88: P2 | C88: 2024 | D88: 12 | E88: Dec 24 | F88: =SUMIFS(Data!$K:$K,Data!$A:$A,2024,Data!$B:$B,12,Data!$G:$G,"CDU",Data!$F:$F,"PADD 2") -> 3.9006 | G88: =IFERROR(F88/F87-1,"") -> -0.98235661 | H88: =IFERROR(F88/F76-1,"")
A89: CDU | B89: P2 | C89: 2025 | D89: 1 | E89: Jan 25 | F89: =SUMIFS(Data!$K:$K,Data!$A:$A,2025,Data!$B:$B,1,Data!$G:$G,"CDU",Data!$F:$F,"PADD 2") -> 44.79 | G89: =IFERROR(F89/F88-1,"") -> 10.482849 | H89: =IFERROR(F89/F77-1,"") -> 3.1091743
A90: CDU | B90: P2 | C90: 2025 | D90: 2 | E90: Feb 25 | F90: =SUMIFS(Data!$K:$K,Data!$A:$A,2025,Data!$B:$B,2,Data!$G:$G,"CDU",Data!$F:$F,"PADD 2") -> 215.325 | G90: =IFERROR(F90/F89-1,"") -> 3.8074347 | H90: =IFERROR(F90/F78-1,"") -> -0.52626452
A91: CDU | B91: P2 | C91: 2025 | D91: 3 | E91: Mar 25 | F91: =SUMIFS(Data!$K:$K,Data!$A:$A,2025,Data!$B:$B,3,Data!$G:$G,"CDU",Data!$F:$F,"PADD 2") -> 467.395 | G91: =IFERROR(F91/F90-1,"") -> 1.170649 | H91: =IFERROR(F91/F79-1,"") -> 0.20418992
A92: CDU | B92: P2 | C92: 2025 | D92: 4 | E92: Apr 25 | F92: =SUMIFS(Data!$K:$K,Data!$A:$A,2025,Data!$B:$B,4,Data!$G:$G,"CDU",Data!$F:$F,"PADD 2") -> 800.2825 | G92: =IFERROR(F92/F91-1,"") -> 0.71221879 | H92: =IFERROR(F92/F80-1,"") -> 0.75896895
A93: CDU | B93: P2 | C93: 2025 | D93: 5 | E93: May 25 | F93: =SUMIFS(Data!$K:$K,Data!$A:$A,2025,Data!$B:$B,5,Data!$G:$G,"CDU",Data!$F:$F,"PADD 2") -> 317.8306 | G93: =IFERROR(F93/F92-1,"") -> -0.60285199 | H93: =IFERROR(F93/F81-1,"") -> 0.76430431
A94: CDU | B94: P2 | C94: 2025 | D94: 6 | E94: Jun 25 | F94: =SUMIFS(Data!$K:$K,Data!$A:$A,2025,Data!$B:$B,6,Data!$G:$G,"CDU",Data!$F:$F,"PADD 2") -> 97.31 | G94: =IFERROR(F94/F93-1,"") -> -0.69383061 | H94: =IFERROR(F94/F82-1,"") -> 0.01554999
A95: CDU | B95: P2 | C95: 2025 | D95: 7 | E95: Jul 25 | F95: =SUMIFS(Data!$K:$K,Data!$A:$A,2025,Data!$B:$B,7,Data!$G:$G,"CDU",Data!$F:$F,"PADD 2") -> 75.827 | G95: =IFERROR(F95/F94-1,"") -> -0.22076868 | H95: =IFERROR(F95/F83-1,"") -> -0.71676752
A96: CDU | B96: P2 | C96: 2025 | D96: 8 | E96: Aug 25 | F96: =SUMIFS(Data!$K:$K,Data!$A:$A,2025,Data!$B:$B,8,Data!$G:$G,"CDU",Data!$F:$F,"PADD 2") -> 248.1758 | G96: =IFERROR(F96/F95-1,"") -> 2.2729213 | H96: =IFERROR(F96/F84-1,"") -> 0.33744234
A97: CDU | B97: P2 | C97: 2025 | D97: 9 | E97: Sep 25 | F97: =SUMIFS(Data!$K:$K,Data!$A:$A,2025,Data!$B:$B,9,Data!$G:$G,"CDU",Data!$F:$F,"PADD 2") -> 383.205 | G97: =IFERROR(F97/F96-1,"") -> 0.54408689 | H97: =IFERROR(F97/F85-1,"") -> -0.093393022
A98: CDU | B98: P2 | C98: 2025 | D98: 10 | E98: Oct 25 | F98: =SUMIFS(Data!$K:$K,Data!$A:$A,2025,Data!$B:$B,10,Data!$G:$G,"CDU",Data!$F:$F,"PADD 2") -> 592.82 | G98: =IFERROR(F98/F97-1,"") -> 0.54700487 | H98: =IFERROR(F98/F86-1,"") -> 0.19681828
A99: CDU | B99: P2 | C99: 2025 | D99: 11 | E99: Nov 25 | F99: =SUMIFS(Data!$K:$K,Data!$A:$A,2025,Data!$B:$B,11,Data!$G:$G,"CDU",Data!$F:$F,"PADD 2") -> 120.2906 | G99: =IFERROR(F99/F98-1,"") -> -0.79708748 | H99: =IFERROR(F99/F87-1,"") -> -0.4558956
A100: CDU | B100: P2 | C100: 2025 | D100: 12 | E100: Dec 25 | F100: =SUMIFS(Data!$K:$K,Data!$A:$A,2025,Data!$B:$B,12,Data!$G:$G,"CDU",Data!$F:$F,"PADD 2") -> 40.62 | G100: =IFERROR(F100/F99-1,"") -> -0.66231775 | H100: =IFERROR(F100/F88-1,"") -> 9.4137825
A101: CDU | B101: P2 | C101: 2026 | D101: 1 | E101: Jan 26 | F101: =SUMIFS(Data!$K:$K,Data!$A:$A,2026,Data!$B:$B,1,Data!$G:$G,"CDU",Data!$F:$F,"PADD 2") -> 65.19 | G101: =IFERROR(F101/F100-1,"") -> 0.60487445 | H101: =IFERROR(F101/F89-1,"") -> 0.45545881
...

Sheet ExxonMobil
A1: ExxonMobil 2027 Focus-Unit Turnarounds, per Unit (kbd)
A2: Cross-checked against ExxonMobil's corporate turnaround plan.
A4: Refinery | B4: Unit | C4: Class | D4: PADD | E4: kbd | F4: Window | G4: Type | H4: Vs corporate plan
A5: Joliet | B5: Crude | C5: CDU | D5: PADD 2 | E5: 250 | F5: Apr-May | G5: Planned | H5: matches corporate plan
A6: Baytown | B6: FCCU 3 (Fuels East) | C6: FCC | D6: PADD 3 | E6: 125 | F6: Feb-Apr | G6: Planned | H6: matches corporate plan
A7: Beaumont | B7: FCCU | C7: FCC | D7: PADD 3 | E7: 120 | F7: Jan-Feb | G7: Planned | H7: matches corporate plan
A8: Baton Rouge | B8: PSLA 9 (Pipestill) | C8: CDU | D8: PADD 3 | E8: 110 | F8: Sep-Oct | G8: Planned | H8: matches corporate plan
A9: Beaumont | B9: Hydrocracker | C9: Hydrocracker | D9: PADD 3 | E9: 65 | F9: Jan-Feb | G9: Planned | H9: matches corporate plan
A10: Joliet | B10: Reformer CCR | C10: Reformer | D10: PADD 2 | E10: 52 | F10: Apr-May | G10: Planned | H10: matches corporate plan

Sheet HVN
A1: HVN (Heavy Virgin Naphtha) Balance: CDU Supply vs Reformer Demand (kbd) = live model
A2: Reformer-feed naphtha. CDU/reformer offline pulled from Data; supply, demand and net recompute off the gold yield cells below. All PADDs, then PADD 3 (Gulf) only.
A4: Month | B4: CDU offline | C4: HVN supply removed | D4: Reformer offline | E4: HVN demand removed | F4: Net balance
A5: Jan | B5: =SUMIFS(Data!$K:$K,Data!$A:$A,2027,Data!$B:$B,1,Data!$G:$G,"CDU") -> 365.125 | C5: =B5*naph_yield -> 127.79375 | D5: =SUMIFS(Data!$K:$K,Data!$A:$A,2027,Data!$B:$B,1,Data!$G:$G,"Reformer") -> 29.125 | E5: =D5*ref_intake -> 29.125 | F5: =E5-C5 -> -98.66875 | G5: =-C5 -> -127.79375
A6: Feb | B6: =SUMIFS(Data!$K:$K,Data!$A:$A,2027,Data!$B:$B,2,Data!$G:$G,"CDU") -> 683.258 | C6: =B6*naph_yield -> 239.1403 | D6: =SUMIFS(Data!$K:$K,Data!$A:$A,2027,Data!$B:$B,2,Data!$G:$G,"Reformer") -> 68.78 | E6: =D6*ref_intake -> 68.78 | F6: =E6-C6 -> -170.3603 | G6: =-C6 -> -239.1403
A7: Mar | B7: =SUMIFS(Data!$K:$K,Data!$A:$A,2027,Data!$B:$B,3,Data!$G:$G,"CDU") -> 1062.14 | C7: =B7*naph_yield -> 371.749 | D7: =SUMIFS(Data!$K:$K,Data!$A:$A,2027,Data!$B:$B,3,Data!$G:$G,"Reformer") -> 184.889 | E7: =D7*ref_intake -> 184.889 | F7: =E7-C7 -> -186.86 | G7: =-C7 -> -371.749
A8: Apr | B8: =SUMIFS(Data!$K:$K,Data!$A:$A,2027,Data!$B:$B,4,Data!$G:$G,"CDU") -> 663.255 | C8: =B8*naph_yield -> 232.13925 | D8: =SUMIFS(Data!$K:$K,Data!$A:$A,2027,Data!$B:$B,4,Data!$G:$G,"Reformer") -> 141.475 | E8: =D8*ref_intake -> 141.475 | F8: =E8-C8 -> -90.66425 | G8: =-C8 -> -232.13925
A9: May | B9: =SUMIFS(Data!$K:$K,Data!$A:$A,2027,Data!$B:$B,5,Data!$G:$G,"CDU") -> 320.192 | C9: =B9*naph_yield -> 112.0672 | D9: =SUMIFS(Data!$K:$K,Data!$A:$A,2027,Data!$B:$B,5,Data!$G:$G,"Reformer") -> 45.428 | E9: =D9*ref_intake -> 45.428 | F9: =E9-C9 -> -66.6392 | G9: =-C9 -> -112.0672
A10: Jun | B10: =SUMIFS(Data!$K:$K,Data!$A:$A,2027,Data!$B:$B,6,Data!$G:$G,"CDU") -> 96 | C10: =B10*naph_yield -> 33.6 | D10: =SUMIFS(Data!$K:$K,Data!$A:$A,2027,Data!$B:$B,6,Data!$G:$G,"Reformer") -> 0.3 | E10: =D10*ref_intake -> 0.3 | F10: =E10-C10 -> -33.3 | G10: =-C10 -> -33.6
A11: Jul | B11: =SUMIFS(Data!$K:$K,Data!$A:$A,2027,Data!$B:$B,7,Data!$G:$G,"CDU") -> 96 | C11: =B11*naph_yield -> 33.6 | D11: =SUMIFS(Data!$K:$K,Data!$A:$A,2027,Data!$B:$B,7,Data!$G:$G,"Reformer") -> 0 | E11: =D11*ref_intake -> 0 | F11: =E11-C11 -> -33.6 | G11: =-C11 -> -33.6
A12: Aug | B12: =SUMIFS(Data!$K:$K,Data!$A:$A,2027,Data!$B:$B,8,Data!$G:$G,"CDU") -> 27.84 | C12: =B12*naph_yield -> 9.744 | D12: =SUMIFS(Data!$K:$K,Data!$A:$A,2027,Data!$B:$B,8,Data!$G:$G,"Reformer") -> 0 | E12: =D12*ref_intake -> 0 | F12: =E12-C12 -> -9.744 | G12: =-C12 -> -9.744
A13: Sep | B13: =SUMIFS(Data!$K:$K,Data!$A:$A,2027,Data!$B:$B,9,Data!$G:$G,"CDU") -> 976.735 | C13: =B13*naph_yield -> 341.85725 | D13: =SUMIFS(Data!$K:$K,Data!$A:$A,2027,Data!$B:$B,9,Data!$G:$G,"Reformer") -> 112.05 | E13: =D13*ref_intake -> 112.05 | F13: =E13-C13 -> -229.80725 | G13: =-C13 -> -341.85725
A14: Oct | B14: =SUMIFS(Data!$K:$K,Data!$A:$A,2027,Data!$B:$B,10,Data!$G:$G,"CDU") -> 1307.315 | C14: =B14*naph_yield -> 457.56025 | D14: =SUMIFS(Data!$K:$K,Data!$A:$A,2027,Data!$B:$B,10,Data!$G:$G,"Reformer") -> 109.945 | E14: =D14*ref_intake -> 109.945 | F14: =E14-C14 -> -347.61525 | G14: =-C14 -> -457.56025
A15: Nov | B15: =SUMIFS(Data!$K:$K,Data!$A:$A,2027,Data!$B:$B,11,Data!$G:$G,"CDU") -> 283.9 | C15: =B15*naph_yield -> 99.365 | D15: =SUMIFS(Data!$K:$K,Data!$A:$A,2027,Data!$B:$B,11,Data!$G:$G,"Reformer") -> 20.105 | E15: =D15*ref_intake -> 20.105 | F15: =E15-C15 -> -79.26 | G15: =-C15 -> -99.365
A16: Dec | B16: =SUMIFS(Data!$K:$K,Data!$A:$A,2027,Data!$B:$B,12,Data!$G:$G,"CDU") -> 0 | C16: =B16*naph_yield -> 0 | D16: =SUMIFS(Data!$K:$K,Data!$A:$A,2027,Data!$B:$B,12,Data!$G:$G,"Reformer") -> 0 | E16: =D16*ref_intake -> 0 | F16: =E16-C16 -> 0 | G16: =-C16 -> 0
A17: Year | B17: =SUM(B5:B16) -> 5881.76 | C17: =SUM(C5:C16) -> 2058.616 | D17: =SUM(D5:D16) -> 712.097 | E17: =SUM(E5:E16) -> 712.097 | F17: =SUM(F5:F16) -> -1346.519
A19: Net < 0 = deficit (HVN short, bullish reformate); net > 0 = surplus.
A20: 2027 annual net = -1,347 kbd (11 deficit months, 0 surplus).
A22: Live inputs (edit -- supply & demand above recompute)
A23: Naphtha yield (per bbl crude) | D23: 0.35
A24: Reformer naphtha intake (per bbl capacity) | D24: 1
A26: PADD 3 (Gulf) only -- CDU & reformer filtered to PADD 3
A27: Month | B27: CDU offline | C27: HVN supply removed | D27: Reformer offline | E27: HVN demand removed | F27: Net balance
A28: Jan | B28: =SUMIFS(Data!$K:$K,Data!$A:$A,2027,Data!$B:$B,1,Data!$G:$G,"CDU",Data!$F:$F,"PADD 3") -> 210.575 | C28: =B28*naph_yield -> 73.70125 | D28: =SUMIFS(Data!$K:$K,Data!$A:$A,2027,Data!$B:$B,1,Data!$G:$G,"Reformer",Data!$F:$F,"PADD 3") -> 5.8 | E28: =D28*ref_intake -> 5.8 | F28: =E28-C28 -> -67.90125 | G28: =-C28 -> -73.70125
A29: Feb | B29: =SUMIFS(Data!$K:$K,Data!$A:$A,2027,Data!$B:$B,2,Data!$G:$G,"CDU",Data!$F:$F,"PADD 3") -> 355.17 | C29: =B29*naph_yield -> 124.3095 | D29: =SUMIFS(Data!$K:$K,Data!$A:$A,2027,Data!$B:$B,2,Data!$G:$G,"Reformer",Data!$F:$F,"PADD 3") -> 17.36 | E29: =D29*ref_intake -> 17.36 | F29: =E29-C29 -> -106.9495 | G29: =-C29 -> -124.3095
A30: Mar | B30: =SUMIFS(Data!$K:$K,Data!$A:$A,2027,Data!$B:$B,3,Data!$G:$G,"CDU",Data!$F:$F,"PADD 3") -> 468.97 | C30: =B30*naph_yield -> 164.1395 | D30: =SUMIFS(Data!$K:$K,Data!$A:$A,2027,Data!$B:$B,3,Data!$G:$G,"Reformer",Data!$F:$F,"PADD 3") -> 100.37 | E30: =D30*ref_intake -> 100.37 | F30: =E30-C30 -> -63.7695 | G30: =-C30 -> -164.1395
A31: Apr | B31: =SUMIFS(Data!$K:$K,Data!$A:$A,2027,Data!$B:$B,4,Data!$G:$G,"CDU",Data!$F:$F,"PADD 3") -> 178.93 | C31: =B31*naph_yield -> 62.6255 | D31: =SUMIFS(Data!$K:$K,Data!$A:$A,2027,Data!$B:$B,4,Data!$G:$G,"Reformer",Data!$F:$F,"PADD 3") -> 52.91 | E31: =D31*ref_intake -> 52.91 | F31: =E31-C31 -> -9.7155 | G31: =-C31 -> -62.6255
A32: May | B32: =SUMIFS(Data!$K:$K,Data!$A:$A,2027,Data!$B:$B,5,Data!$G:$G,"CDU",Data!$F:$F,"PADD 3") -> 0 | C32: =B32*naph_yield -> 0 | D32: =SUMIFS(Data!$K:$K,Data!$A:$A,2027,Data!$B:$B,5,Data!$G:$G,"Reformer",Data!$F:$F,"PADD 3") -> 0 | E32: =D32*ref_intake -> 0 | F32: =E32-C32 -> 0 | G32: =-C32 -> 0
A33: Jun | B33: =SUMIFS(Data!$K:$K,Data!$A:$A,2027,Data!$B:$B,6,Data!$G:$G,"CDU",Data!$F:$F,"PADD 3") -> 96 | C33: =B33*naph_yield -> 33.6 | D33: =SUMIFS(Data!$K:$K,Data!$A:$A,2027,Data!$B:$B,6,Data!$G:$G,"Reformer",Data!$F:$F,"PADD 3") -> 0 | E33: =D33*ref_intake -> 0 | F33: =E33-C33 -> -33.6 | G33: =-C33 -> -33.6
A34: Jul | B34: =SUMIFS(Data!$K:$K,Data!$A:$A,2027,Data!$B:$B,7,Data!$G:$G,"CDU",Data!$F:$F,"PADD 3") -> 96 | C34: =B34*naph_yield -> 33.6 | D34: =SUMIFS(Data!$K:$K,Data!$A:$A,2027,Data!$B:$B,7,Data!$G:$G,"Reformer",Data!$F:$F,"PADD 3") -> 0 | E34: =D34*ref_intake -> 0 | F34: =E34-C34 -> -33.6 | G34: =-C34 -> -33.6
A35: Aug | B35: =SUMIFS(Data!$K:$K,Data!$A:$A,2027,Data!$B:$B,8,Data!$G:$G,"CDU",Data!$F:$F,"PADD 3") -> 27.84 | C35: =B35*naph_yield -> 9.744 | D35: =SUMIFS(Data!$K:$K,Data!$A:$A,2027,Data!$B:$B,8,Data!$G:$G,"Reformer",Data!$F:$F,"PADD 3") -> 0 | E35: =D35*ref_intake -> 0 | F35: =E35-C35 -> -9.744 | G35: =-C35 -> -9.744
A36: Sep | B36: =SUMIFS(Data!$K:$K,Data!$A:$A,2027,Data!$B:$B,9,Data!$G:$G,"CDU",Data!$F:$F,"PADD 3") -> 583.89 | C36: =B36*naph_yield -> 204.3615 | D36: =SUMIFS(Data!$K:$K,Data!$A:$A,2027,Data!$B:$B,9,Data!$G:$G,"Reformer",Data!$F:$F,"PADD 3") -> 0 | E36: =D36*ref_intake -> 0 | F36: =E36-C36 -> -204.3615 | G36: =-C36 -> -204.3615
A37: Oct | B37: =SUMIFS(Data!$K:$K,Data!$A:$A,2027,Data!$B:$B,10,Data!$G:$G,"CDU",Data!$F:$F,"PADD 3") -> 865.76 | C37: =B37*naph_yield -> 303.016 | D37: =SUMIFS(Data!$K:$K,Data!$A:$A,2027,Data!$B:$B,10,Data!$G:$G,"Reformer",Data!$F:$F,"PADD 3") -> 15.015 | E37: =D37*ref_intake -> 15.015 | F37: =E37-C37 -> -288.001 | G37: =-C37 -> -303.016
A38: Nov | B38: =SUMIFS(Data!$K:$K,Data!$A:$A,2027,Data!$B:$B,11,Data!$G:$G,"CDU",Data!$F:$F,"PADD 3") -> 250.9 | C38: =B38*naph_yield -> 87.815 | D38: =SUMIFS(Data!$K:$K,Data!$A:$A,2027,Data!$B:$B,11,Data!$G:$G,"Reformer",Data!$F:$F,"PADD 3") -> 13.025 | E38: =D38*ref_intake -> 13.025 | F38: =E38-C38 -> -74.79 | G38: =-C38 -> -87.815
A39: Dec | B39: =SUMIFS(Data!$K:$K,Data!$A:$A,2027,Data!$B:$B,12,Data!$G:$G,"CDU",Data!$F:$F,"PADD 3") -> 0 | C39: =B39*naph_yield -> 0 | D39: =SUMIFS(Data!$K:$K,Data!$A:$A,2027,Data!$B:$B,12,Data!$G:$G,"Reformer",Data!$F:$F,"PADD 3") -> 0 | E39: =D39*ref_intake -> 0 | F39: =E39-C39 -> 0 | G39: =-C39 -> 0
A40: Year | B40: =SUM(B28:B39) -> 3134.035 | C40: =SUM(C28:C39) -> 1096.9122 | D40: =SUM(D28:D39) -> 204.48 | E40: =SUM(E28:E39) -> 204.48 | F40: =SUM(F28:F39) -> -892.43225
A42: PADD 3 2027 annual net = -892 kbd (10 deficit months) -- the Gulf share of the HVN deficit.

Sheet Forecast
A1: 2027 Unplanned Scenario (kbd/month) = baseline x multiplier (live)
A2: Headline by month (peak/avg = real levels). Annual Sigma (sum of the 12 monthly concurrent figures) is kept for reference -- a magnitude, not a level; not for slides.
A4: Unplanned scenario (kbd/mo) | B4: Jan | C4: Feb | D4: Mar | E4: Apr | F4: May | G4: Jun | H4: Jul | I4: Aug | J4: Sep | K4: Oct | L4: Nov | M4: Dec | N4: Peak/mo | O4: Avg/mo | P4: Annual Σ
A5: Baseline (2023-2026, completeness-aware) | B5: 1946.2278 | C5: 2880.2243 | D5: 2118.639 | E5: 2253.8666 | F5: 1411.2534 | G5: 1333.7552 | H5: 1173.2245 | I5: 1212.6027 | J5: 1621.1806 | K5: 2132.5508 | L5: 1240.6596 | M5: 806.31737 | N5: =MAX(B5:M5) -> 2880.2243 | O5: =AVERAGE(B5:M5) -> 1677.5418 | P5: =SUM(B5:M5) -> 20130.502
A6: Conservative | B6: =B5*mult_cons -> 1556.9823 | C6: =C5*mult_cons -> 2304.1795 | D6: =D5*mult_cons -> 1694.9112 | E6: =E5*mult_cons -> 1803.0933 | F6: =F5*mult_cons -> 1129.0027 | G6: =G5*mult_cons -> 1067.0042 | H6: =H5*mult_cons -> 938.57962 | I6: =I5*mult_cons -> 970.08216 | ... M6: =M5*mult_cons -> 645.05389 | N6: =MAX(B6:M6) -> 2304.1795 | O6: =AVERAGE(B6:M6) -> 1342.0335 | P6: =SUM(B6:M6) -> 16104.402
A7: Average | B7: =B5*mult_avg -> 1946.2278 | C7: =C5*mult_avg -> 2880.2243 | D7: =D5*mult_avg -> 2118.639 | E7: =E5*mult_avg -> 2253.8666 | F7: =F5*mult_avg -> 1411.2534 | G7: =G5*mult_avg -> 1333.7552 | H7: =H5*mult_avg -> 1173.2245 | I7: =I5*mult_avg -> 1212.6027 | ... M7: =M5*mult_avg -> 806.31737 | N7: =MAX(B7:M7) -> 2880.2243 | O7: =AVERAGE(B7:M7) -> 1677.5418 | P7: =SUM(B7:M7) -> 20130.502
A8: Active | B8: =B5*mult_act -> 2530.0962 | C8: =C5*mult_act -> 3744.2917 | D8: =D5*mult_act -> 2754.2306 | E8: =E5*mult_act -> 2930.0266 | F8: =F5*mult_act -> 1834.6294 | G8: =G5*mult_act -> 1733.8818 | H8: =H5*mult_act -> 1525.1919 | I8: =I5*mult_act -> 1576.3835 | ... M8: =M5*mult_act -> 1048.2126 | N8: =MAX(B8:M8) -> 3744.2917 | O8: =AVERAGE(B8:M8) -> 2180.8044 | P8: =SUM(B8:M8) -> 26169.653
A9: Booked planned 2027 (by month) | B9: =SUMIFS(Data!$K:$K,Data!$A:$A,2027,Data!$B:$B,1,Data!$J:$J,"PLANNED") -> 1103.883 | C9: =SUMIFS(Data!$K:$K,Data!$A:$A,2027,Data!$B:$B,2,Data!$J:$J,"PLANNED") -> 2114.6201 | D9: =SUMIFS(Data!$K:$K,Data!$A:$A,2027,Data!$B:$B,3,Data!$J:$J,"PLANNED") -> 2889.3523 | E9: =SUMIFS(Data!$K:$K,Data!$A:$A,2027,Data!$B:$B,4,Data!$J:$J,"PLANNED") -> 1954.1924 | F9: =SUMIFS(Data!$K:$K,Data!$A:$A,2027,Data!$B:$B,5,Data!$J:$J,"PLANNED") -> 856.532 | G9: =SUMIFS(Data!$K:$K,Data!$A:$A,2027,Data!$B:$B,6,Data!$J:$J,"PLANNED") -> 215.305 | H9: =SUMIFS(Data!$K:$K,Data!$A:$A,2027,Data!$B:$B,7,Data!$J:$J,"PLANNED") -> 167.5 | I9: =SUMIFS(Data!$K:$K,Data!$A:$A,2027,Data!$B:$B,8,Data!$J:$J,"PLANNED") -> 51.06 | J9: =SUMIFS(Data!$K:$K,Data!$A:$A,2027,Data!$B:$B,9,Data!$J:$J,"PLANNED") -> 2763.7719 | K9: =SUMIFS(Data!$K:$K,Data!$A:$A,2027,Data!$B:$B,10,Data!$J:$J,"PLANNED") -> 2799.5469 | L9: =SUMIFS(Data!$K:$K,Data!$A:$A,2027,Data!$B:$B,11,Data!$J:$J,"PLANNED") -> 546.936 | M9: =SUMIFS(Data!$K:$K,Data!$A:$A,2027,Data!$B:$B,12,Data!$J:$J,"PLANNED") -> 3.5 | N9: =MAX(B9:M9) -> 2889.3523 | O9: =AVERAGE(B9:M9) -> 1288.85 | P9: =SUM(B9:M9) -> 15466.2
A11: Implied total offline by month = scenario unplanned + booked planned
A12: Scenario | B12: Jan | C12: Feb | D12: Mar | E12: Apr | F12: May | G12: Jun | H12: Jul | I12: Aug | J12: Sep | K12: Oct | L12: Nov | M12: Dec | N12: Peak month | O12: Avg month | P12: Annual Σ
A13: Conservative | B13: =B6+B9 -> 2660.8653 | C13: =C6+C9 -> 4418.7996 | D13: =D6+D9 -> 4584.2635 | E13: =E6+E9 -> 3757.2857 | F13: =F6+F9 -> 1985.5347 | G13: =G6+G9 -> 1282.3092 | H13: =H6+H9 -> 1106.0796 | I13: =I6+I9 -> 1021.1422 | ... M13: =M6+M9 -> 648.55389 | N13: =MAX(B13:M13) -> 4584.2635 | O13: =AVERAGE(B13:M13) -> 2630.8834 | P13: =SUM(B13:M13) -> 31570.601
A14: Average | B14: =B7+B9 -> 3050.1108 | C14: =C7+C9 -> 4994.8445 | D14: =D7+D9 -> 5007.9913 | E14: =E7+E9 -> 4208.059 | F14: =F7+F9 -> 2267.7854 | G14: =G7+G9 -> 1549.0602 | H14: =H7+H9 -> 1340.7245 | I14: =I7+I9 -> 1263.6627 | ... M14: =M7+M9 -> 809.81737 | N14: =MAX(B14:M14) -> 5007.9913 | O14: =AVERAGE(B14:M14) -> 2966.3918 | P14: =SUM(B14:M14) -> 35596.702
A15: Active | B15: =B8+B9 -> 3633.9792 | C15: =C8+C9 -> 5858.9118 | D15: =D8+D9 -> 5643.5829 | E15: =E8+E9 -> 4884.219 | F15: =F8+F9 -> 2691.1614 | G15: =G8+G9 -> 1949.1868 | H15: =H8+H9 -> 1692.6919 | I15: =I8+I9 -> 1627.4435 | ... M15: =M8+M9 -> 1051.7126 | N15: =MAX(B15:M15) -> 5858.9118 | O15: =AVERAGE(B15:M15) -> 3469.6544 | P15: =SUM(B15:M15) -> 41635.852
A16: Peak month = worst single month offline (trade this). Avg month = average. Annual Σ = sum of the 12 monthly figures: a reference magnitude, not a level -- keep it off slides.
A18: History (complete years, annual Σ unplanned)
A19: P25 | B19: 20420.06
A20: Median | B20: 21582.567
A21: P90 | B21: 23317.415
A22: Mean | B22: 21530.416
A24: Scenario multipliers (x baseline -- the paths above recompute live)
A25: Conservative | B25: 0.8
A26: Average | B26: 1
A27: Active | B27: 1.3
A29: Baseline window 2023-2026 | actuals reported through Jul 2026

Sheet Scenarios
A1: Scenarios & Sensitivities: stressing the 2027 book (peak-month kbd)
A2: Three forward what-ifs in one place. Peak-month = the worst single month of total capacity offline. Edit the gold cells; everything recomputes live.
A4: 1) Peak-month sensitivity grid (unplanned multiplier x one-off shock)
A5: mult v / shock > | B5: 0 | C5: 250 | D5: 500 | E5: 750 | F5: 1000
A6: 0.7 | B6: {=MAX($A6*Forecast!$B$5:$M$5+Forecast!$B$9:$M$9)+B$5} -> 4372.3996 | C6: {=MAX($A6*Forecast!$B$5:$M$5+Forecast!$B$9:$M$9)+C$5} -> 4622.3996 | D6: {=MAX($A6*Forecast!$B$5:$M$5+Forecast!$B$9:$M$9)+D$5} -> 4872.3996 | E6: {=MAX($A6*Forecast!$B$5:$M$5+Forecast!$B$9:$M$9)+E$5} -> 5122.3996 | F6: {=MAX($A6*Forecast!$B$5:$M$5+Forecast!$B$9:$M$9)+F$5} -> 5372.3996
A7: 0.85 | B7: {=MAX($A7*Forecast!$B$5:$M$5+Forecast!$B$9:$M$9)+B$5} -> 4690.1954 | C7: {=MAX($A7*Forecast!$B$5:$M$5+Forecast!$B$9:$M$9)+C$5} -> 4940.1954 | D7: {=MAX($A7*Forecast!$B$5:$M$5+Forecast!$B$9:$M$9)+D$5} -> 5190.1954 | E7: {=MAX($A7*Forecast!$B$5:$M$5+Forecast!$B$9:$M$9)+E$5} -> 5440.1954 | F7: {=MAX($A7*Forecast!$B$5:$M$5+Forecast!$B$9:$M$9)+F$5} -> 5690.1954
A8: 1 | B8: {=MAX($A8*Forecast!$B$5:$M$5+Forecast!$B$9:$M$9)+B$5} -> 5007.9913 | C8: {=MAX($A8*Forecast!$B$5:$M$5+Forecast!$B$9:$M$9)+C$5} -> 5257.9913 | D8: {=MAX($A8*Forecast!$B$5:$M$5+Forecast!$B$9:$M$9)+D$5} -> 5507.9913 | E8: {=MAX($A8*Forecast!$B$5:$M$5+Forecast!$B$9:$M$9)+E$5} -> 5757.9913 | F8: {=MAX($A8*Forecast!$B$5:$M$5+Forecast!$B$9:$M$9)+F$5} -> 6007.9913
A9: 1.15 | B9: {=MAX($A9*Forecast!$B$5:$M$5+Forecast!$B$9:$M$9)+B$5} -> 5426.8781 | C9: {=MAX($A9*Forecast!$B$5:$M$5+Forecast!$B$9:$M$9)+C$5} -> 5676.8781 | D9: {=MAX($A9*Forecast!$B$5:$M$5+Forecast!$B$9:$M$9)+D$5} -> 5926.8781 | E9: {=MAX($A9*Forecast!$B$5:$M$5+Forecast!$B$9:$M$9)+E$5} -> 6176.8781 | F9: {=MAX($A9*Forecast!$B$5:$M$5+Forecast!$B$9:$M$9)+F$5} -> 6426.8781
A10: 1.3 | B10: {=MAX($A10*Forecast!$B$5:$M$5+Forecast!$B$9:$M$9)+B$5} -> 5858.9118 | C10: {=MAX($A10*Forecast!$B$5:$M$5+Forecast!$B$9:$M$9)+C$5} -> 6108.9118 | D10: {=MAX($A10*Forecast!$B$5:$M$5+Forecast!$B$9:$M$9)+D$5} -> 6358.9118 | E10: {=MAX($A10*Forecast!$B$5:$M$5+Forecast!$B$9:$M$9)+E$5} -> 6608.9118 | F10: {=MAX($A10*Forecast!$B$5:$M$5+Forecast!$B$9:$M$9)+F$5} -> 6858.9118
A11: 1.5 | B11: {=MAX($A11*Forecast!$B$5:$M$5+Forecast!$B$9:$M$9)+B$5} -> 6434.9566 | C11: {=MAX($A11*Forecast!$B$5:$M$5+Forecast!$B$9:$M$9)+C$5} -> 6684.9566 | D11: {=MAX($A11*Forecast!$B$5:$M$5+Forecast!$B$9:$M$9)+D$5} -> 6934.9566 | E11: {=MAX($A11*Forecast!$B$5:$M$5+Forecast!$B$9:$M$9)+E$5} -> 7184.9566 | F11: {=MAX($A11*Forecast!$B$5:$M$5+Forecast!$B$9:$M$9)+F$5} -> 7434.9566
A13: Rows = unplanned multiplier x baseline; columns = one-off shock added to that month. Peak-month implied = worst month of (baseline x multiplier + booked planned) + shock. Base = 1.0 / 0.
A16: 2) Named stress shocks on the book
A17: Scenario | B17: Description | C17: Crude shock (kbd) | D17: Other shock (kbd) | E17: Peak-month implied | F17: Naphtha net impact
A18: USGC hurricane | B18: PADD 3 unplanned spike, ~1-2 months | C18: 800 | D18: 0 | E18: =Forecast!$N$14+C18+D18 -> 5807.9913 | F18: =-naph_yield*C18 -> -280
A19: Winter freeze (Uri-like) | B19: National unplanned spike in Feb | C19: 0 | D19: 2000 | E19: =Forecast!$N$14+C19+D19 -> 7007.9913 | F19: =-naph_yield*C19 -> 0
A20: Two large CDUs trip | B20: ~500 kbd crude unplanned, 1 month | C20: 500 | D20: 0 | E20: =Forecast!$N$14+C20+D20 -> 5507.9913 | F20: =-naph_yield*C20 -> -175
A21: Heavy fall TA overlap | B21: Sep-Oct planned overlap adds load | C21: 0 | D21: 600 | E21: =Forecast!$N$14+C21+D21 -> 5607.9913 | F21: =-naph_yield*C21 -> 0
A22: Quiet year | B22: Light unplanned, fewer surprises | C22: 0 | D22: -1500 | E22: =Forecast!$N$14+C22+D22 -> 3507.9913 | F22: =-naph_yield*C22 -> 0
A24: Peak-month implied = Average scenario's worst-month offline + crude + other shock. Naphtha impact = -naphtha_yield x crude shock (more crude down = shorter naphtha).
A27: 3) PADD connectivity: effective crude-outage impact (edit the pass-through cells)
A28: PADD | B28: Pass-thru | C28: 2026 CDU (Σ kbd) | D28: 2026 effective | E28: 2027 CDU (Σ kbd) | F28: 2027 effective
A29: PADD 1 | B29: 0.85 | C29: =SUMIFS(Data!$K:$K,Data!$A:$A,2026,Data!$G:$G,"CDU",Data!$F:$F,"PADD 1") -> 591.52 | D29: =C29*conn_p1 -> 502.792 | E29: =SUMIFS(Data!$K:$K,Data!$A:$A,2027,Data!$G:$G,"CDU",Data!$F:$F,"PADD 1") -> 153.7 | F29: =E29*conn_p1 -> 130.645
A30: PADD 2 | B30: 0.9 | C30: =SUMIFS(Data!$K:$K,Data!$A:$A,2026,Data!$G:$G,"CDU",Data!$F:$F,"PADD 2") -> 2312.79 | D30: =C30*conn_p2 -> 2081.511 | E30: =SUMIFS(Data!$K:$K,Data!$A:$A,2027,Data!$G:$G,"CDU",Data!$F:$F,"PADD 2") -> 1276.47 | F30: =E30*conn_p2 -> 1148.823
A31: PADD 3 | B31: 0.4 | C31: =SUMIFS(Data!$K:$K,Data!$A:$A,2026,Data!$G:$G,"CDU",Data!$F:$F,"PADD 3") -> 3295.209 | D31: =C31*conn_p3 -> 1318.0836 | E31: =SUMIFS(Data!$K:$K,Data!$A:$A,2027,Data!$G:$G,"CDU",Data!$F:$F,"PADD 3") -> 3134.035 | F31: =E31*conn_p3 -> 1253.614
A32: PADD 4 | B32: 0.9 | C32: =SUMIFS(Data!$K:$K,Data!$A:$A,2026,Data!$G:$G,"CDU",Data!$F:$F,"PADD 4") -> 161.536 | D32: =C32*conn_p4 -> 145.3824 | E32: =SUMIFS(Data!$K:$K,Data!$A:$A,2027,Data!$G:$G,"CDU",Data!$F:$F,"PADD 4") -> 349.462 | F32: =E32*conn_p4 -> 314.5158
A33: PADD 5 | B33: 0.95 | C33: =SUMIFS(Data!$K:$K,Data!$A:$A,2026,Data!$G:$G,"CDU",Data!$F:$F,"PADD 5") -> 902.123 | D33: =C33*conn_p5 -> 857.01685 | E33: =SUMIFS(Data!$K:$K,Data!$A:$A,2027,Data!$G:$G,"CDU",Data!$F:$F,"PADD 5") -> 968.093 | F33: =E33*conn_p5 -> 919.68835
A34: Total | C34: =SUM(C29:C33) -> 7263.178 | D34: =SUM(D29:D33) -> 4904.7859 | E34: =SUM(E29:E33) -> 5881.76 | F34: =SUM(F29:F33) -> 3767.2862
A36: Buffered by connectivity (nominal - effective): | D36: =C34-D34 -> 2358.3921 | F36: =E34-F34 -> 2114.4738
A37: ="Effective crude tightness is "&TEXT(1-F34/E34,"0%")&" below nominal in 2027 -- the P3 connectivity buffer." -> Effective crude tightness is 36% below nominal in 2027 -- the P3 connectivity buffer.
A39: Low pass-through = well-connected (P3 Gulf): downstream keeps running on piped-in intermediates. High (P2 / P4 / P5, parts of P1): islanded, the outage cascades. Edit the pass-through cells (column B).

Sheet Historicals
A1: Historicals: monthly offline 2023-2027 (kbd) = SUMIFS over Data
A2: Total / planned / unplanned, unplanned %, per focus unit and per PADD. The series the stats use.
A4: Year | B4: Mon | C4: Period | D4: Total | E4: Planned | F4: Unplanned | G4: Unpl % | H4: CDU | I4: FCC | J4: HydroCk | K4: Reformer | L4: PADD1 | M4: PADD2 | N4: PADD3 | O4: PADD4 | P4: PADD5 | Q4: Naph net
A5: 2023 | B5: 1 | C5: Jan 23 | D5: =SUMIFS(Data!$K:$K,Data!$A:$A,2023,Data!$B:$B,1) -> 5716.2146 | E5: =SUMIFS(Data!$K:$K,Data!$A:$A,2023,Data!$B:$B,1,Data!$J:$J,"PLANNED") -> 2552.9085 | F5: =SUMIFS(Data!$K:$K,Data!$A:$A,2023,Data!$B:$B,1,Data!$J:$J,"UNPLANNED") -> 3163.3061 | G5: =IFERROR(F5/D5,0) -> 0.55339177 | H5: =SUMIFS(Data!$K:$K,Data!$A:$A,2023,Data!$B:$B,1,Data!$G:$G,"CDU") -> 1739.545 | I5: =SUMIFS(Data!$K:$K,Data!$A:$A,2023,Data!$B:$B,1,Data!$G:$G,"FCC") -> 810.943 | J5: =SUMIFS(Data!$K:$K,Data!$A:$A,2023,Data!$B:$B,1,Data!$G:$G,"Hydrocracker") -> 281.7 | K5: =SUMIFS(Data!$K:$K,Data!$A:$A,2023,Data!$B:$B,1,Data!$G:$G,"Reformer") -> 432.859 | L5: =SUMIFS(Data!$K:$K,Data!$A:$A,2023,Data!$B:$B,1,Data!$F:$F,"PADD 1") -> 126.05 | M5: =SUMIFS(Data!$K:$K,Data!$A:$A,2023,Data!$B:$B,1,Data!$F:$F,"PADD 2") -> 1256.5976 | N5: =SUMIFS(Data!$K:$K,Data!$A:$A,2023,Data!$B:$B,1,Data!$F:$F,"PADD 3") -> 3222.9692 | O5: =SUMIFS(Data!$K:$K,Data!$A:$A,2023,Data!$B:$B,1,Data!$F:$F,"PADD 4") -> 493.348 | P5: =SUMIFS(Data!$K:$K,Data!$A:$A,2023,Data!$B:$B,1,Data!$F:$F,"PADD 5") -> 617.2498 | Q5: =K5*ref_intake-H5*naph_yield -> -175.98175
A6: 2023 | B6: 2 | C6: Feb 23 | D6: =SUMIFS(Data!$K:$K,Data!$A:$A,2023,Data!$B:$B,2) -> 6813.7157 | E6: =SUMIFS(Data!$K:$K,Data!$A:$A,2023,Data!$B:$B,2,Data!$J:$J,"PLANNED") -> 4134.309 | F6: =SUMIFS(Data!$K:$K,Data!$A:$A,2023,Data!$B:$B,2,Data!$J:$J,"UNPLANNED") -> 2679.4067 | G6: =IFERROR(F6/D6,0) -> 0.39323723 | H6: =SUMIFS(Data!$K:$K,Data!$A:$A,2023,Data!$B:$B,2,Data!$G:$G,"CDU") -> 2180.255 | I6: =SUMIFS(Data!$K:$K,Data!$A:$A,2023,Data!$B:$B,2,Data!$G:$G,"FCC") -> 1025.05 | J6: =SUMIFS(Data!$K:$K,Data!$A:$A,2023,Data!$B:$B,2,Data!$G:$G,"Hydrocracker") -> 420.495 | K6: =SUMIFS(Data!$K:$K,Data!$A:$A,2023,Data!$B:$B,2,Data!$G:$G,"Reformer") -> 453.94 | L6: =SUMIFS(Data!$K:$K,Data!$A:$A,2023,Data!$B:$B,2,Data!$F:$F,"PADD 1") -> 440 | M6: =SUMIFS(Data!$K:$K,Data!$A:$A,2023,Data!$B:$B,2,Data!$F:$F,"PADD 2") -> 1088.065 | N6: =SUMIFS(Data!$K:$K,Data!$A:$A,2023,Data!$B:$B,2,Data!$F:$F,"PADD 3") -> 3622.339 | O6: =SUMIFS(Data!$K:$K,Data!$A:$A,2023,Data!$B:$B,2,Data!$F:$F,"PADD 4") -> 408.143 | P6: =SUMIFS(Data!$K:$K,Data!$A:$A,2023,Data!$B:$B,2,Data!$F:$F,"PADD 5") -> 1255.1687 | Q6: =K6*ref_intake-H6*naph_yield -> -309.14925
A7: 2023 | B7: 3 | C7: Mar 23 | D7: =SUMIFS(Data!$K:$K,Data!$A:$A,2023,Data!$B:$B,3) -> 6741.2225 | E7: =SUMIFS(Data!$K:$K,Data!$A:$A,2023,Data!$B:$B,3,Data!$J:$J,"PLANNED") -> 3664.6845 | F7: =SUMIFS(Data!$K:$K,Data!$A:$A,2023,Data!$B:$B,3,Data!$J:$J,"UNPLANNED") -> 3076.538 | G7: =IFERROR(F7/D7,0) -> 0.45637687 | H7: =SUMIFS(Data!$K:$K,Data!$A:$A,2023,Data!$B:$B,3,Data!$G:$G,"CDU") -> 2060.202 | I7: =SUMIFS(Data!$K:$K,Data!$A:$A,2023,Data!$B:$B,3,Data!$G:$G,"FCC") -> 880.265 | J7: =SUMIFS(Data!$K:$K,Data!$A:$A,2023,Data!$B:$B,3,Data!$G:$G,"Hydrocracker") -> 492.643 | K7: =SUMIFS(Data!$K:$K,Data!$A:$A,2023,Data!$B:$B,3,Data!$G:$G,"Reformer") -> 486.416 | L7: =SUMIFS(Data!$K:$K,Data!$A:$A,2023,Data!$B:$B,3,Data!$F:$F,"PADD 1") -> 473.92 | M7: =SUMIFS(Data!$K:$K,Data!$A:$A,2023,Data!$B:$B,3,Data!$F:$F,"PADD 2") -> 1877.395 | N7: =SUMIFS(Data!$K:$K,Data!$A:$A,2023,Data!$B:$B,3,Data!$F:$F,"PADD 3") -> 3305.26 | O7: =SUMIFS(Data!$K:$K,Data!$A:$A,2023,Data!$B:$B,3,Data!$F:$F,"PADD 4") -> 357.3731 | P7: =SUMIFS(Data!$K:$K,Data!$A:$A,2023,Data!$B:$B,3,Data!$F:$F,"PADD 5") -> 727.2744 | Q7: =K7*ref_intake-H7*naph_yield -> -234.6547
A8: 2023 | B8: 4 | C8: Apr 23 | D8: =SUMIFS(Data!$K:$K,Data!$A:$A,2023,Data!$B:$B,4) -> 6116.2489 | E8: =SUMIFS(Data!$K:$K,Data!$A:$A,2023,Data!$B:$B,4,Data!$J:$J,"PLANNED") -> 3647.546 | F8: =SUMIFS(Data!$K:$K,Data!$A:$A,2023,Data!$B:$B,4,Data!$J:$J,"UNPLANNED") -> 2468.7029 | G8: =IFERROR(F8/D8,0) -> 0.40363022 | H8: =SUMIFS(Data!$K:$K,Data!$A:$A,2023,Data!$B:$B,4,Data!$G:$G,"CDU") -> 1806.215 | I8: =SUMIFS(Data!$K:$K,Data!$A:$A,2023,Data!$B:$B,4,Data!$G:$G,"FCC") -> 615.626 | J8: =SUMIFS(Data!$K:$K,Data!$A:$A,2023,Data!$B:$B,4,Data!$G:$G,"Hydrocracker") -> 424.371 | K8: =SUMIFS(Data!$K:$K,Data!$A:$A,2023,Data!$B:$B,4,Data!$G:$G,"Reformer") -> 495.342 | L8: =SUMIFS(Data!$K:$K,Data!$A:$A,2023,Data!$B:$B,4,Data!$F:$F,"PADD 1") -> 110.08 | M8: =SUMIFS(Data!$K:$K,Data!$A:$A,2023,Data!$B:$B,4,Data!$F:$F,"PADD 2") -> 2007.8074 | N8: =SUMIFS(Data!$K:$K,Data!$A:$A,2023,Data!$B:$B,4,Data!$F:$F,"PADD 3") -> 2929.6089 | O8: =SUMIFS(Data!$K:$K,Data!$A:$A,2023,Data!$B:$B,4,Data!$F:$F,"PADD 4") -> 344.0876 | P8: =SUMIFS(Data!$K:$K,Data!$A:$A,2023,Data!$B:$B,4,Data!$F:$F,"PADD 5") -> 724.665 | Q8: =K8*ref_intake-H8*naph_yield -> -136.83325
A9: 2023 | B9: 5 | C9: May 23 | D9: =SUMIFS(Data!$K:$K,Data!$A:$A,2023,Data!$B:$B,5) -> 3819.9794 | E9: =SUMIFS(Data!$K:$K,Data!$A:$A,2023,Data!$B:$B,5,Data!$J:$J,"PLANNED") -> 2071.2518 | F9: =SUMIFS(Data!$K:$K,Data!$A:$A,2023,Data!$B:$B,5,Data!$J:$J,"UNPLANNED") -> 1748.7276 | G9: =IFERROR(F9/D9,0) -> 0.45778456 | H9: =SUMIFS(Data!$K:$K,Data!$A:$A,2023,Data!$B:$B,5,Data!$G:$G,"CDU") -> 1061.1038 | I9: =SUMIFS(Data!$K:$K,Data!$A:$A,2023,Data!$B:$B,5,Data!$G:$G,"FCC") -> 530.395 | J9: =SUMIFS(Data!$K:$K,Data!$A:$A,2023,Data!$B:$B,5,Data!$G:$G,"Hydrocracker") -> 158.444 | K9: =SUMIFS(Data!$K:$K,Data!$A:$A,2023,Data!$B:$B,5,Data!$G:$G,"Reformer") -> 360.457 | L9: =SUMIFS(Data!$K:$K,Data!$A:$A,2023,Data!$B:$B,5,Data!$F:$F,"PADD 1") -> 46.16 | M9: =SUMIFS(Data!$K:$K,Data!$A:$A,2023,Data!$B:$B,5,Data!$F:$F,"PADD 2") -> 1042.2436 | N9: =SUMIFS(Data!$K:$K,Data!$A:$A,2023,Data!$B:$B,5,Data!$F:$F,"PADD 3") -> 2020.7778 | O9: =SUMIFS(Data!$K:$K,Data!$A:$A,2023,Data!$B:$B,5,Data!$F:$F,"PADD 4") -> 228.289 | P9: =SUMIFS(Data!$K:$K,Data!$A:$A,2023,Data!$B:$B,5,Data!$F:$F,"PADD 5") -> 482.509 | Q9: =K9*ref_intake-H9*naph_yield -> -10.92933
A10: 2023 | B10: 6 | C10: Jun 23 | D10: =SUMIFS(Data!$K:$K,Data!$A:$A,2023,Data!$B:$B,6) -> 2342.9731 | E10: =SUMIFS(Data!$K:$K,Data!$A:$A,2023,Data!$B:$B,6,Data!$J:$J,"PLANNED") -> 368.477 | F10: =SUMIFS(Data!$K:$K,Data!$A:$A,2023,Data!$B:$B,6,Data!$J:$J,"UNPLANNED") -> 1974.4961 | G10: =IFERROR(F10/D10,0) -> 0.84273102 | H10: =SUMIFS(Data!$K:$K,Data!$A:$A,2023,Data!$B:$B,6,Data!$G:$G,"CDU") -> 794.9545 | I10: =SUMIFS(Data!$K:$K,Data!$A:$A,2023,Data!$B:$B,6,Data!$G:$G,"FCC") -> 406.9475 | J10: =SUMIFS(Data!$K:$K,Data!$A:$A,2023,Data!$B:$B,6,Data!$G:$G,"Hydrocracker") -> 11.7462 | K10: =SUMIFS(Data!$K:$K,Data!$A:$A,2023,Data!$B:$B,6,Data!$G:$G,"Reformer") -> 198.97 | L10: =SUMIFS(Data!$K:$K,Data!$A:$A,2023,Data!$B:$B,6,Data!$F:$F,"PADD 1") -> 316.8375 | M10: =SUMIFS(Data!$K:$K,Data!$A:$A,2023,Data!$B:$B,6,Data!$F:$F,"PADD 2") -> 511.95 | N10: =SUMIFS(Data!$K:$K,Data!$A:$A,2023,Data!$B:$B,6,Data!$F:$F,"PADD 3") -> 1420.2069 | O10: =SUMIFS(Data!$K:$K,Data!$A:$A,2023,Data!$B:$B,6,Data!$F:$F,"PADD 4") -> 53.3175 | P10: =SUMIFS(Data!$K:$K,Data!$A:$A,2023,Data!$B:$B,6,Data!$F:$F,"PADD 5") -> 40.6612 | Q10: =K10*ref_intake-H10*naph_yield -> -79.264075
A11: 2023 | B11: 7 | C11: Jul 23 | D11: =SUMIFS(Data!$K:$K,Data!$A:$A,2023,Data!$B:$B,7) -> 1647.0638 | E11: =SUMIFS(Data!$K:$K,Data!$A:$A,2023,Data!$B:$B,7,Data!$J:$J,"PLANNED") -> 171.937 | F11: =SUMIFS(Data!$K:$K,Data!$A:$A,2023,Data!$B:$B,7,Data!$J:$J,"UNPLANNED") -> 1475.1268 | G11: =IFERROR(F11/D11,0) -> 0.89560999 | H11: =SUMIFS(Data!$K:$K,Data!$A:$A,2023,Data!$B:$B,7,Data!$G:$G,"CDU") -> 510.65 | I11: =SUMIFS(Data!$K:$K,Data!$A:$A,2023,Data!$B:$B,7,Data!$G:$G,"FCC") -> 232.66 | J11: =SUMIFS(Data!$K:$K,Data!$A:$A,2023,Data!$B:$B,7,Data!$G:$G,"Hydrocracker") -> 40.6884 | K11: =SUMIFS(Data!$K:$K,Data!$A:$A,2023,Data!$B:$B,7,Data!$G:$G,"Reformer") -> 147.233 | L11: =SUMIFS(Data!$K:$K,Data!$A:$A,2023,Data!$B:$B,7,Data!$F:$F,"PADD 1") -> 283.35 | M11: =SUMIFS(Data!$K:$K,Data!$A:$A,2023,Data!$B:$B,7,Data!$F:$F,"PADD 2") -> 453.487 | N11: =SUMIFS(Data!$K:$K,Data!$A:$A,2023,Data!$B:$B,7,Data!$F:$F,"PADD 3") -> 772.8094 | O11: =SUMIFS(Data!$K:$K,Data!$A:$A,2023,Data!$B:$B,7,Data!$F:$F,"PADD 4") -> 40.651 | P11: =SUMIFS(Data!$K:$K,Data!$A:$A,2023,Data!$B:$B,7,Data!$F:$F,"PADD 5") -> 96.7664 | Q11: =K11*ref_intake-H11*naph_yield -> -31.4945
A12: 2023 | B12: 8 | C12: Aug 23 | D12: =SUMIFS(Data!$K:$K,Data!$A:$A,2023,Data!$B:$B,8) -> 1761.651 | E12: =SUMIFS(Data!$K:$K,Data!$A:$A,2023,Data!$B:$B,8,Data!$J:$J,"PLANNED") -> 315.56 | F12: =SUMIFS(Data!$K:$K,Data!$A:$A,2023,Data!$B:$B,8,Data!$J:$J,"UNPLANNED") -> 1446.091 | G12: =IFERROR(F12/D12,0) -> 0.82087258 | H12: =SUMIFS(Data!$K:$K,Data!$A:$A,2023,Data!$B:$B,8,Data!$G:$G,"CDU") -> 510.13 | I12: =SUMIFS(Data!$K:$K,Data!$A:$A,2023,Data!$B:$B,8,Data!$G:$G,"FCC") -> 161.055 | J12: =SUMIFS(Data!$K:$K,Data!$A:$A,2023,Data!$B:$B,8,Data!$G:$G,"Hydrocracker") -> 64.313 | K12: =SUMIFS(Data!$K:$K,Data!$A:$A,2023,Data!$B:$B,8,Data!$G:$G,"Reformer") -> 238.18 | L12: =SUMIFS(Data!$K:$K,Data!$A:$A,2023,Data!$B:$B,8,Data!$F:$F,"PADD 1") -> 2.6 | M12: =SUMIFS(Data!$K:$K,Data!$A:$A,2023,Data!$B:$B,8,Data!$F:$F,"PADD 2") -> 182.999 | N12: =SUMIFS(Data!$K:$K,Data!$A:$A,2023,Data!$B:$B,8,Data!$F:$F,"PADD 3") -> 1367.907 | O12: =SUMIFS(Data!$K:$K,Data!$A:$A,2023,Data!$B:$B,8,Data!$F:$F,"PADD 4") -> 76.8 | P12: =SUMIFS(Data!$K:$K,Data!$A:$A,2023,Data!$B:$B,8,Data!$F:$F,"PADD 5") -> 131.345 | Q12: =K12*ref_intake-H12*naph_yield -> 59.6345
A13: 2023 | B13: 9 | C13: Sep 23 | D13: =SUMIFS(Data!$K:$K,Data!$A:$A,2023,Data!$B:$B,9) -> 3954.8585 | E13: =SUMIFS(Data!$K:$K,Data!$A:$A,2023,Data!$B:$B,9,Data!$J:$J,"PLANNED") -> 2423.3365 | F13: =SUMIFS(Data!$K:$K,Data!$A:$A,2023,Data!$B:$B,9,Data!$J:$J,"UNPLANNED") -> 1531.522 | G13: =IFERROR(F13/D13,0) -> 0.38725077 | H13: =SUMIFS(Data!$K:$K,Data!$A:$A,2023,Data!$B:$B,9,Data!$G:$G,"CDU") -> 1099.23 | I13: =SUMIFS(Data!$K:$K,Data!$A:$A,2023,Data!$B:$B,9,Data!$G:$G,"FCC") -> 407.94 | J13: =SUMIFS(Data!$K:$K,Data!$A:$A,2023,Data!$B:$B,9,Data!$G:$G,"Hydrocracker") -> 85.565 | K13: =SUMIFS(Data!$K:$K,Data!$A:$A,2023,Data!$B:$B,9,Data!$G:$G,"Reformer") -> 236.457 | L13: =SUMIFS(Data!$K:$K,Data!$A:$A,2023,Data!$B:$B,9,Data!$F:$F,"PADD 1") -> 391.5052 | M13: =SUMIFS(Data!$K:$K,Data!$A:$A,2023,Data!$B:$B,9,Data!$F:$F,"PADD 2") -> 1481.1244 | N13: =SUMIFS(Data!$K:$K,Data!$A:$A,2023,Data!$B:$B,9,Data!$F:$F,"PADD 3") -> 1980.1739 | O13: =SUMIFS(Data!$K:$K,Data!$A:$A,2023,Data!$B:$B,9,Data!$F:$F,"PADD 4") -> 0 | P13: =SUMIFS(Data!$K:$K,Data!$A:$A,2023,Data!$B:$B,9,Data!$F:$F,"PADD 5") -> 102.055 | Q13: =K13*ref_intake-H13*naph_yield -> -148.2735
A14: 2023 | B14: 10 | C14: Oct 23 | D14: =SUMIFS(Data!$K:$K,Data!$A:$A,2023,Data!$B:$B,10) -> 6931.9118 | E14: =SUMIFS(Data!$K:$K,Data!$A:$A,2023,Data!$B:$B,10,Data!$J:$J,"PLANNED") -> 4943.1683 | F14: =SUMIFS(Data!$K:$K,Data!$A:$A,2023,Data!$B:$B,10,Data!$J:$J,"UNPLANNED") -> 1988.7435 | G14: =IFERROR(F14/D14,0) -> 0.28689683 | H14: =SUMIFS(Data!$K:$K,Data!$A:$A,2023,Data!$B:$B,10,Data!$G:$G,"CDU") -> 2033.6085 | I14: =SUMIFS(Data!$K:$K,Data!$A:$A,2023,Data!$B:$B,10,Data!$G:$G,"FCC") -> 590.53 | J14: =SUMIFS(Data!$K:$K,Data!$A:$A,2023,Data!$B:$B,10,Data!$G:$G,"Hydrocracker") -> 169.43 | K14: =SUMIFS(Data!$K:$K,Data!$A:$A,2023,Data!$B:$B,10,Data!$G:$G,"Reformer") -> 529.1175 | L14: =SUMIFS(Data!$K:$K,Data!$A:$A,2023,Data!$B:$B,10,Data!$F:$F,"PADD 1") -> 695.69 | M14: =SUMIFS(Data!$K:$K,Data!$A:$A,2023,Data!$B:$B,10,Data!$F:$F,"PADD 2") -> 1816.5088 | N14: =SUMIFS(Data!$K:$K,Data!$A:$A,2023,Data!$B:$B,10,Data!$F:$F,"PADD 3") -> 3552.627 | O14: =SUMIFS(Data!$K:$K,Data!$A:$A,2023,Data!$B:$B,10,Data!$F:$F,"PADD 4") -> 2.726 | P14: =SUMIFS(Data!$K:$K,Data!$A:$A,2023,Data!$B:$B,10,Data!$F:$F,"PADD 5") -> 864.36 | Q14: =K14*ref_intake-H14*naph_yield -> -182.64548
A15: 2023 | B15: 11 | C15: Nov 23 | D15: =SUMIFS(Data!$K:$K,Data!$A:$A,2023,Data!$B:$B,11) -> 3069.4329 | E15: =SUMIFS(Data!$K:$K,Data!$A:$A,2023,Data!$B:$B,11,Data!$J:$J,"PLANNED") -> 1718.509 | F15: =SUMIFS(Data!$K:$K,Data!$A:$A,2023,Data!$B:$B,11,Data!$J:$J,"UNPLANNED") -> 1350.9239 | G15: =IFERROR(F15/D15,0) -> 0.44012166 | H15: =SUMIFS(Data!$K:$K,Data!$A:$A,2023,Data!$B:$B,11,Data!$G:$G,"CDU") -> 881.06 | I15: =SUMIFS(Data!$K:$K,Data!$A:$A,2023,Data!$B:$B,11,Data!$G:$G,"FCC") -> 347.605 | J15: =SUMIFS(Data!$K:$K,Data!$A:$A,2023,Data!$B:$B,11,Data!$G:$G,"Hydrocracker") -> 66.22 | K15: =SUMIFS(Data!$K:$K,Data!$A:$A,2023,Data!$B:$B,11,Data!$G:$G,"Reformer") -> 371.958 | L15: =SUMIFS(Data!$K:$K,Data!$A:$A,2023,Data!$B:$B,11,Data!$F:$F,"PADD 1") -> 256.507 | M15: =SUMIFS(Data!$K:$K,Data!$A:$A,2023,Data!$B:$B,11,Data!$F:$F,"PADD 2") -> 326.1729 | N15: =SUMIFS(Data!$K:$K,Data!$A:$A,2023,Data!$B:$B,11,Data!$F:$F,"PADD 3") -> 1809.522 | O15: =SUMIFS(Data!$K:$K,Data!$A:$A,2023,Data!$B:$B,11,Data!$F:$F,"PADD 4") -> 18.951 | P15: =SUMIFS(Data!$K:$K,Data!$A:$A,2023,Data!$B:$B,11,Data!$F:$F,"PADD 5") -> 658.28 | Q15: =K15*ref_intake-H15*naph_yield -> 63.587
A16: 2023 | B16: 12 | C16: Dec 23 | D16: =SUMIFS(Data!$K:$K,Data!$A:$A,2023,Data!$B:$B,12) -> 976.1005 | E16: =SUMIFS(Data!$K:$K,Data!$A:$A,2023,Data!$B:$B,12,Data!$J:$J,"PLANNED") -> 128.5582 | F16: =SUMIFS(Data!$K:$K,Data!$A:$A,2023,Data!$B:$B,12,Data!$J:$J,"UNPLANNED") -> 847.5423 | G16: =IFERROR(F16/D16,0) -> 0.86829409 | H16: =SUMIFS(Data!$K:$K,Data!$A:$A,2023,Data!$B:$B,12,Data!$G:$G,"CDU") -> 256.08 | I16: =SUMIFS(Data!$K:$K,Data!$A:$A,2023,Data!$B:$B,12,Data!$G:$G,"FCC") -> 152.404 | J16: =SUMIFS(Data!$K:$K,Data!$A:$A,2023,Data!$B:$B,12,Data!$G:$G,"Hydrocracker") -> 60.28 | K16: =SUMIFS(Data!$K:$K,Data!$A:$A,2023,Data!$B:$B,12,Data!$G:$G,"Reformer") -> 67.175 | L16: =SUMIFS(Data!$K:$K,Data!$A:$A,2023,Data!$B:$B,12,Data!$F:$F,"PADD 1") -> 30.79 | M16: =SUMIFS(Data!$K:$K,Data!$A:$A,2023,Data!$B:$B,12,Data!$F:$F,"PADD 2") -> 60.5386 | N16: =SUMIFS(Data!$K:$K,Data!$A:$A,2023,Data!$B:$B,12,Data!$F:$F,"PADD 3") -> 541.6272 | O16: =SUMIFS(Data!$K:$K,Data!$A:$A,2023,Data!$B:$B,12,Data!$F:$F,"PADD 4") -> 111.2157 | P16: =SUMIFS(Data!$K:$K,Data!$A:$A,2023,Data!$B:$B,12,Data!$F:$F,"PADD 5") -> 231.929 | Q16: =K16*ref_intake-H16*naph_yield -> -22.453
A17: 2024 | B17: 1 | C17: Jan 24 | D17: =SUMIFS(Data!$K:$K,Data!$A:$A,2024,Data!$B:$B,1) -> 4684.8428 | E17: =SUMIFS(Data!$K:$K,Data!$A:$A,2024,Data!$B:$B,1,Data!$J:$J,"PLANNED") -> 2251.219 | F17: =SUMIFS(Data!$K:$K,Data!$A:$A,2024,Data!$B:$B,1,Data!$J:$J,"UNPLANNED") -> 2433.6238 | G17: =IFERROR(F17/D17,0) -> 0.51946755 | H17: =SUMIFS(Data!$K:$K,Data!$A:$A,2024,Data!$B:$B,1,Data!$G:$G,"CDU") -> 1313.892 | I17: =SUMIFS(Data!$K:$K,Data!$A:$A,2024,Data!$B:$B,1,Data!$G:$G,"FCC") -> 313.199 | J17: =SUMIFS(Data!$K:$K,Data!$A:$A,2024,Data!$B:$B,1,Data!$G:$G,"Hydrocracker") -> 248.172 | K17: =SUMIFS(Data!$K:$K,Data!$A:$A,2024,Data!$B:$B,1,Data!$G:$G,"Reformer") -> 436.8612 | L17: =SUMIFS(Data!$K:$K,Data!$A:$A,2024,Data!$B:$B,1,Data!$F:$F,"PADD 1") -> 99.0698 | M17: =SUMIFS(Data!$K:$K,Data!$A:$A,2024,Data!$B:$B,1,Data!$F:$F,"PADD 2") -> 82.622 | N17: =SUMIFS(Data!$K:$K,Data!$A:$A,2024,Data!$B:$B,1,Data!$F:$F,"PADD 3") -> 3897.7506 | O17: =SUMIFS(Data!$K:$K,Data!$A:$A,2024,Data!$B:$B,1,Data!$F:$F,"PADD 4") -> 71.7204 | P17: =SUMIFS(Data!$K:$K,Data!$A:$A,2024,Data!$B:$B,1,Data!$F:$F,"PADD 5") -> 533.68 | Q17: =K17*ref_intake-H17*naph_yield -> -23.001
A18: 2024 | B18: 2 | C18: Feb 24 | D18: =SUMIFS(Data!$K:$K,Data!$A:$A,2024,Data!$B:$B,2) -> 8792.021 | E18: =SUMIFS(Data!$K:$K,Data!$A:$A,2024,Data!$B:$B,2,Data!$J:$J,"PLANNED") -> 3766.8788 | F18: =SUMIFS(Data!$K:$K,Data!$A:$A,2024,Data!$B:$B,2,Data!$J:$J,"UNPLANNED") -> 5025.1422 | G18: =IFERROR(F18/D18,0) -> 0.57155712 | H18: =SUMIFS(Data!$K:$K,Data!$A:$A,2024,Data!$B:$B,2,Data!$G:$G,"CDU") -> 2142.5348 | I18: =SUMIFS(Data!$K:$K,Data!$A:$A,2024,Data!$B:$B,2,Data!$G:$G,"FCC") -> 1054.9718 | J18: =SUMIFS(Data!$K:$K,Data!$A:$A,2024,Data!$B:$B,2,Data!$G:$G,"Hydrocracker") -> 429.613 | K18: =SUMIFS(Data!$K:$K,Data!$A:$A,2024,Data!$B:$B,2,Data!$G:$G,"Reformer") -> 843.04 | L18: =SUMIFS(Data!$K:$K,Data!$A:$A,2024,Data!$B:$B,2,Data!$F:$F,"PADD 1") -> 62.445 | M18: =SUMIFS(Data!$K:$K,Data!$A:$A,2024,Data!$B:$B,2,Data!$F:$F,"PADD 2") -> 1893.1044 | N18: =SUMIFS(Data!$K:$K,Data!$A:$A,2024,Data!$B:$B,2,Data!$F:$F,"PADD 3") -> 5540.9283 | O18: =SUMIFS(Data!$K:$K,Data!$A:$A,2024,Data!$B:$B,2,Data!$F:$F,"PADD 4") -> 226.08 | P18: =SUMIFS(Data!$K:$K,Data!$A:$A,2024,Data!$B:$B,2,Data!$F:$F,"PADD 5") -> 1069.4633 | Q18: =K18*ref_intake-H18*naph_yield -> 93.15282
A19: 2024 | B19: 3 | C19: Mar 24 | D19: =SUMIFS(Data!$K:$K,Data!$A:$A,2024,Data!$B:$B,3) -> 4695.105 | E19: =SUMIFS(Data!$K:$K,Data!$A:$A,2024,Data!$B:$B,3,Data!$J:$J,"PLANNED") -> 2643.9494 | F19: =SUMIFS(Data!$K:$K,Data!$A:$A,2024,Data!$B:$B,3,Data!$J:$J,"UNPLANNED") -> 2051.1556 | G19: =IFERROR(F19/D19,0) -> 0.43687108 | H19: =SUMIFS(Data!$K:$K,Data!$A:$A,2024,Data!$B:$B,3,Data!$G:$G,"CDU") -> 1268.1126 | I19: =SUMIFS(Data!$K:$K,Data!$A:$A,2024,Data!$B:$B,3,Data!$G:$G,"FCC") -> 579.138 | J19: =SUMIFS(Data!$K:$K,Data!$A:$A,2024,Data!$B:$B,3,Data!$G:$G,"Hydrocracker") -> 305.265 | K19: =SUMIFS(Data!$K:$K,Data!$A:$A,2024,Data!$B:$B,3,Data!$G:$G,"Reformer") -> 439.2958 | L19: =SUMIFS(Data!$K:$K,Data!$A:$A,2024,Data!$B:$B,3,Data!$F:$F,"PADD 1") -> 236.6964 | M19: =SUMIFS(Data!$K:$K,Data!$A:$A,2024,Data!$B:$B,3,Data!$F:$F,"PADD 2") -> 1347.1691 | N19: =SUMIFS(Data!$K:$K,Data!$A:$A,2024,Data!$B:$B,3,Data!$F:$F,"PADD 3") -> 2248.1637 | O19: =SUMIFS(Data!$K:$K,Data!$A:$A,2024,Data!$B:$B,3,Data!$F:$F,"PADD 4") -> 244.3878 | P19: =SUMIFS(Data!$K:$K,Data!$A:$A,2024,Data!$B:$B,3,Data!$F:$F,"PADD 5") -> 618.688 | Q19: =K19*ref_intake-H19*naph_yield -> -4.54361
A20: 2024 | B20: 4 | C20: Apr 24 | D20: =SUMIFS(Data!$K:$K,Data!$A:$A,2024,Data!$B:$B,4) -> 4532.5513 | E20: =SUMIFS(Data!$K:$K,Data!$A:$A,2024,Data!$B:$B,4,Data!$J:$J,"PLANNED") -> 2651.0149 | F20: =SUMIFS(Data!$K:$K,Data!$A:$A,2024,Data!$B:$B,4,Data!$J:$J,"UNPLANNED") -> 1881.5364 | G20: =IFERROR(F20/D20,0) -> 0.4151164 | H20: =SUMIFS(Data!$K:$K,Data!$A:$A,2024,Data!$B:$B,4,Data!$G:$G,"CDU") -> 1440.7505 | I20: =SUMIFS(Data!$K:$K,Data!$A:$A,2024,Data!$B:$B,4,Data!$G:$G,"FCC") -> 489.937 | J20: =SUMIFS(Data!$K:$K,Data!$A:$A,2024,Data!$B:$B,4,Data!$G:$G,"Hydrocracker") -> 142.443 | K20: =SUMIFS(Data!$K:$K,Data!$A:$A,2024,Data!$B:$B,4,Data!$G:$G,"Reformer") -> 470.9954 | L20: =SUMIFS(Data!$K:$K,Data!$A:$A,2024,Data!$B:$B,4,Data!$F:$F,"PADD 1") -> 214.8537 | M20: =SUMIFS(Data!$K:$K,Data!$A:$A,2024,Data!$B:$B,4,Data!$F:$F,"PADD 2") -> 1456.5636 | N20: =SUMIFS(Data!$K:$K,Data!$A:$A,2024,Data!$B:$B,4,Data!$F:$F,"PADD 3") -> 2012.658 | O20: =SUMIFS(Data!$K:$K,Data!$A:$A,2024,Data!$B:$B,4,Data!$F:$F,"PADD 4") -> 138.769 | P20: =SUMIFS(Data!$K:$K,Data!$A:$A,2024,Data!$B:$B,4,Data!$F:$F,"PADD 5") -> 709.707 | Q20: =K20*ref_intake-H20*naph_yield -> -33.267275
A21: 2024 | B21: 5 | C21: May 24 | D21: =SUMIFS(Data!$K:$K,Data!$A:$A,2024,Data!$B:$B,5) -> 2481.8625 | E21: =SUMIFS(Data!$K:$K,Data!$A:$A,2024,Data!$B:$B,5,Data!$J:$J,"PLANNED") -> 1541.172 | F21: =SUMIFS(Data!$K:$K,Data!$A:$A,2024,Data!$B:$B,5,Data!$J:$J,"UNPLANNED") -> 940.6905 | G21: =IFERROR(F21/D21,0) -> 0.37902603 | H21: =SUMIFS(Data!$K:$K,Data!$A:$A,2024,Data!$B:$B,5,Data!$G:$G,"CDU") -> 501.391 | I21: =SUMIFS(Data!$K:$K,Data!$A:$A,2024,Data!$B:$B,5,Data!$G:$G,"FCC") -> 277.135 | J21: =SUMIFS(Data!$K:$K,Data!$A:$A,2024,Data!$B:$B,5,Data!$G:$G,"Hydrocracker") -> 153.69 | K21: =SUMIFS(Data!$K:$K,Data!$A:$A,2024,Data!$B:$B,5,Data!$G:$G,"Reformer") -> 285.8775 | L21: =SUMIFS(Data!$K:$K,Data!$A:$A,2024,Data!$B:$B,5,Data!$F:$F,"PADD 1") -> 23.4 | M21: =SUMIFS(Data!$K:$K,Data!$A:$A,2024,Data!$B:$B,5,Data!$F:$F,"PADD 2") -> 670.5625 | N21: =SUMIFS(Data!$K:$K,Data!$A:$A,2024,Data!$B:$B,5,Data!$F:$F,"PADD 3") -> 1141.365 | O21: =SUMIFS(Data!$K:$K,Data!$A:$A,2024,Data!$B:$B,5,Data!$F:$F,"PADD 4") -> 31.459 | P21: =SUMIFS(Data!$K:$K,Data!$A:$A,2024,Data!$B:$B,5,Data!$F:$F,"PADD 5") -> 615.076 | Q21: =K21*ref_intake-H21*naph_yield -> 110.39065
A22: 2024 | B22: 6 | C22: Jun 24 | D22: =SUMIFS(Data!$K:$K,Data!$A:$A,2024,Data!$B:$B,6) -> 2108.9555 | E22: =SUMIFS(Data!$K:$K,Data!$A:$A,2024,Data!$B:$B,6,Data!$J:$J,"PLANNED") -> 1085.2415 | F22: =SUMIFS(Data!$K:$K,Data!$A:$A,2024,Data!$B:$B,6,Data!$J:$J,"UNPLANNED") -> 1023.714 | G22: =IFERROR(F22/D22,0) -> 0.4854128 | H22: =SUMIFS(Data!$K:$K,Data!$A:$A,2024,Data!$B:$B,6,Data!$G:$G,"CDU") -> 455.03 | I22: =SUMIFS(Data!$K:$K,Data!$A:$A,2024,Data!$B:$B,6,Data!$G:$G,"FCC") -> 334.165 | J22: =SUMIFS(Data!$K:$K,Data!$A:$A,2024,Data!$B:$B,6,Data!$G:$G,"Hydrocracker") -> 81.81 | K22: =SUMIFS(Data!$K:$K,Data!$A:$A,2024,Data!$B:$B,6,Data!$G:$G,"Reformer") -> 303.314 | L22: =SUMIFS(Data!$K:$K,Data!$A:$A,2024,Data!$B:$B,6,Data!$F:$F,"PADD 1") -> 1.82 | M22: =SUMIFS(Data!$K:$K,Data!$A:$A,2024,Data!$B:$B,6,Data!$F:$F,"PADD 2") -> 364.397 | N22: =SUMIFS(Data!$K:$K,Data!$A:$A,2024,Data!$B:$B,6,Data!$F:$F,"PADD 3") -> 1180.7915 | O22: =SUMIFS(Data!$K:$K,Data!$A:$A,2024,Data!$B:$B,6,Data!$F:$F,"PADD 4") -> 17.778 | P22: =SUMIFS(Data!$K:$K,Data!$A:$A,2024,Data!$B:$B,6,Data!$F:$F,"PADD 5") -> 544.169 | Q22: =K22*ref_intake-H22*naph_yield -> 144.0535
A23: 2024 | B23: 7 | C23: Jul 24 | D23: =SUMIFS(Data!$K:$K,Data!$A:$A,2024,Data!$B:$B,7) -> 1985.748 | E23: =SUMIFS(Data!$K:$K,Data!$A:$A,2024,Data!$B:$B,7,Data!$J:$J,"PLANNED") -> 512.8795 | F23: =SUMIFS(Data!$K:$K,Data!$A:$A,2024,Data!$B:$B,7,Data!$J:$J,"UNPLANNED") -> 1472.8685 | G23: =IFERROR(F23/D23,0) -> 0.74171974 | H23: =SUMIFS(Data!$K:$K,Data!$A:$A,2024,Data!$B:$B,7,Data!$G:$G,"CDU") -> 646.83 | I23: =SUMIFS(Data!$K:$K,Data!$A:$A,2024,Data!$B:$B,7,Data!$G:$G,"FCC") -> 356.206 | J23: =SUMIFS(Data!$K:$K,Data!$A:$A,2024,Data!$B:$B,7,Data!$G:$G,"Hydrocracker") -> 44.115 | K23: =SUMIFS(Data!$K:$K,Data!$A:$A,2024,Data!$B:$B,7,Data!$G:$G,"Reformer") -> 129.5725 | L23: =SUMIFS(Data!$K:$K,Data!$A:$A,2024,Data!$B:$B,7,Data!$F:$F,"PADD 1") -> 75.05 | M23: =SUMIFS(Data!$K:$K,Data!$A:$A,2024,Data!$B:$B,7,Data!$F:$F,"PADD 2") -> 802.508 | N23: =SUMIFS(Data!$K:$K,Data!$A:$A,2024,Data!$B:$B,7,Data!$F:$F,"PADD 3") -> 1019.787 | O23: =SUMIFS(Data!$K:$K,Data!$A:$A,2024,Data!$B:$B,7,Data!$F:$F,"PADD 4") -> 23.131 | P23: =SUMIFS(Data!$K:$K,Data!$A:$A,2024,Data!$B:$B,7,Data!$F:$F,"PADD 5") -> 65.272 | Q23: =K23*ref_intake-H23*naph_yield -> -96.818
A24: 2024 | B24: 8 | C24: Aug 24 | D24: =SUMIFS(Data!$K:$K,Data!$A:$A,2024,Data!$B:$B,8) -> 1698.4168 | E24: =SUMIFS(Data!$K:$K,Data!$A:$A,2024,Data!$B:$B,8,Data!$J:$J,"PLANNED") -> 486.4172 | F24: =SUMIFS(Data!$K:$K,Data!$A:$A,2024,Data!$B:$B,8,Data!$J:$J,"UNPLANNED") -> 1211.9996 | G24: =IFERROR(F24/D24,0) -> 0.71360552 | H24: =SUMIFS(Data!$K:$K,Data!$A:$A,2024,Data!$B:$B,8,Data!$G:$G,"CDU") -> 550.098 | I24: =SUMIFS(Data!$K:$K,Data!$A:$A,2024,Data!$B:$B,8,Data!$G:$G,"FCC") -> 309.4394 | J24: =SUMIFS(Data!$K:$K,Data!$A:$A,2024,Data!$B:$B,8,Data!$G:$G,"Hydrocracker") -> 39.24 | K24: =SUMIFS(Data!$K:$K,Data!$A:$A,2024,Data!$B:$B,8,Data!$G:$G,"Reformer") -> 149.935 | L24: =SUMIFS(Data!$K:$K,Data!$A:$A,2024,Data!$B:$B,8,Data!$F:$F,"PADD 1") -> 10.9 | M24: =SUMIFS(Data!$K:$K,Data!$A:$A,2024,Data!$B:$B,8,Data!$F:$F,"PADD 2") -> 516.3492 | N24: =SUMIFS(Data!$K:$K,Data!$A:$A,2024,Data!$B:$B,8,Data!$F:$F,"PADD 3") -> 1019.9182 | O24: =SUMIFS(Data!$K:$K,Data!$A:$A,2024,Data!$B:$B,8,Data!$F:$F,"PADD 4") -> 38.4844 | P24: =SUMIFS(Data!$K:$K,Data!$A:$A,2024,Data!$B:$B,8,Data!$F:$F,"PADD 5") -> 112.765 | Q24: =K24*ref_intake-H24*naph_yield -> -42.5993
A25: 2024 | B25: 9 | C25: Sep 24 | D25: =SUMIFS(Data!$K:$K,Data!$A:$A,2024,Data!$B:$B,9) -> 3566.3252 | E25: =SUMIFS(Data!$K:$K,Data!$A:$A,2024,Data!$B:$B,9,Data!$J:$J,"PLANNED") -> 1721.3308 | F25: =SUMIFS(Data!$K:$K,Data!$A:$A,2024,Data!$B:$B,9,Data!$J:$J,"UNPLANNED") -> 1844.9944 | G25: =IFERROR(F25/D25,0) -> 0.51733768 | H25: =SUMIFS(Data!$K:$K,Data!$A:$A,2024,Data!$B:$B,9,Data!$G:$G,"CDU") -> 1090.8784 | I25: =SUMIFS(Data!$K:$K,Data!$A:$A,2024,Data!$B:$B,9,Data!$G:$G,"FCC") -> 652.189 | J25: =SUMIFS(Data!$K:$K,Data!$A:$A,2024,Data!$B:$B,9,Data!$G:$G,"Hydrocracker") -> 212.99 | K25: =SUMIFS(Data!$K:$K,Data!$A:$A,2024,Data!$B:$B,9,Data!$G:$G,"Reformer") -> 319.02 | L25: =SUMIFS(Data!$K:$K,Data!$A:$A,2024,Data!$B:$B,9,Data!$F:$F,"PADD 1") -> 87.2639 | M25: =SUMIFS(Data!$K:$K,Data!$A:$A,2024,Data!$B:$B,9,Data!$F:$F,"PADD 2") -> 1029.2768 | N25: =SUMIFS(Data!$K:$K,Data!$A:$A,2024,Data!$B:$B,9,Data!$F:$F,"PADD 3") -> 1784.1745 | O25: =SUMIFS(Data!$K:$K,Data!$A:$A,2024,Data!$B:$B,9,Data!$F:$F,"PADD 4") -> 131.881 | P25: =SUMIFS(Data!$K:$K,Data!$A:$A,2024,Data!$B:$B,9,Data!$F:$F,"PADD 5") -> 533.729 | Q25: =K25*ref_intake-H25*naph_yield -> -62.78744
A26: 2024 | B26: 10 | C26: Oct 24 | D26: =SUMIFS(Data!$K:$K,Data!$A:$A,2024,Data!$B:$B,10) -> 4409.9705 | E26: =SUMIFS(Data!$K:$K,Data!$A:$A,2024,Data!$B:$B,10,Data!$J:$J,"PLANNED") -> 2469.8125 | F26: =SUMIFS(Data!$K:$K,Data!$A:$A,2024,Data!$B:$B,10,Data!$J:$J,"UNPLANNED") -> 1940.158 | G26: =IFERROR(F26/D26,0) -> 0.43994807 | H26: =SUMIFS(Data!$K:$K,Data!$A:$A,2024,Data!$B:$B,10,Data!$G:$G,"CDU") -> 1122.32 | I26: =SUMIFS(Data!$K:$K,Data!$A:$A,2024,Data!$B:$B,10,Data!$G:$G,"FCC") -> 453.501 | J26: =SUMIFS(Data!$K:$K,Data!$A:$A,2024,Data!$B:$B,10,Data!$G:$G,"Hydrocracker") -> 245.08 | K26: =SUMIFS(Data!$K:$K,Data!$A:$A,2024,Data!$B:$B,10,Data!$G:$G,"Reformer") -> 587.828 | L26: =SUMIFS(Data!$K:$K,Data!$A:$A,2024,Data!$B:$B,10,Data!$F:$F,"PADD 1") -> 154.0685 | M26: =SUMIFS(Data!$K:$K,Data!$A:$A,2024,Data!$B:$B,10,Data!$F:$F,"PADD 2") -> 1512.466 | N26: =SUMIFS(Data!$K:$K,Data!$A:$A,2024,Data!$B:$B,10,Data!$F:$F,"PADD 3") -> 2036.786 | O26: =SUMIFS(Data!$K:$K,Data!$A:$A,2024,Data!$B:$B,10,Data!$F:$F,"PADD 4") -> 58.955 | P26: =SUMIFS(Data!$K:$K,Data!$A:$A,2024,Data!$B:$B,10,Data!$F:$F,"PADD 5") -> 647.695 | Q26: =K26*ref_intake-H26*naph_yield -> 195.016
A27: 2024 | B27: 11 | C27: Nov 24 | D27: =SUMIFS(Data!$K:$K,Data!$A:$A,2024,Data!$B:$B,11) -> 2230.0646 | E27: =SUMIFS(Data!$K:$K,Data!$A:$A,2024,Data!$B:$B,11,Data!$J:$J,"PLANNED") -> 1183.0576 | F27: =SUMIFS(Data!$K:$K,Data!$A:$A,2024,Data!$B:$B,11,Data!$J:$J,"UNPLANNED") -> 1047.007 | G27: =IFERROR(F27/D27,0) -> 0.46949626 | H27: =SUMIFS(Data!$K:$K,Data!$A:$A,2024,Data!$B:$B,11,Data!$G:$G,"CDU") -> 715.6 | I27: =SUMIFS(Data!$K:$K,Data!$A:$A,2024,Data!$B:$B,11,Data!$G:$G,"FCC") -> 153.011 | J27: =SUMIFS(Data!$K:$K,Data!$A:$A,2024,Data!$B:$B,11,Data!$G:$G,"Hydrocracker") -> 91.11 | K27: =SUMIFS(Data!$K:$K,Data!$A:$A,2024,Data!$B:$B,11,Data!$G:$G,"Reformer") -> 228.1725 | L27: =SUMIFS(Data!$K:$K,Data!$A:$A,2024,Data!$B:$B,11,Data!$F:$F,"PADD 1") -> 159.3301 | M27: =SUMIFS(Data!$K:$K,Data!$A:$A,2024,Data!$B:$B,11,Data!$F:$F,"PADD 2") -> 525.778 | N27: =SUMIFS(Data!$K:$K,Data!$A:$A,2024,Data!$B:$B,11,Data!$F:$F,"PADD 3") -> 1212.9515 | O27: =SUMIFS(Data!$K:$K,Data!$A:$A,2024,Data!$B:$B,11,Data!$F:$F,"PADD 4") -> 6.975 | P27: =SUMIFS(Data!$K:$K,Data!$A:$A,2024,Data!$B:$B,11,Data!$F:$F,"PADD 5") -> 325.03 | Q27: =K27*ref_intake-H27*naph_yield -> -22.2875
A28: 2024 | B28: 12 | C28: Dec 24 | D28: =SUMIFS(Data!$K:$K,Data!$A:$A,2024,Data!$B:$B,12) -> 779.1993 | E28: =SUMIFS(Data!$K:$K,Data!$A:$A,2024,Data!$B:$B,12,Data!$J:$J,"PLANNED") -> 69.5225 | F28: =SUMIFS(Data!$K:$K,Data!$A:$A,2024,Data!$B:$B,12,Data!$J:$J,"UNPLANNED") -> 709.6768 | G28: =IFERROR(F28/D28,0) -> 0.910777 | H28: =SUMIFS(Data!$K:$K,Data!$A:$A,2024,Data!$B:$B,12,Data!$G:$G,"CDU") -> 288.8526 | I28: =SUMIFS(Data!$K:$K,Data!$A:$A,2024,Data!$B:$B,12,Data!$G:$G,"FCC") -> 59.754 | J28: =SUMIFS(Data!$K:$K,Data!$A:$A,2024,Data!$B:$B,12,Data!$G:$G,"Hydrocracker") -> 64.27 | K28: =SUMIFS(Data!$K:$K,Data!$A:$A,2024,Data!$B:$B,12,Data!$G:$G,"Reformer") -> 29.63 | L28: =SUMIFS(Data!$K:$K,Data!$A:$A,2024,Data!$B:$B,12,Data!$F:$F,"PADD 1") -> 197.87 | M28: =SUMIFS(Data!$K:$K,Data!$A:$A,2024,Data!$B:$B,12,Data!$F:$F,"PADD 2") -> 41.1286 | N28: =SUMIFS(Data!$K:$K,Data!$A:$A,2024,Data!$B:$B,12,Data!$F:$F,"PADD 3") -> 324.6714 | O28: =SUMIFS(Data!$K:$K,Data!$A:$A,2024,Data!$B:$B,12,Data!$F:$F,"PADD 4") -> 44.4628 | P28: =SUMIFS(Data!$K:$K,Data!$A:$A,2024,Data!$B:$B,12,Data!$F:$F,"PADD 5") -> 171.0665 | Q28: =K28*ref_intake-H28*naph_yield -> -71.46841
A29: 2025 | B29: 1 | C29: Jan 25 | D29: =SUMIFS(Data!$K:$K,Data!$A:$A,2025,Data!$B:$B,1) -> 3521.0971 | E29: =SUMIFS(Data!$K:$K,Data!$A:$A,2025,Data!$B:$B,1,Data!$J:$J,"PLANNED") -> 2120.1022 | F29: =SUMIFS(Data!$K:$K,Data!$A:$A,2025,Data!$B:$B,1,Data!$J:$J,"UNPLANNED") -> 1400.9949 | G29: =IFERROR(F29/D29,0) -> 0.3978859 | H29: =SUMIFS(Data!$K:$K,Data!$A:$A,2025,Data!$B:$B,1,Data!$G:$G,"CDU") -> 1256.145 | I29: =SUMIFS(Data!$K:$K,Data!$A:$A,2025,Data!$B:$B,1,Data!$G:$G,"FCC") -> 297.316 | J29: =SUMIFS(Data!$K:$K,Data!$A:$A,2025,Data!$B:$B,1,Data!$G:$G,"Hydrocracker") -> 158.245 | K29: =SUMIFS(Data!$K:$K,Data!$A:$A,2025,Data!$B:$B,1,Data!$G:$G,"Reformer") -> 160.3135 | L29: =SUMIFS(Data!$K:$K,Data!$A:$A,2025,Data!$B:$B,1,Data!$F:$F,"PADD 1") -> 240.51 | M29: =SUMIFS(Data!$K:$K,Data!$A:$A,2025,Data!$B:$B,1,Data!$F:$F,"PADD 2") -> 194.6489 | N29: =SUMIFS(Data!$K:$K,Data!$A:$A,2025,Data!$B:$B,1,Data!$F:$F,"PADD 3") -> 2513.4756 | O29: =SUMIFS(Data!$K:$K,Data!$A:$A,2025,Data!$B:$B,1,Data!$F:$F,"PADD 4") -> 63.1796 | P29: =SUMIFS(Data!$K:$K,Data!$A:$A,2025,Data!$B:$B,1,Data!$F:$F,"PADD 5") -> 509.283 | Q29: =K29*ref_intake-H29*naph_yield -> -279.33725
A30: 2025 | B30: 2 | C30: Feb 25 | D30: =SUMIFS(Data!$K:$K,Data!$A:$A,2025,Data!$B:$B,2) -> 5027.1616 | E30: =SUMIFS(Data!$K:$K,Data!$A:$A,2025,Data!$B:$B,2,Data!$J:$J,"PLANNED") -> 3003.7811 | F30: =SUMIFS(Data!$K:$K,Data!$A:$A,2025,Data!$B:$B,2,Data!$J:$J,"UNPLANNED") -> 2023.3805 | G30: =IFERROR(F30/D30,0) -> 0.40248965 | H30: =SUMIFS(Data!$K:$K,Data!$A:$A,2025,Data!$B:$B,2,Data!$G:$G,"CDU") -> 1649.407 | I30: =SUMIFS(Data!$K:$K,Data!$A:$A,2025,Data!$B:$B,2,Data!$G:$G,"FCC") -> 403.831 | J30: =SUMIFS(Data!$K:$K,Data!$A:$A,2025,Data!$B:$B,2,Data!$G:$G,"Hydrocracker") -> 255.94 | K30: =SUMIFS(Data!$K:$K,Data!$A:$A,2025,Data!$B:$B,2,Data!$G:$G,"Reformer") -> 251.5285 | L30: =SUMIFS(Data!$K:$K,Data!$A:$A,2025,Data!$B:$B,2,Data!$F:$F,"PADD 1") -> 486.744 | M30: =SUMIFS(Data!$K:$K,Data!$A:$A,2025,Data!$B:$B,2,Data!$F:$F,"PADD 2") -> 601.5409 | N30: =SUMIFS(Data!$K:$K,Data!$A:$A,2025,Data!$B:$B,2,Data!$F:$F,"PADD 3") -> 2916.5111 | O30: =SUMIFS(Data!$K:$K,Data!$A:$A,2025,Data!$B:$B,2,Data!$F:$F,"PADD 4") -> 36.9436 | P30: =SUMIFS(Data!$K:$K,Data!$A:$A,2025,Data!$B:$B,2,Data!$F:$F,"PADD 5") -> 985.422 | Q30: =K30*ref_intake-H30*naph_yield -> -325.76395
A31: 2025 | B31: 3 | C31: Mar 25 | D31: =SUMIFS(Data!$K:$K,Data!$A:$A,2025,Data!$B:$B,3) -> 4447.6385 | E31: =SUMIFS(Data!$K:$K,Data!$A:$A,2025,Data!$B:$B,3,Data!$J:$J,"PLANNED") -> 2219.192 | F31: =SUMIFS(Data!$K:$K,Data!$A:$A,2025,Data!$B:$B,3,Data!$J:$J,"UNPLANNED") -> 2228.4465 | G31: =IFERROR(F31/D31,0) -> 0.50104038 | H31: =SUMIFS(Data!$K:$K,Data!$A:$A,2025,Data!$B:$B,3,Data!$G:$G,"CDU") -> 1632.123 | I31: =SUMIFS(Data!$K:$K,Data!$A:$A,2025,Data!$B:$B,3,Data!$G:$G,"FCC") -> 472.933 | J31: =SUMIFS(Data!$K:$K,Data!$A:$A,2025,Data!$B:$B,3,Data!$G:$G,"Hydrocracker") -> 219.599 | K31: =SUMIFS(Data!$K:$K,Data!$A:$A,2025,Data!$B:$B,3,Data!$G:$G,"Reformer") -> 301.84 | L31: =SUMIFS(Data!$K:$K,Data!$A:$A,2025,Data!$B:$B,3,Data!$F:$F,"PADD 1") -> 667.28 | M31: =SUMIFS(Data!$K:$K,Data!$A:$A,2025,Data!$B:$B,3,Data!$F:$F,"PADD 2") -> 1279.6 | N31: =SUMIFS(Data!$K:$K,Data!$A:$A,2025,Data!$B:$B,3,Data!$F:$F,"PADD 3") -> 1164.668 | O31: =SUMIFS(Data!$K:$K,Data!$A:$A,2025,Data!$B:$B,3,Data!$F:$F,"PADD 4") -> 72.1625 | P31: =SUMIFS(Data!$K:$K,Data!$A:$A,2025,Data!$B:$B,3,Data!$F:$F,"PADD 5") -> 1263.928 | Q31: =K31*ref_intake-H31*naph_yield -> -269.40305
A32: 2025 | B32: 4 | C32: Apr 25 | D32: =SUMIFS(Data!$K:$K,Data!$A:$A,2025,Data!$B:$B,4) -> 5357.5436 | E32: =SUMIFS(Data!$K:$K,Data!$A:$A,2025,Data!$B:$B,4,Data!$J:$J,"PLANNED") -> 2736.3085 | F32: =SUMIFS(Data!$K:$K,Data!$A:$A,2025,Data!$B:$B,4,Data!$J:$J,"UNPLANNED") -> 2621.2351 | G32: =IFERROR(F32/D32,0) -> 0.48926062 | H32: =SUMIFS(Data!$K:$K,Data!$A:$A,2025,Data!$B:$B,4,Data!$G:$G,"CDU") -> 1850.1686 | I32: =SUMIFS(Data!$K:$K,Data!$A:$A,2025,Data!$B:$B,4,Data!$G:$G,"FCC") -> 576.225 | J32: =SUMIFS(Data!$K:$K,Data!$A:$A,2025,Data!$B:$B,4,Data!$G:$G,"Hydrocracker") -> 244.39 | K32: =SUMIFS(Data!$K:$K,Data!$A:$A,2025,Data!$B:$B,4,Data!$G:$G,"Reformer") -> 443.2805 | L32: =SUMIFS(Data!$K:$K,Data!$A:$A,2025,Data!$B:$B,4,Data!$F:$F,"PADD 1") -> 363.0836 | M32: =SUMIFS(Data!$K:$K,Data!$A:$A,2025,Data!$B:$B,4,Data!$F:$F,"PADD 2") -> 2216.888 | N32: =SUMIFS(Data!$K:$K,Data!$A:$A,2025,Data!$B:$B,4,Data!$F:$F,"PADD 3") -> 951.206 | O32: =SUMIFS(Data!$K:$K,Data!$A:$A,2025,Data!$B:$B,4,Data!$F:$F,"PADD 4") -> 127.706 | P32: =SUMIFS(Data!$K:$K,Data!$A:$A,2025,Data!$B:$B,4,Data!$F:$F,"PADD 5") -> 1698.66 | Q32: =K32*ref_intake-H32*naph_yield -> -204.27851
A33: 2025 | B33: 5 | C33: May 25 | D33: =SUMIFS(Data!$K:$K,Data!$A:$A,2025,Data!$B:$B,5) -> 2654.0926 | E33: =SUMIFS(Data!$K:$K,Data!$A:$A,2025,Data!$B:$B,5,Data!$J:$J,"PLANNED") -> 900.91 | F33: =SUMIFS(Data!$K:$K,Data!$A:$A,2025,Data!$B:$B,5,Data!$J:$J,"UNPLANNED") -> 1753.1826 | G33: =IFERROR(F33/D33,0) -> 0.66055819 | H33: =SUMIFS(Data!$K:$K,Data!$A:$A,2025,Data!$B:$B,5,Data!$G:$G,"CDU") -> 956.3466 | I33: =SUMIFS(Data!$K:$K,Data!$A:$A,2025,Data!$B:$B,5,Data!$G:$G,"FCC") -> 393.455 | J33: =SUMIFS(Data!$K:$K,Data!$A:$A,2025,Data!$B:$B,5,Data!$G:$G,"Hydrocracker") -> 128.7 | K33: =SUMIFS(Data!$K:$K,Data!$A:$A,2025,Data!$B:$B,5,Data!$G:$G,"Reformer") -> 213.1394 | L33: =SUMIFS(Data!$K:$K,Data!$A:$A,2025,Data!$B:$B,5,Data!$F:$F,"PADD 1") -> 265.68 | M33: =SUMIFS(Data!$K:$K,Data!$A:$A,2025,Data!$B:$B,5,Data!$F:$F,"PADD 2") -> 919.8906 | N33: =SUMIFS(Data!$K:$K,Data!$A:$A,2025,Data!$B:$B,5,Data!$F:$F,"PADD 3") -> 451.324 | O33: =SUMIFS(Data!$K:$K,Data!$A:$A,2025,Data!$B:$B,5,Data!$F:$F,"PADD 4") -> 75.15 | P33: =SUMIFS(Data!$K:$K,Data!$A:$A,2025,Data!$B:$B,5,Data!$F:$F,"PADD 5") -> 942.048 | Q33: =K33*ref_intake-H33*naph_yield -> -121.58191
A34: 2025 | B34: 6 | C34: Jun 25 | D34: =SUMIFS(Data!$K:$K,Data!$A:$A,2025,Data!$B:$B,6) -> 1540.4157 | E34: =SUMIFS(Data!$K:$K,Data!$A:$A,2025,Data!$B:$B,6,Data!$J:$J,"PLANNED") -> 370.8306 | F34: =SUMIFS(Data!$K:$K,Data!$A:$A,2025,Data!$B:$B,6,Data!$J:$J,"UNPLANNED") -> 1169.5851 | G34: =IFERROR(F34/D34,0) -> 0.75926589 | H34: =SUMIFS(Data!$K:$K,Data!$A:$A,2025,Data!$B:$B,6,Data!$G:$G,"CDU") -> 488.1771 | I34: =SUMIFS(Data!$K:$K,Data!$A:$A,2025,Data!$B:$B,6,Data!$G:$G,"FCC") -> 215.541 | J34: =SUMIFS(Data!$K:$K,Data!$A:$A,2025,Data!$B:$B,6,Data!$G:$G,"Hydrocracker") -> 149.126 | K34: =SUMIFS(Data!$K:$K,Data!$A:$A,2025,Data!$B:$B,6,Data!$G:$G,"Reformer") -> 90.0075 | L34: =SUMIFS(Data!$K:$K,Data!$A:$A,2025,Data!$B:$B,6,Data!$F:$F,"PADD 1") -> 191.7042 | M34: =SUMIFS(Data!$K:$K,Data!$A:$A,2025,Data!$B:$B,6,Data!$F:$F,"PADD 2") -> 326.2495 | N34: =SUMIFS(Data!$K:$K,Data!$A:$A,2025,Data!$B:$B,6,Data!$F:$F,"PADD 3") -> 382.749 | O34: =SUMIFS(Data!$K:$K,Data!$A:$A,2025,Data!$B:$B,6,Data!$F:$F,"PADD 4") -> 8.223 | P34: =SUMIFS(Data!$K:$K,Data!$A:$A,2025,Data!$B:$B,6,Data!$F:$F,"PADD 5") -> 631.49 | Q34: =K34*ref_intake-H34*naph_yield -> -80.854485
A35: 2025 | B35: 7 | C35: Jul 25 | D35: =SUMIFS(Data!$K:$K,Data!$A:$A,2025,Data!$B:$B,7) -> 1195.17 | E35: =SUMIFS(Data!$K:$K,Data!$A:$A,2025,Data!$B:$B,7,Data!$J:$J,"PLANNED") -> 255.7162 | F35: =SUMIFS(Data!$K:$K,Data!$A:$A,2025,Data!$B:$B,7,Data!$J:$J,"UNPLANNED") -> 939.4538 | G35: =IFERROR(F35/D35,0) -> 0.78604199 | H35: =SUMIFS(Data!$K:$K,Data!$A:$A,2025,Data!$B:$B,7,Data!$G:$G,"CDU") -> 349.903 | I35: =SUMIFS(Data!$K:$K,Data!$A:$A,2025,Data!$B:$B,7,Data!$G:$G,"FCC") -> 183.557 | J35: =SUMIFS(Data!$K:$K,Data!$A:$A,2025,Data!$B:$B,7,Data!$G:$G,"Hydrocracker") -> 155.395 | K35: =SUMIFS(Data!$K:$K,Data!$A:$A,2025,Data!$B:$B,7,Data!$G:$G,"Reformer") -> 37.819 | L35: =SUMIFS(Data!$K:$K,Data!$A:$A,2025,Data!$B:$B,7,Data!$F:$F,"PADD 1") -> 175.9952 | M35: =SUMIFS(Data!$K:$K,Data!$A:$A,2025,Data!$B:$B,7,Data!$F:$F,"PADD 2") -> 260.566 | N35: =SUMIFS(Data!$K:$K,Data!$A:$A,2025,Data!$B:$B,7,Data!$F:$F,"PADD 3") -> 296.0898 | O35: =SUMIFS(Data!$K:$K,Data!$A:$A,2025,Data!$B:$B,7,Data!$F:$F,"PADD 4") -> 92.112 | P35: =SUMIFS(Data!$K:$K,Data!$A:$A,2025,Data!$B:$B,7,Data!$F:$F,"PADD 5") -> 370.407 | Q35: =K35*ref_intake-H35*naph_yield -> -84.64705
A36: 2025 | B36: 8 | C36: Aug 25 | D36: =SUMIFS(Data!$K:$K,Data!$A:$A,2025,Data!$B:$B,8) -> 1609.1225 | E36: =SUMIFS(Data!$K:$K,Data!$A:$A,2025,Data!$B:$B,8,Data!$J:$J,"PLANNED") -> 629.405 | F36: =SUMIFS(Data!$K:$K,Data!$A:$A,2025,Data!$B:$B,8,Data!$J:$J,"UNPLANNED") -> 979.7175 | G36: =IFERROR(F36/D36,0) -> 0.60885203 | H36: =SUMIFS(Data!$K:$K,Data!$A:$A,2025,Data!$B:$B,8,Data!$G:$G,"CDU") -> 393.8658 | I36: =SUMIFS(Data!$K:$K,Data!$A:$A,2025,Data!$B:$B,8,Data!$G:$G,"FCC") -> 235.215 | J36: =SUMIFS(Data!$K:$K,Data!$A:$A,2025,Data!$B:$B,8,Data!$G:$G,"Hydrocracker") -> 201.5 | K36: =SUMIFS(Data!$K:$K,Data!$A:$A,2025,Data!$B:$B,8,Data!$G:$G,"Reformer") -> 87.9 | L36: =SUMIFS(Data!$K:$K,Data!$A:$A,2025,Data!$B:$B,8,Data!$F:$F,"PADD 1") -> 4.58 | M36: =SUMIFS(Data!$K:$K,Data!$A:$A,2025,Data!$B:$B,8,Data!$F:$F,"PADD 2") -> 603.6235 | N36: =SUMIFS(Data!$K:$K,Data!$A:$A,2025,Data!$B:$B,8,Data!$F:$F,"PADD 3") -> 608.524 | O36: =SUMIFS(Data!$K:$K,Data!$A:$A,2025,Data!$B:$B,8,Data!$F:$F,"PADD 4") -> 4.78 | P36: =SUMIFS(Data!$K:$K,Data!$A:$A,2025,Data!$B:$B,8,Data!$F:$F,"PADD 5") -> 387.615 | Q36: =K36*ref_intake-H36*naph_yield -> -49.95303
A37: 2025 | B37: 9 | C37: Sep 25 | D37: =SUMIFS(Data!$K:$K,Data!$A:$A,2025,Data!$B:$B,9) -> 3544.1765 | E37: =SUMIFS(Data!$K:$K,Data!$A:$A,2025,Data!$B:$B,9,Data!$J:$J,"PLANNED") -> 2057.151 | F37: =SUMIFS(Data!$K:$K,Data!$A:$A,2025,Data!$B:$B,9,Data!$J:$J,"UNPLANNED") -> 1487.0255 | G37: =IFERROR(F37/D37,0) -> 0.41956869 | H37: =SUMIFS(Data!$K:$K,Data!$A:$A,2025,Data!$B:$B,9,Data!$G:$G,"CDU") -> 1152.71 | I37: =SUMIFS(Data!$K:$K,Data!$A:$A,2025,Data!$B:$B,9,Data!$G:$G,"FCC") -> 364.325 | J37: =SUMIFS(Data!$K:$K,Data!$A:$A,2025,Data!$B:$B,9,Data!$G:$G,"Hydrocracker") -> 144.05 | K37: =SUMIFS(Data!$K:$K,Data!$A:$A,2025,Data!$B:$B,9,Data!$G:$G,"Reformer") -> 131.7565 | L37: =SUMIFS(Data!$K:$K,Data!$A:$A,2025,Data!$B:$B,9,Data!$F:$F,"PADD 1") -> 7.8 | M37: =SUMIFS(Data!$K:$K,Data!$A:$A,2025,Data!$B:$B,9,Data!$F:$F,"PADD 2") -> 773.2645 | N37: =SUMIFS(Data!$K:$K,Data!$A:$A,2025,Data!$B:$B,9,Data!$F:$F,"PADD 3") -> 2193.196 | O37: =SUMIFS(Data!$K:$K,Data!$A:$A,2025,Data!$B:$B,9,Data!$F:$F,"PADD 4") -> 6.365 | P37: =SUMIFS(Data!$K:$K,Data!$A:$A,2025,Data!$B:$B,9,Data!$F:$F,"PADD 5") -> 563.551 | Q37: =K37*ref_intake-H37*naph_yield -> -271.692
A38: 2025 | B38: 10 | C38: Oct 25 | D38: =SUMIFS(Data!$K:$K,Data!$A:$A,2025,Data!$B:$B,10) -> 5848.478 | E38: =SUMIFS(Data!$K:$K,Data!$A:$A,2025,Data!$B:$B,10,Data!$J:$J,"PLANNED") -> 3379.727 | F38: =SUMIFS(Data!$K:$K,Data!$A:$A,2025,Data!$B:$B,10,Data!$J:$J,"UNPLANNED") -> 2468.751 | G38: =IFERROR(F38/D38,0) -> 0.42211854 | H38: =SUMIFS(Data!$K:$K,Data!$A:$A,2025,Data!$B:$B,10,Data!$G:$G,"CDU") -> 1864.885 | I38: =SUMIFS(Data!$K:$K,Data!$A:$A,2025,Data!$B:$B,10,Data!$G:$G,"FCC") -> 702.5715 | J38: =SUMIFS(Data!$K:$K,Data!$A:$A,2025,Data!$B:$B,10,Data!$G:$G,"Hydrocracker") -> 242.68 | K38: =SUMIFS(Data!$K:$K,Data!$A:$A,2025,Data!$B:$B,10,Data!$G:$G,"Reformer") -> 379.416 | L38: =SUMIFS(Data!$K:$K,Data!$A:$A,2025,Data!$B:$B,10,Data!$F:$F,"PADD 1") -> 10.24 | M38: =SUMIFS(Data!$K:$K,Data!$A:$A,2025,Data!$B:$B,10,Data!$F:$F,"PADD 2") -> 1204.6989 | N38: =SUMIFS(Data!$K:$K,Data!$A:$A,2025,Data!$B:$B,10,Data!$F:$F,"PADD 3") -> 3093.4153 | O38: =SUMIFS(Data!$K:$K,Data!$A:$A,2025,Data!$B:$B,10,Data!$F:$F,"PADD 4") -> 54.195 | P38: =SUMIFS(Data!$K:$K,Data!$A:$A,2025,Data!$B:$B,10,Data!$F:$F,"PADD 5") -> 1485.9288 | Q38: =K38*ref_intake-H38*naph_yield -> -273.29375
A39: 2025 | B39: 11 | C39: Nov 25 | D39: =SUMIFS(Data!$K:$K,Data!$A:$A,2025,Data!$B:$B,11) -> 3057.862 | E39: =SUMIFS(Data!$K:$K,Data!$A:$A,2025,Data!$B:$B,11,Data!$J:$J,"PLANNED") -> 1733.814 | F39: =SUMIFS(Data!$K:$K,Data!$A:$A,2025,Data!$B:$B,11,Data!$J:$J,"UNPLANNED") -> 1324.048 | G39: =IFERROR(F39/D39,0) -> 0.43299796 | H39: =SUMIFS(Data!$K:$K,Data!$A:$A,2025,Data!$B:$B,11,Data!$G:$G,"CDU") -> 989.6356 | I39: =SUMIFS(Data!$K:$K,Data!$A:$A,2025,Data!$B:$B,11,Data!$G:$G,"FCC") -> 409.0129 | J39: =SUMIFS(Data!$K:$K,Data!$A:$A,2025,Data!$B:$B,11,Data!$G:$G,"Hydrocracker") -> 146.955 | K39: =SUMIFS(Data!$K:$K,Data!$A:$A,2025,Data!$B:$B,11,Data!$G:$G,"Reformer") -> 227.8095 | L39: =SUMIFS(Data!$K:$K,Data!$A:$A,2025,Data!$B:$B,11,Data!$F:$F,"PADD 1") -> 2.04 | M39: =SUMIFS(Data!$K:$K,Data!$A:$A,2025,Data!$B:$B,11,Data!$F:$F,"PADD 2") -> 328.8481 | N39: =SUMIFS(Data!$K:$K,Data!$A:$A,2025,Data!$B:$B,11,Data!$F:$F,"PADD 3") -> 1683.7699 | O39: =SUMIFS(Data!$K:$K,Data!$A:$A,2025,Data!$B:$B,11,Data!$F:$F,"PADD 4") -> 16.895 | P39: =SUMIFS(Data!$K:$K,Data!$A:$A,2025,Data!$B:$B,11,Data!$F:$F,"PADD 5") -> 1026.309 | Q39: =K39*ref_intake-H39*naph_yield -> -118.56296
A40: 2025 | B40: 12 | C40: Dec 25 | D40: =SUMIFS(Data!$K:$K,Data!$A:$A,2025,Data!$B:$B,12) -> 943.353 | E40: =SUMIFS(Data!$K:$K,Data!$A:$A,2025,Data!$B:$B,12,Data!$J:$J,"PLANNED") -> 81.62 | F40: =SUMIFS(Data!$K:$K,Data!$A:$A,2025,Data!$B:$B,12,Data!$J:$J,"UNPLANNED") -> 861.733 | G40: =IFERROR(F40/D40,0) -> 0.91347884 | H40: =SUMIFS(Data!$K:$K,Data!$A:$A,2025,Data!$B:$B,12,Data!$G:$G,"CDU") -> 313.306 | I40: =SUMIFS(Data!$K:$K,Data!$A:$A,2025,Data!$B:$B,12,Data!$G:$G,"FCC") -> 75.961 | J40: =SUMIFS(Data!$K:$K,Data!$A:$A,2025,Data!$B:$B,12,Data!$G:$G,"Hydrocracker") -> 84.29 | K40: =SUMIFS(Data!$K:$K,Data!$A:$A,2025,Data!$B:$B,12,Data!$G:$G,"Reformer") -> 25.235 | L40: =SUMIFS(Data!$K:$K,Data!$A:$A,2025,Data!$B:$B,12,Data!$F:$F,"PADD 1") -> 0 | M40: =SUMIFS(Data!$K:$K,Data!$A:$A,2025,Data!$B:$B,12,Data!$F:$F,"PADD 2") -> 129.87 | N40: =SUMIFS(Data!$K:$K,Data!$A:$A,2025,Data!$B:$B,12,Data!$F:$F,"PADD 3") -> 172.694 | O40: =SUMIFS(Data!$K:$K,Data!$A:$A,2025,Data!$B:$B,12,Data!$F:$F,"PADD 4") -> 14.089 | P40: =SUMIFS(Data!$K:$K,Data!$A:$A,2025,Data!$B:$B,12,Data!$F:$F,"PADD 5") -> 626.7 | Q40: =K40*ref_intake-H40*naph_yield -> -84.4221
A41: 2026 | B41: 1 | C41: Jan 26 | D41: =SUMIFS(Data!$K:$K,Data!$A:$A,2026,Data!$B:$B,1) -> 1849.6688 | E41: =SUMIFS(Data!$K:$K,Data!$A:$A,2026,Data!$B:$B,1,Data!$J:$J,"PLANNED") -> 1062.6823 | F41: =SUMIFS(Data!$K:$K,Data!$A:$A,2026,Data!$B:$B,1,Data!$J:$J,"UNPLANNED") -> 786.9865 | G41: =IFERROR(F41/D41,0) -> 0.42547428 | H41: =SUMIFS(Data!$K:$K,Data!$A:$A,2026,Data!$B:$B,1,Data!$G:$G,"CDU") -> 531.3 | I41: =SUMIFS(Data!$K:$K,Data!$A:$A,2026,Data!$B:$B,1,Data!$G:$G,"FCC") -> 299.98 | J41: =SUMIFS(Data!$K:$K,Data!$A:$A,2026,Data!$B:$B,1,Data!$G:$G,"Hydrocracker") -> 50.92 | K41: =SUMIFS(Data!$K:$K,Data!$A:$A,2026,Data!$B:$B,1,Data!$G:$G,"Reformer") -> 95.4175 | L41: =SUMIFS(Data!$K:$K,Data!$A:$A,2026,Data!$B:$B,1,Data!$F:$F,"PADD 1") -> 32.8 | M41: =SUMIFS(Data!$K:$K,Data!$A:$A,2026,Data!$B:$B,1,Data!$F:$F,"PADD 2") -> 161.3505 | N41: =SUMIFS(Data!$K:$K,Data!$A:$A,2026,Data!$B:$B,1,Data!$F:$F,"PADD 3") -> 1155.2534 | O41: =SUMIFS(Data!$K:$K,Data!$A:$A,2026,Data!$B:$B,1,Data!$F:$F,"PADD 4") -> 0 | P41: =SUMIFS(Data!$K:$K,Data!$A:$A,2026,Data!$B:$B,1,Data!$F:$F,"PADD 5") -> 500.2649 | Q41: =K41*ref_intake-H41*naph_yield -> -90.5375
A42: 2026 | B42: 2 | C42: Feb 26 | D42: =SUMIFS(Data!$K:$K,Data!$A:$A,2026,Data!$B:$B,2) -> 3739.2241 | E42: =SUMIFS(Data!$K:$K,Data!$A:$A,2026,Data!$B:$B,2,Data!$J:$J,"PLANNED") -> 1946.2561 | F42: =SUMIFS(Data!$K:$K,Data!$A:$A,2026,Data!$B:$B,2,Data!$J:$J,"UNPLANNED") -> 1792.968 | G42: =IFERROR(F42/D42,0) -> 0.47950269 | H42: =SUMIFS(Data!$K:$K,Data!$A:$A,2026,Data!$B:$B,2,Data!$G:$G,"CDU") -> 1246.845 | I42: =SUMIFS(Data!$K:$K,Data!$A:$A,2026,Data!$B:$B,2,Data!$G:$G,"FCC") -> 559.7625 | J42: =SUMIFS(Data!$K:$K,Data!$A:$A,2026,Data!$B:$B,2,Data!$G:$G,"Hydrocracker") -> 68.32 | K42: =SUMIFS(Data!$K:$K,Data!$A:$A,2026,Data!$B:$B,2,Data!$G:$G,"Reformer") -> 210.5685 | L42: =SUMIFS(Data!$K:$K,Data!$A:$A,2026,Data!$B:$B,2,Data!$F:$F,"PADD 1") -> 37.14 | M42: =SUMIFS(Data!$K:$K,Data!$A:$A,2026,Data!$B:$B,2,Data!$F:$F,"PADD 2") -> 720.4935 | N42: =SUMIFS(Data!$K:$K,Data!$A:$A,2026,Data!$B:$B,2,Data!$F:$F,"PADD 3") -> 2305.337 | O42: =SUMIFS(Data!$K:$K,Data!$A:$A,2026,Data!$B:$B,2,Data!$F:$F,"PADD 4") -> 35.302 | P42: =SUMIFS(Data!$K:$K,Data!$A:$A,2026,Data!$B:$B,2,Data!$F:$F,"PADD 5") -> 640.9516 | Q42: =K42*ref_intake-H42*naph_yield -> -225.82725
A43: 2026 | B43: 3 | C43: Mar 26 | D43: =SUMIFS(Data!$K:$K,Data!$A:$A,2026,Data!$B:$B,3) -> 3152.1816 | E43: =SUMIFS(Data!$K:$K,Data!$A:$A,2026,Data!$B:$B,3,Data!$J:$J,"PLANNED") -> 2033.7659 | F43: =SUMIFS(Data!$K:$K,Data!$A:$A,2026,Data!$B:$B,3,Data!$J:$J,"UNPLANNED") -> 1118.4157 | G43: =IFERROR(F43/D43,0) -> 0.35480687 | H43: =SUMIFS(Data!$K:$K,Data!$A:$A,2026,Data!$B:$B,3,Data!$G:$G,"CDU") -> 968.521 | I43: =SUMIFS(Data!$K:$K,Data!$A:$A,2026,Data!$B:$B,3,Data!$G:$G,"FCC") -> 331.375 | J43: =SUMIFS(Data!$K:$K,Data!$A:$A,2026,Data!$B:$B,3,Data!$G:$G,"Hydrocracker") -> 145.776 | K43: =SUMIFS(Data!$K:$K,Data!$A:$A,2026,Data!$B:$B,3,Data!$G:$G,"Reformer") -> 159.17 | L43: =SUMIFS(Data!$K:$K,Data!$A:$A,2026,Data!$B:$B,3,Data!$F:$F,"PADD 1") -> 51.028 | M43: =SUMIFS(Data!$K:$K,Data!$A:$A,2026,Data!$B:$B,3,Data!$F:$F,"PADD 2") -> 1236.0397 | N43: =SUMIFS(Data!$K:$K,Data!$A:$A,2026,Data!$B:$B,3,Data!$F:$F,"PADD 3") -> 1298.356 | O43: =SUMIFS(Data!$K:$K,Data!$A:$A,2026,Data!$B:$B,3,Data!$F:$F,"PADD 4") -> 193.667 | P43: =SUMIFS(Data!$K:$K,Data!$A:$A,2026,Data!$B:$B,3,Data!$F:$F,"PADD 5") -> 373.0909 | Q43: =K43*ref_intake-H43*naph_yield -> -179.81235
A44: 2026 | B44: 4 | C44: Apr 26 | D44: =SUMIFS(Data!$K:$K,Data!$A:$A,2026,Data!$B:$B,4) -> 3982.502 | E44: =SUMIFS(Data!$K:$K,Data!$A:$A,2026,Data!$B:$B,4,Data!$J:$J,"PLANNED") -> 1938.51 | F44: =SUMIFS(Data!$K:$K,Data!$A:$A,2026,Data!$B:$B,4,Data!$J:$J,"UNPLANNED") -> 2043.992 | G44: =IFERROR(F44/D44,0) -> 0.51324318 | H44: =SUMIFS(Data!$K:$K,Data!$A:$A,2026,Data!$B:$B,4,Data!$G:$G,"CDU") -> 1411.605 | I44: =SUMIFS(Data!$K:$K,Data!$A:$A,2026,Data!$B:$B,4,Data!$G:$G,"FCC") -> 558.008 | J44: =SUMIFS(Data!$K:$K,Data!$A:$A,2026,Data!$B:$B,4,Data!$G:$G,"Hydrocracker") -> 172.765 | K44: =SUMIFS(Data!$K:$K,Data!$A:$A,2026,Data!$B:$B,4,Data!$G:$G,"Reformer") -> 154.283 | L44: =SUMIFS(Data!$K:$K,Data!$A:$A,2026,Data!$B:$B,4,Data!$F:$F,"PADD 1") -> 5.98 | M44: =SUMIFS(Data!$K:$K,Data!$A:$A,2026,Data!$B:$B,4,Data!$F:$F,"PADD 2") -> 1514.833 | N44: =SUMIFS(Data!$K:$K,Data!$A:$A,2026,Data!$B:$B,4,Data!$F:$F,"PADD 3") -> 1274.583 | O44: =SUMIFS(Data!$K:$K,Data!$A:$A,2026,Data!$B:$B,4,Data!$F:$F,"PADD 4") -> 298.055 | P44: =SUMIFS(Data!$K:$K,Data!$A:$A,2026,Data!$B:$B,4,Data!$F:$F,"PADD 5") -> 889.051 | Q44: =K44*ref_intake-H44*naph_yield -> -339.77875
A45: 2026 | B45: 5 | C45: May 26 | D45: =SUMIFS(Data!$K:$K,Data!$A:$A,2026,Data!$B:$B,5) -> 2203.7437 | E45: =SUMIFS(Data!$K:$K,Data!$A:$A,2026,Data!$B:$B,5,Data!$J:$J,"PLANNED") -> 1001.3308 | F45: =SUMIFS(Data!$K:$K,Data!$A:$A,2026,Data!$B:$B,5,Data!$J:$J,"UNPLANNED") -> 1202.4129 | G45: =IFERROR(F45/D45,0) -> 0.54562284 | H45: =SUMIFS(Data!$K:$K,Data!$A:$A,2026,Data!$B:$B,5,Data!$G:$G,"CDU") -> 841.202 | I45: =SUMIFS(Data!$K:$K,Data!$A:$A,2026,Data!$B:$B,5,Data!$G:$G,"FCC") -> 360.0815 | J45: =SUMIFS(Data!$K:$K,Data!$A:$A,2026,Data!$B:$B,5,Data!$G:$G,"Hydrocracker") -> 92.77 | K45: =SUMIFS(Data!$K:$K,Data!$A:$A,2026,Data!$B:$B,5,Data!$G:$G,"Reformer") -> 157.769 | L45: =SUMIFS(Data!$K:$K,Data!$A:$A,2026,Data!$B:$B,5,Data!$F:$F,"PADD 1") -> 21.2 | M45: =SUMIFS(Data!$K:$K,Data!$A:$A,2026,Data!$B:$B,5,Data!$F:$F,"PADD 2") -> 829.96 | N45: =SUMIFS(Data!$K:$K,Data!$A:$A,2026,Data!$B:$B,5,Data!$F:$F,"PADD 3") -> 752.5585 | O45: =SUMIFS(Data!$K:$K,Data!$A:$A,2026,Data!$B:$B,5,Data!$F:$F,"PADD 4") -> 128.6544 | P45: =SUMIFS(Data!$K:$K,Data!$A:$A,2026,Data!$B:$B,5,Data!$F:$F,"PADD 5") -> 471.3708 | Q45: =K45*ref_intake-H45*naph_yield -> -136.6517
A46: 2026 | B46: 6 | C46: Jun 26 | D46: =SUMIFS(Data!$K:$K,Data!$A:$A,2026,Data!$B:$B,6) -> 1349.6757 | E46: =SUMIFS(Data!$K:$K,Data!$A:$A,2026,Data!$B:$B,6,Data!$J:$J,"PLANNED") -> 182.45 | F46: =SUMIFS(Data!$K:$K,Data!$A:$A,2026,Data!$B:$B,6,Data!$J:$J,"UNPLANNED") -> 1167.2257 | G46: =IFERROR(F46/D46,0) -> 0.86481938 | H46: =SUMIFS(Data!$K:$K,Data!$A:$A,2026,Data!$B:$B,6,Data!$G:$G,"CDU") -> 435.03 | I46: =SUMIFS(Data!$K:$K,Data!$A:$A,2026,Data!$B:$B,6,Data!$G:$G,"FCC") -> 147.405 | J46: =SUMIFS(Data!$K:$K,Data!$A:$A,2026,Data!$B:$B,6,Data!$G:$G,"Hydrocracker") -> 21.38 | K46: =SUMIFS(Data!$K:$K,Data!$A:$A,2026,Data!$B:$B,6,Data!$G:$G,"Reformer") -> 130.51 | L46: =SUMIFS(Data!$K:$K,Data!$A:$A,2026,Data!$B:$B,6,Data!$F:$F,"PADD 1") -> 334.0757 | M46: =SUMIFS(Data!$K:$K,Data!$A:$A,2026,Data!$B:$B,6,Data!$F:$F,"PADD 2") -> 158.585 | N46: =SUMIFS(Data!$K:$K,Data!$A:$A,2026,Data!$B:$B,6,Data!$F:$F,"PADD 3") -> 730.815 | O46: =SUMIFS(Data!$K:$K,Data!$A:$A,2026,Data!$B:$B,6,Data!$F:$F,"PADD 4") -> 6.6 | P46: =SUMIFS(Data!$K:$K,Data!$A:$A,2026,Data!$B:$B,6,Data!$F:$F,"PADD 5") -> 119.6 | Q46: =K46*ref_intake-H46*naph_yield -> -21.7505
A47: 2026 | B47: 7 | C47: Jul 26 | D47: =SUMIFS(Data!$K:$K,Data!$A:$A,2026,Data!$B:$B,7) -> 1075.021 | E47: =SUMIFS(Data!$K:$K,Data!$A:$A,2026,Data!$B:$B,7,Data!$J:$J,"PLANNED") -> 269.572 | F47: =SUMIFS(Data!$K:$K,Data!$A:$A,2026,Data!$B:$B,7,Data!$J:$J,"UNPLANNED") -> 805.449 | G47: =IFERROR(F47/D47,0) -> 0.74924025 | H47: =SUMIFS(Data!$K:$K,Data!$A:$A,2026,Data!$B:$B,7,Data!$G:$G,"CDU") -> 378.602 | I47: =SUMIFS(Data!$K:$K,Data!$A:$A,2026,Data!$B:$B,7,Data!$G:$G,"FCC") -> 69.8 | J47: =SUMIFS(Data!$K:$K,Data!$A:$A,2026,Data!$B:$B,7,Data!$G:$G,"Hydrocracker") -> 30.24 | K47: =SUMIFS(Data!$K:$K,Data!$A:$A,2026,Data!$B:$B,7,Data!$G:$G,"Reformer") -> 98.204 | L47: =SUMIFS(Data!$K:$K,Data!$A:$A,2026,Data!$B:$B,7,Data!$F:$F,"PADD 1") -> 654.394 | M47: =SUMIFS(Data!$K:$K,Data!$A:$A,2026,Data!$B:$B,7,Data!$F:$F,"PADD 2") -> 57.76 | N47: =SUMIFS(Data!$K:$K,Data!$A:$A,2026,Data!$B:$B,7,Data!$F:$F,"PADD 3") -> 253.287 | O47: =SUMIFS(Data!$K:$K,Data!$A:$A,2026,Data!$B:$B,7,Data!$F:$F,"PADD 4") -> 0 | P47: =SUMIFS(Data!$K:$K,Data!$A:$A,2026,Data!$B:$B,7,Data!$F:$F,"PADD 5") -> 109.58 | Q47: =K47*ref_intake-H47*naph_yield -> -34.3067
A48: 2026 | B48: 8 | C48: Aug 26 | D48: =SUMIFS(Data!$K:$K,Data!$A:$A,2026,Data!$B:$B,8) -> 553.6705 | E48: =SUMIFS(Data!$K:$K,Data!$A:$A,2026,Data!$B:$B,8,Data!$J:$J,"PLANNED") -> 204.11 | F48: =SUMIFS(Data!$K:$K,Data!$A:$A,2026,Data!$B:$B,8,Data!$J:$J,"UNPLANNED") -> 349.5605 | G48: =IFERROR(F48/D48,0) -> 0.63135114 | H48: =SUMIFS(Data!$K:$K,Data!$A:$A,2026,Data!$B:$B,8,Data!$G:$G,"CDU") -> 126 | I48: =SUMIFS(Data!$K:$K,Data!$A:$A,2026,Data!$B:$B,8,Data!$G:$G,"FCC") -> 30.6 | J48: =SUMIFS(Data!$K:$K,Data!$A:$A,2026,Data!$B:$B,8,Data!$G:$G,"Hydrocracker") -> 69.66 | K48: =SUMIFS(Data!$K:$K,Data!$A:$A,2026,Data!$B:$B,8,Data!$G:$G,"Reformer") -> 44.905 | L48: =SUMIFS(Data!$K:$K,Data!$A:$A,2026,Data!$B:$B,8,Data!$F:$F,"PADD 1") -> 294.1605 | M48: =SUMIFS(Data!$K:$K,Data!$A:$A,2026,Data!$B:$B,8,Data!$F:$F,"PADD 2") -> 0 | N48: =SUMIFS(Data!$K:$K,Data!$A:$A,2026,Data!$B:$B,8,Data!$F:$F,"PADD 3") -> 211.98 | O48: =SUMIFS(Data!$K:$K,Data!$A:$A,2026,Data!$B:$B,8,Data!$F:$F,"PADD 4") -> 0 | P48: =SUMIFS(Data!$K:$K,Data!$A:$A,2026,Data!$B:$B,8,Data!$F:$F,"PADD 5") -> 47.53 | Q48: =K48*ref_intake-H48*naph_yield -> 0.805
A49: 2026 | B49: 9 | C49: Sep 26 | D49: =SUMIFS(Data!$K:$K,Data!$A:$A,2026,Data!$B:$B,9) -> 1218.8349 | E49: =SUMIFS(Data!$K:$K,Data!$A:$A,2026,Data!$B:$B,9,Data!$J:$J,"PLANNED") -> 1171.8349 | F49: =SUMIFS(Data!$K:$K,Data!$A:$A,2026,Data!$B:$B,9,Data!$J:$J,"UNPLANNED") -> 47 | G49: =IFERROR(F49/D49,0) -> 0.038561416 | H49: =SUMIFS(Data!$K:$K,Data!$A:$A,2026,Data!$B:$B,9,Data!$G:$G,"CDU") -> 448.14 | I49: =SUMIFS(Data!$K:$K,Data!$A:$A,2026,Data!$B:$B,9,Data!$G:$G,"FCC") -> 68.93 | J49: =SUMIFS(Data!$K:$K,Data!$A:$A,2026,Data!$B:$B,9,Data!$G:$G,"Hydrocracker") -> 149.15 | K49: =SUMIFS(Data!$K:$K,Data!$A:$A,2026,Data!$B:$B,9,Data!$G:$G,"Reformer") -> 137.55 | L49: =SUMIFS(Data!$K:$K,Data!$A:$A,2026,Data!$B:$B,9,Data!$F:$F,"PADD 1") -> 71.8939 | M49: =SUMIFS(Data!$K:$K,Data!$A:$A,2026,Data!$B:$B,9,Data!$F:$F,"PADD 2") -> 572.94 | N49: =SUMIFS(Data!$K:$K,Data!$A:$A,2026,Data!$B:$B,9,Data!$F:$F,"PADD 3") -> 463.941 | O49: =SUMIFS(Data!$K:$K,Data!$A:$A,2026,Data!$B:$B,9,Data!$F:$F,"PADD 4") -> 0 | P49: =SUMIFS(Data!$K:$K,Data!$A:$A,2026,Data!$B:$B,9,Data!$F:$F,"PADD 5") -> 110.06 | Q49: =K49*ref_intake-H49*naph_yield -> -19.299
A50: 2026 | B50: 10 | C50: Oct 26 | D50: =SUMIFS(Data!$K:$K,Data!$A:$A,2026,Data!$B:$B,10) -> 1640.294 | E50: =SUMIFS(Data!$K:$K,Data!$A:$A,2026,Data!$B:$B,10,Data!$J:$J,"PLANNED") -> 1593.294 | F50: =SUMIFS(Data!$K:$K,Data!$A:$A,2026,Data!$B:$B,10,Data!$J:$J,"UNPLANNED") -> 47 | G50: =IFERROR(F50/D50,0) -> 0.0286534 | H50: =SUMIFS(Data!$K:$K,Data!$A:$A,2026,Data!$B:$B,10,Data!$G:$G,"CDU") -> 661.633 | I50: =SUMIFS(Data!$K:$K,Data!$A:$A,2026,Data!$B:$B,10,Data!$G:$G,"FCC") -> 189.01 | J50: =SUMIFS(Data!$K:$K,Data!$A:$A,2026,Data!$B:$B,10,Data!$G:$G,"Hydrocracker") -> 73.98 | K50: =SUMIFS(Data!$K:$K,Data!$A:$A,2026,Data!$B:$B,10,Data!$G:$G,"Reformer") -> 166.385 | L50: =SUMIFS(Data!$K:$K,Data!$A:$A,2026,Data!$B:$B,10,Data!$F:$F,"PADD 1") -> 82.5856 | M50: =SUMIFS(Data!$K:$K,Data!$A:$A,2026,Data!$B:$B,10,Data!$F:$F,"PADD 2") -> 705.146 | N50: =SUMIFS(Data!$K:$K,Data!$A:$A,2026,Data!$B:$B,10,Data!$F:$F,"PADD 3") -> 634.8024 | O50: =SUMIFS(Data!$K:$K,Data!$A:$A,2026,Data!$B:$B,10,Data!$F:$F,"PADD 4") -> 19.62 | P50: =SUMIFS(Data!$K:$K,Data!$A:$A,2026,Data!$B:$B,10,Data!$F:$F,"PADD 5") -> 198.14 | Q50: =K50*ref_intake-H50*naph_yield -> -65.18655
A51: 2026 | B51: 11 | C51: Nov 26 | D51: =SUMIFS(Data!$K:$K,Data!$A:$A,2026,Data!$B:$B,11) -> 697.476 | E51: =SUMIFS(Data!$K:$K,Data!$A:$A,2026,Data!$B:$B,11,Data!$J:$J,"PLANNED") -> 655.176 | F51: =SUMIFS(Data!$K:$K,Data!$A:$A,2026,Data!$B:$B,11,Data!$J:$J,"UNPLANNED") -> 42.3 | G51: =IFERROR(F51/D51,0) -> 0.060647248 | H51: =SUMIFS(Data!$K:$K,Data!$A:$A,2026,Data!$B:$B,11,Data!$G:$G,"CDU") -> 214.3 | I51: =SUMIFS(Data!$K:$K,Data!$A:$A,2026,Data!$B:$B,11,Data!$G:$G,"FCC") -> 127.225 | J51: =SUMIFS(Data!$K:$K,Data!$A:$A,2026,Data!$B:$B,11,Data!$G:$G,"Hydrocracker") -> 17.296 | K51: =SUMIFS(Data!$K:$K,Data!$A:$A,2026,Data!$B:$B,11,Data!$G:$G,"Reformer") -> 68.1 | L51: =SUMIFS(Data!$K:$K,Data!$A:$A,2026,Data!$B:$B,11,Data!$F:$F,"PADD 1") -> 0 | M51: =SUMIFS(Data!$K:$K,Data!$A:$A,2026,Data!$B:$B,11,Data!$F:$F,"PADD 2") -> 397.5 | N51: =SUMIFS(Data!$K:$K,Data!$A:$A,2026,Data!$B:$B,11,Data!$F:$F,"PADD 3") -> 163.78 | O51: =SUMIFS(Data!$K:$K,Data!$A:$A,2026,Data!$B:$B,11,Data!$F:$F,"PADD 4") -> 0 | P51: =SUMIFS(Data!$K:$K,Data!$A:$A,2026,Data!$B:$B,11,Data!$F:$F,"PADD 5") -> 136.196 | Q51: =K51*ref_intake-H51*naph_yield -> -6.905
A52: 2026 | B52: 12 | C52: Dec 26 | D52: =SUMIFS(Data!$K:$K,Data!$A:$A,2026,Data!$B:$B,12) -> 9.5 | E52: =SUMIFS(Data!$K:$K,Data!$A:$A,2026,Data!$B:$B,12,Data!$J:$J,"PLANNED") -> 9.5 | F52: =SUMIFS(Data!$K:$K,Data!$A:$A,2026,Data!$B:$B,12,Data!$J:$J,"UNPLANNED") -> 0 | G52: =IFERROR(F52/D52,0) -> 0 | H52: =SUMIFS(Data!$K:$K,Data!$A:$A,2026,Data!$B:$B,12,Data!$G:$G,"CDU") -> 0 | I52: =SUMIFS(Data!$K:$K,Data!$A:$A,2026,Data!$B:$B,12,Data!$G:$G,"FCC") -> 4.8 | J52: =SUMIFS(Data!$K:$K,Data!$A:$A,2026,Data!$B:$B,12,Data!$G:$G,"Hydrocracker") -> 0 | K52: =SUMIFS(Data!$K:$K,Data!$A:$A,2026,Data!$B:$B,12,Data!$G:$G,"Reformer") -> 0 | L52: =SUMIFS(Data!$K:$K,Data!$A:$A,2026,Data!$B:$B,12,Data!$F:$F,"PADD 1") -> 0 | M52: =SUMIFS(Data!$K:$K,Data!$A:$A,2026,Data!$B:$B,12,Data!$F:$F,"PADD 2") -> 0 | N52: =SUMIFS(Data!$K:$K,Data!$A:$A,2026,Data!$B:$B,12,Data!$F:$F,"PADD 3") -> 0 | O52: =SUMIFS(Data!$K:$K,Data!$A:$A,2026,Data!$B:$B,12,Data!$F:$F,"PADD 4") -> 0 | P52: =SUMIFS(Data!$K:$K,Data!$A:$A,2026,Data!$B:$B,12,Data!$F:$F,"PADD 5") -> 9.5 | Q52: =K52*ref_intake-H52*naph_yield -> 0
A53: 2027 | B53: 1 | C53: Jan 27 | D53: =SUMIFS(Data!$K:$K,Data!$A:$A,2027,Data!$B:$B,1) -> 1103.883 | E53: =SUMIFS(Data!$K:$K,Data!$A:$A,2027,Data!$B:$B,1,Data!$J:$J,"PLANNED") -> 1103.883 | F53: =SUMIFS(Data!$K:$K,Data!$A:$A,2027,Data!$B:$B,1,Data!$J:$J,"UNPLANNED") -> 0 | G53: =IFERROR(F53/D53,0) -> 0 | H53: =SUMIFS(Data!$K:$K,Data!$A:$A,2027,Data!$B:$B,1,Data!$G:$G,"CDU") -> 365.125 | I53: =SUMIFS(Data!$K:$K,Data!$A:$A,2027,Data!$B:$B,1,Data!$G:$G,"FCC") -> 250.98 | J53: =SUMIFS(Data!$K:$K,Data!$A:$A,2027,Data!$B:$B,1,Data!$G:$G,"Hydrocracker") -> 121.41 | K53: =SUMIFS(Data!$K:$K,Data!$A:$A,2027,Data!$B:$B,1,Data!$G:$G,"Reformer") -> 29.125 | L53: =SUMIFS(Data!$K:$K,Data!$A:$A,2027,Data!$B:$B,1,Data!$F:$F,"PADD 1") -> 0 | M53: =SUMIFS(Data!$K:$K,Data!$A:$A,2027,Data!$B:$B,1,Data!$F:$F,"PADD 2") -> 0 | N53: =SUMIFS(Data!$K:$K,Data!$A:$A,2027,Data!$B:$B,1,Data!$F:$F,"PADD 3") -> 707.863 | O53: =SUMIFS(Data!$K:$K,Data!$A:$A,2027,Data!$B:$B,1,Data!$F:$F,"PADD 4") -> 0 | P53: =SUMIFS(Data!$K:$K,Data!$A:$A,2027,Data!$B:$B,1,Data!$F:$F,"PADD 5") -> 396.02 | Q53: =K53*ref_intake-H53*naph_yield -> -98.66875
A54: 2027 | B54: 2 | C54: Feb 27 | D54: =SUMIFS(Data!$K:$K,Data!$A:$A,2027,Data!$B:$B,2) -> 2114.6201 | E54: =SUMIFS(Data!$K:$K,Data!$A:$A,2027,Data!$B:$B,2,Data!$J:$J,"PLANNED") -> 2114.6201 | F54: =SUMIFS(Data!$K:$K,Data!$A:$A,2027,Data!$B:$B,2,Data!$J:$J,"UNPLANNED") -> 0 | G54: =IFERROR(F54/D54,0) -> 0 | H54: =SUMIFS(Data!$K:$K,Data!$A:$A,2027,Data!$B:$B,2,Data!$G:$G,"CDU") -> 683.258 | I54: =SUMIFS(Data!$K:$K,Data!$A:$A,2027,Data!$B:$B,2,Data!$G:$G,"FCC") -> 450.5215 | J54: =SUMIFS(Data!$K:$K,Data!$A:$A,2027,Data!$B:$B,2,Data!$G:$G,"Hydrocracker") -> 141.67 | K54: =SUMIFS(Data!$K:$K,Data!$A:$A,2027,Data!$B:$B,2,Data!$G:$G,"Reformer") -> 68.78 | L54: =SUMIFS(Data!$K:$K,Data!$A:$A,2027,Data!$B:$B,2,Data!$F:$F,"PADD 1") -> 0 | M54: =SUMIFS(Data!$K:$K,Data!$A:$A,2027,Data!$B:$B,2,Data!$F:$F,"PADD 2") -> 192.48 | N54: =SUMIFS(Data!$K:$K,Data!$A:$A,2027,Data!$B:$B,2,Data!$F:$F,"PADD 3") -> 1278.3421 | O54: =SUMIFS(Data!$K:$K,Data!$A:$A,2027,Data!$B:$B,2,Data!$F:$F,"PADD 4") -> 139.68 | P54: =SUMIFS(Data!$K:$K,Data!$A:$A,2027,Data!$B:$B,2,Data!$F:$F,"PADD 5") -> 504.118 | Q54: =K54*ref_intake-H54*naph_yield -> -170.3603
A55: 2027 | B55: 3 | C55: Mar 27 | D55: =SUMIFS(Data!$K:$K,Data!$A:$A,2027,Data!$B:$B,3) -> 2889.3523 | E55: =SUMIFS(Data!$K:$K,Data!$A:$A,2027,Data!$B:$B,3,Data!$J:$J,"PLANNED") -> 2889.3523 | F55: =SUMIFS(Data!$K:$K,Data!$A:$A,2027,Data!$B:$B,3,Data!$J:$J,"UNPLANNED") -> 0 | G55: =IFERROR(F55/D55,0) -> 0 | H55: =SUMIFS(Data!$K:$K,Data!$A:$A,2027,Data!$B:$B,3,Data!$G:$G,"CDU") -> 1062.14 | I55: =SUMIFS(Data!$K:$K,Data!$A:$A,2027,Data!$B:$B,3,Data!$G:$G,"FCC") -> 447.892 | J55: =SUMIFS(Data!$K:$K,Data!$A:$A,2027,Data!$B:$B,3,Data!$G:$G,"Hydrocracker") -> 75.53 | K55: =SUMIFS(Data!$K:$K,Data!$A:$A,2027,Data!$B:$B,3,Data!$G:$G,"Reformer") -> 184.889 | L55: =SUMIFS(Data!$K:$K,Data!$A:$A,2027,Data!$B:$B,3,Data!$F:$F,"PADD 1") -> 236.8488 | M55: =SUMIFS(Data!$K:$K,Data!$A:$A,2027,Data!$B:$B,3,Data!$F:$F,"PADD 2") -> 614.741 | N55: =SUMIFS(Data!$K:$K,Data!$A:$A,2027,Data!$B:$B,3,Data!$F:$F,"PADD 3") -> 1544.8915 | O55: =SUMIFS(Data!$K:$K,Data!$A:$A,2027,Data!$B:$B,3,Data!$F:$F,"PADD 4") -> 251.725 | P55: =SUMIFS(Data!$K:$K,Data!$A:$A,2027,Data!$B:$B,3,Data!$F:$F,"PADD 5") -> 241.146 | Q55: =K55*ref_intake-H55*naph_yield -> -186.86
A56: 2027 | B56: 4 | C56: Apr 27 | D56: =SUMIFS(Data!$K:$K,Data!$A:$A,2027,Data!$B:$B,4) -> 1954.1924 | E56: =SUMIFS(Data!$K:$K,Data!$A:$A,2027,Data!$B:$B,4,Data!$J:$J,"PLANNED") -> 1954.1924 | F56: =SUMIFS(Data!$K:$K,Data!$A:$A,2027,Data!$B:$B,4,Data!$J:$J,"UNPLANNED") -> 0 | G56: =IFERROR(F56/D56,0) -> 0 | H56: =SUMIFS(Data!$K:$K,Data!$A:$A,2027,Data!$B:$B,4,Data!$G:$G,"CDU") -> 663.255 | I56: =SUMIFS(Data!$K:$K,Data!$A:$A,2027,Data!$B:$B,4,Data!$G:$G,"FCC") -> 150.455 | J56: =SUMIFS(Data!$K:$K,Data!$A:$A,2027,Data!$B:$B,4,Data!$G:$G,"Hydrocracker") -> 39.15 | K56: =SUMIFS(Data!$K:$K,Data!$A:$A,2027,Data!$B:$B,4,Data!$G:$G,"Reformer") -> 141.475 | L56: =SUMIFS(Data!$K:$K,Data!$A:$A,2027,Data!$B:$B,4,Data!$F:$F,"PADD 1") -> 108.2632 | M56: =SUMIFS(Data!$K:$K,Data!$A:$A,2027,Data!$B:$B,4,Data!$F:$F,"PADD 2") -> 911.25 | N56: =SUMIFS(Data!$K:$K,Data!$A:$A,2027,Data!$B:$B,4,Data!$F:$F,"PADD 3") -> 664.0222 | O56: =SUMIFS(Data!$K:$K,Data!$A:$A,2027,Data!$B:$B,4,Data!$F:$F,"PADD 4") -> 257.098 | P56: =SUMIFS(Data!$K:$K,Data!$A:$A,2027,Data!$B:$B,4,Data!$F:$F,"PADD 5") -> 13.559 | Q56: =K56*ref_intake-H56*naph_yield -> -90.66425
A57: 2027 | B57: 5 | C57: May 27 | D57: =SUMIFS(Data!$K:$K,Data!$A:$A,2027,Data!$B:$B,5) -> 856.532 | E57: =SUMIFS(Data!$K:$K,Data!$A:$A,2027,Data!$B:$B,5,Data!$J:$J,"PLANNED") -> 856.532 | F57: =SUMIFS(Data!$K:$K,Data!$A:$A,2027,Data!$B:$B,5,Data!$J:$J,"UNPLANNED") -> 0 | G57: =IFERROR(F57/D57,0) -> 0 | H57: =SUMIFS(Data!$K:$K,Data!$A:$A,2027,Data!$B:$B,5,Data!$G:$G,"CDU") -> 320.192 | I57: =SUMIFS(Data!$K:$K,Data!$A:$A,2027,Data!$B:$B,5,Data!$G:$G,"FCC") -> 23.3 | J57: =SUMIFS(Data!$K:$K,Data!$A:$A,2027,Data!$B:$B,5,Data!$G:$G,"Hydrocracker") -> 0 | K57: =SUMIFS(Data!$K:$K,Data!$A:$A,2027,Data!$B:$B,5,Data!$G:$G,"Reformer") -> 45.428 | L57: =SUMIFS(Data!$K:$K,Data!$A:$A,2027,Data!$B:$B,5,Data!$F:$F,"PADD 1") -> 0 | M57: =SUMIFS(Data!$K:$K,Data!$A:$A,2027,Data!$B:$B,5,Data!$F:$F,"PADD 2") -> 428.63 | N57: =SUMIFS(Data!$K:$K,Data!$A:$A,2027,Data!$B:$B,5,Data!$F:$F,"PADD 3") -> 134.4 | O57: =SUMIFS(Data!$K:$K,Data!$A:$A,2027,Data!$B:$B,5,Data!$F:$F,"PADD 4") -> 242.162 | P57: =SUMIFS(Data!$K:$K,Data!$A:$A,2027,Data!$B:$B,5,Data!$F:$F,"PADD 5") -> 51.34 | Q57: =K57*ref_intake-H57*naph_yield -> -66.6392
A58: 2027 | B58: 6 | C58: Jun 27 | D58: =SUMIFS(Data!$K:$K,Data!$A:$A,2027,Data!$B:$B,6) -> 215.305 | E58: =SUMIFS(Data!$K:$K,Data!$A:$A,2027,Data!$B:$B,6,Data!$J:$J,"PLANNED") -> 215.305 | F58: =SUMIFS(Data!$K:$K,Data!$A:$A,2027,Data!$B:$B,6,Data!$J:$J,"UNPLANNED") -> 0 | G58: =IFERROR(F58/D58,0) -> 0 | H58: =SUMIFS(Data!$K:$K,Data!$A:$A,2027,Data!$B:$B,6,Data!$G:$G,"CDU") -> 96 | I58: =SUMIFS(Data!$K:$K,Data!$A:$A,2027,Data!$B:$B,6,Data!$G:$G,"FCC") -> 68.255 | J58: =SUMIFS(Data!$K:$K,Data!$A:$A,2027,Data!$B:$B,6,Data!$G:$G,"Hydrocracker") -> 0 | K58: =SUMIFS(Data!$K:$K,Data!$A:$A,2027,Data!$B:$B,6,Data!$G:$G,"Reformer") -> 0.3 | L58: =SUMIFS(Data!$K:$K,Data!$A:$A,2027,Data!$B:$B,6,Data!$F:$F,"PADD 1") -> 0 | M58: =SUMIFS(Data!$K:$K,Data!$A:$A,2027,Data!$B:$B,6,Data!$F:$F,"PADD 2") -> 0 | N58: =SUMIFS(Data!$K:$K,Data!$A:$A,2027,Data!$B:$B,6,Data!$F:$F,"PADD 3") -> 210.95 | O58: =SUMIFS(Data!$K:$K,Data!$A:$A,2027,Data!$B:$B,6,Data!$F:$F,"PADD 4") -> 0.855 | P58: =SUMIFS(Data!$K:$K,Data!$A:$A,2027,Data!$B:$B,6,Data!$F:$F,"PADD 5") -> 3.5 | Q58: =K58*ref_intake-H58*naph_yield -> -33.3
A59: 2027 | B59: 7 | C59: Jul 27 | D59: =SUMIFS(Data!$K:$K,Data!$A:$A,2027,Data!$B:$B,7) -> 167.5 | E59: =SUMIFS(Data!$K:$K,Data!$A:$A,2027,Data!$B:$B,7,Data!$J:$J,"PLANNED") -> 167.5 | F59: =SUMIFS(Data!$K:$K,Data!$A:$A,2027,Data!$B:$B,7,Data!$J:$J,"UNPLANNED") -> 0 | G59: =IFERROR(F59/D59,0) -> 0 | H59: =SUMIFS(Data!$K:$K,Data!$A:$A,2027,Data!$B:$B,7,Data!$G:$G,"CDU") -> 96 | I59: =SUMIFS(Data!$K:$K,Data!$A:$A,2027,Data!$B:$B,7,Data!$G:$G,"FCC") -> 68 | J59: =SUMIFS(Data!$K:$K,Data!$A:$A,2027,Data!$B:$B,7,Data!$G:$G,"Hydrocracker") -> 0 | K59: =SUMIFS(Data!$K:$K,Data!$A:$A,2027,Data!$B:$B,7,Data!$G:$G,"Reformer") -> 0 | L59: =SUMIFS(Data!$K:$K,Data!$A:$A,2027,Data!$B:$B,7,Data!$F:$F,"PADD 1") -> 0 | M59: =SUMIFS(Data!$K:$K,Data!$A:$A,2027,Data!$B:$B,7,Data!$F:$F,"PADD 2") -> 0 | N59: =SUMIFS(Data!$K:$K,Data!$A:$A,2027,Data!$B:$B,7,Data!$F:$F,"PADD 3") -> 164 | O59: =SUMIFS(Data!$K:$K,Data!$A:$A,2027,Data!$B:$B,7,Data!$F:$F,"PADD 4") -> 0 | P59: =SUMIFS(Data!$K:$K,Data!$A:$A,2027,Data!$B:$B,7,Data!$F:$F,"PADD 5") -> 3.5 | Q59: =K59*ref_intake-H59*naph_yield -> -33.6
A60: 2027 | B60: 8 | C60: Aug 27 | D60: =SUMIFS(Data!$K:$K,Data!$A:$A,2027,Data!$B:$B,8) -> 51.06 | E60: =SUMIFS(Data!$K:$K,Data!$A:$A,2027,Data!$B:$B,8,Data!$J:$J,"PLANNED") -> 51.06 | F60: =SUMIFS(Data!$K:$K,Data!$A:$A,2027,Data!$B:$B,8,Data!$J:$J,"UNPLANNED") -> 0 | G60: =IFERROR(F60/D60,0) -> 0 | H60: =SUMIFS(Data!$K:$K,Data!$A:$A,2027,Data!$B:$B,8,Data!$G:$G,"CDU") -> 27.84 | I60: =SUMIFS(Data!$K:$K,Data!$A:$A,2027,Data!$B:$B,8,Data!$G:$G,"FCC") -> 19.72 | J60: =SUMIFS(Data!$K:$K,Data!$A:$A,2027,Data!$B:$B,8,Data!$G:$G,"Hydrocracker") -> 0 | K60: =SUMIFS(Data!$K:$K,Data!$A:$A,2027,Data!$B:$B,8,Data!$G:$G,"Reformer") -> 0 | L60: =SUMIFS(Data!$K:$K,Data!$A:$A,2027,Data!$B:$B,8,Data!$F:$F,"PADD 1") -> 0 | M60: =SUMIFS(Data!$K:$K,Data!$A:$A,2027,Data!$B:$B,8,Data!$F:$F,"PADD 2") -> 0 | N60: =SUMIFS(Data!$K:$K,Data!$A:$A,2027,Data!$B:$B,8,Data!$F:$F,"PADD 3") -> 47.56 | O60: =SUMIFS(Data!$K:$K,Data!$A:$A,2027,Data!$B:$B,8,Data!$F:$F,"PADD 4") -> 0 | P60: =SUMIFS(Data!$K:$K,Data!$A:$A,2027,Data!$B:$B,8,Data!$F:$F,"PADD 5") -> 3.5 | Q60: =K60*ref_intake-H60*naph_yield -> -9.744
A61: 2027 | B61: 9 | C61: Sep 27 | D61: =SUMIFS(Data!$K:$K,Data!$A:$A,2027,Data!$B:$B,9) -> 2763.7719 | E61: =SUMIFS(Data!$K:$K,Data!$A:$A,2027,Data!$B:$B,9,Data!$J:$J,"PLANNED") -> 2763.7719 | F61: =SUMIFS(Data!$K:$K,Data!$A:$A,2027,Data!$B:$B,9,Data!$J:$J,"UNPLANNED") -> 0 | G61: =IFERROR(F61/D61,0) -> 0 | H61: =SUMIFS(Data!$K:$K,Data!$A:$A,2027,Data!$B:$B,9,Data!$G:$G,"CDU") -> 976.735 | I61: =SUMIFS(Data!$K:$K,Data!$A:$A,2027,Data!$B:$B,9,Data!$G:$G,"FCC") -> 176.274 | J61: =SUMIFS(Data!$K:$K,Data!$A:$A,2027,Data!$B:$B,9,Data!$G:$G,"Hydrocracker") -> 104.88 | K61: =SUMIFS(Data!$K:$K,Data!$A:$A,2027,Data!$B:$B,9,Data!$G:$G,"Reformer") -> 112.05 | L61: =SUMIFS(Data!$K:$K,Data!$A:$A,2027,Data!$B:$B,9,Data!$F:$F,"PADD 1") -> 38.7069 | M61: =SUMIFS(Data!$K:$K,Data!$A:$A,2027,Data!$B:$B,9,Data!$F:$F,"PADD 2") -> 945.416 | N61: =SUMIFS(Data!$K:$K,Data!$A:$A,2027,Data!$B:$B,9,Data!$F:$F,"PADD 3") -> 1545.905 | O61: =SUMIFS(Data!$K:$K,Data!$A:$A,2027,Data!$B:$B,9,Data!$F:$F,"PADD 4") -> 42.994 | P61: =SUMIFS(Data!$K:$K,Data!$A:$A,2027,Data!$B:$B,9,Data!$F:$F,"PADD 5") -> 190.75 | Q61: =K61*ref_intake-H61*naph_yield -> -229.80725
A62: 2027 | B62: 10 | C62: Oct 27 | D62: =SUMIFS(Data!$K:$K,Data!$A:$A,2027,Data!$B:$B,10) -> 2799.5469 | E62: =SUMIFS(Data!$K:$K,Data!$A:$A,2027,Data!$B:$B,10,Data!$J:$J,"PLANNED") -> 2799.5469 | F62: =SUMIFS(Data!$K:$K,Data!$A:$A,2027,Data!$B:$B,10,Data!$J:$J,"UNPLANNED") -> 0 | G62: =IFERROR(F62/D62,0) -> 0 | H62: =SUMIFS(Data!$K:$K,Data!$A:$A,2027,Data!$B:$B,10,Data!$G:$G,"CDU") -> 1307.315 | I62: =SUMIFS(Data!$K:$K,Data!$A:$A,2027,Data!$B:$B,10,Data!$G:$G,"FCC") -> 189.624 | J62: =SUMIFS(Data!$K:$K,Data!$A:$A,2027,Data!$B:$B,10,Data!$G:$G,"Hydrocracker") -> 63.94 | K62: =SUMIFS(Data!$K:$K,Data!$A:$A,2027,Data!$B:$B,10,Data!$G:$G,"Reformer") -> 109.945 | L62: =SUMIFS(Data!$K:$K,Data!$A:$A,2027,Data!$B:$B,10,Data!$F:$F,"PADD 1") -> 5.5959 | M62: =SUMIFS(Data!$K:$K,Data!$A:$A,2027,Data!$B:$B,10,Data!$F:$F,"PADD 2") -> 427.23 | N62: =SUMIFS(Data!$K:$K,Data!$A:$A,2027,Data!$B:$B,10,Data!$F:$F,"PADD 3") -> 1819.237 | O62: =SUMIFS(Data!$K:$K,Data!$A:$A,2027,Data!$B:$B,10,Data!$F:$F,"PADD 4") -> 34.444 | P62: =SUMIFS(Data!$K:$K,Data!$A:$A,2027,Data!$B:$B,10,Data!$F:$F,"PADD 5") -> 513.04 | Q62: =K62*ref_intake-H62*naph_yield -> -347.61525
A63: 2027 | B63: 11 | C63: Nov 27 | D63: =SUMIFS(Data!$K:$K,Data!$A:$A,2027,Data!$B:$B,11) -> 546.936 | E63: =SUMIFS(Data!$K:$K,Data!$A:$A,2027,Data!$B:$B,11,Data!$J:$J,"PLANNED") -> 546.936 | F63: =SUMIFS(Data!$K:$K,Data!$A:$A,2027,Data!$B:$B,11,Data!$J:$J,"UNPLANNED") -> 0 | G63: =IFERROR(F63/D63,0) -> 0 | H63: =SUMIFS(Data!$K:$K,Data!$A:$A,2027,Data!$B:$B,11,Data!$G:$G,"CDU") -> 283.9 | I63: =SUMIFS(Data!$K:$K,Data!$A:$A,2027,Data!$B:$B,11,Data!$G:$G,"FCC") -> 54.87 | J63: =SUMIFS(Data!$K:$K,Data!$A:$A,2027,Data!$B:$B,11,Data!$G:$G,"Hydrocracker") -> 17.653 | K63: =SUMIFS(Data!$K:$K,Data!$A:$A,2027,Data!$B:$B,11,Data!$G:$G,"Reformer") -> 20.105 | L63: =SUMIFS(Data!$K:$K,Data!$A:$A,2027,Data!$B:$B,11,Data!$F:$F,"PADD 1") -> 0 | M63: =SUMIFS(Data!$K:$K,Data!$A:$A,2027,Data!$B:$B,11,Data!$F:$F,"PADD 2") -> 1.8 | N63: =SUMIFS(Data!$K:$K,Data!$A:$A,2027,Data!$B:$B,11,Data!$F:$F,"PADD 3") -> 446.133 | O63: =SUMIFS(Data!$K:$K,Data!$A:$A,2027,Data!$B:$B,11,Data!$F:$F,"PADD 4") -> 4.753 | P63: =SUMIFS(Data!$K:$K,Data!$A:$A,2027,Data!$B:$B,11,Data!$F:$F,"PADD 5") -> 94.25 | Q63: =K63*ref_intake-H63*naph_yield -> -79.26
A64: 2027 | B64: 12 | C64: Dec 27 | D64: =SUMIFS(Data!$K:$K,Data!$A:$A,2027,Data!$B:$B,12) -> 3.5 | E64: =SUMIFS(Data!$K:$K,Data!$A:$A,2027,Data!$B:$B,12,Data!$J:$J,"PLANNED") -> 3.5 | F64: =SUMIFS(Data!$K:$K,Data!$A:$A,2027,Data!$B:$B,12,Data!$J:$J,"UNPLANNED") -> 0 | G64: =IFERROR(F64/D64,0) -> 0 | H64: =SUMIFS(Data!$K:$K,Data!$A:$A,2027,Data!$B:$B,12,Data!$G:$G,"CDU") -> 0 | I64: =SUMIFS(Data!$K:$K,Data!$A:$A,2027,Data!$B:$B,12,Data!$G:$G,"FCC") -> 0 | J64: =SUMIFS(Data!$K:$K,Data!$A:$A,2027,Data!$B:$B,12,Data!$G:$G,"Hydrocracker") -> 0 | K64: =SUMIFS(Data!$K:$K,Data!$A:$A,2027,Data!$B:$B,12,Data!$G:$G,"Reformer") -> 0 | L64: =SUMIFS(Data!$K:$K,Data!$A:$A,2027,Data!$B:$B,12,Data!$F:$F,"PADD 1") -> 0 | M64: =SUMIFS(Data!$K:$K,Data!$A:$A,2027,Data!$B:$B,12,Data!$F:$F,"PADD 2") -> 0 | N64: =SUMIFS(Data!$K:$K,Data!$A:$A,2027,Data!$B:$B,12,Data!$F:$F,"PADD 3") -> 0 | O64: =SUMIFS(Data!$K:$K,Data!$A:$A,2027,Data!$B:$B,12,Data!$F:$F,"PADD 4") -> 0 | P64: =SUMIFS(Data!$K:$K,Data!$A:$A,2027,Data!$B:$B,12,Data!$F:$F,"PADD 5") -> 3.5 | Q64: =K64*ref_intake-H64*naph_yield -> 0
A66: Annual (kbd) and YoY%
A67: Year | B67: Total | C67: Planned | D67: Unplanned | E67: Unpl % | F67: Total YoY%
A68: 2023 | B68: =SUMIFS(Data!$K:$K,Data!$A:$A,2023) -> 49891.373 | C68: =SUMIFS(Data!$K:$K,Data!$A:$A,2023,Data!$J:$J,"PLANNED") -> 26140.246 | D68: =SUMIFS(Data!$K:$K,Data!$A:$A,2023,Data!$J:$J,"UNPLANNED") -> 23751.127 | E68: =IFERROR(D68/B68,0) -> 0.47605679 | F68: n/a
A69: 2024 | B69: =SUMIFS(Data!$K:$K,Data!$A:$A,2024) -> 41965.062 | C69: =SUMIFS(Data!$K:$K,Data!$A:$A,2024,Data!$J:$J,"PLANNED") -> 20382.496 | D69: =SUMIFS(Data!$K:$K,Data!$A:$A,2024,Data!$J:$J,"UNPLANNED") -> 21582.567 | E69: =IFERROR(D69/B69,0) -> 0.51429845 | F69: =IFERROR(B69/B68-1,0) -> -0.15887136
A70: 2025 | B70: =SUMIFS(Data!$K:$K,Data!$A:$A,2025) -> 38746.111 | C70: =SUMIFS(Data!$K:$K,Data!$A:$A,2025,Data!$J:$J,"PLANNED") -> 19488.558 | D70: =SUMIFS(Data!$K:$K,Data!$A:$A,2025,Data!$J:$J,"UNPLANNED") -> 19257.554 | E70: =IFERROR(D70/B70,0) -> 0.497019 | F70: =IFERROR(B70/B69-1,0) -> -0.076705507
A71: 2026 | B71: =SUMIFS(Data!$K:$K,Data!$A:$A,2026) -> 21471.792 | C71: =SUMIFS(Data!$K:$K,Data!$A:$A,2026,Data!$J:$J,"PLANNED") -> 12068.482 | D71: =SUMIFS(Data!$K:$K,Data!$A:$A,2026,Data!$J:$J,"UNPLANNED") -> 9403.3103 | E71: =IFERROR(D71/B71,0) -> 0.43793784 | F71: =IFERROR(B71/B70-1,0) -> -0.44583362
A72: 2027 | B72: =SUMIFS(Data!$K:$K,Data!$A:$A,2027) -> 15466.2 | C72: =SUMIFS(Data!$K:$K,Data!$A:$A,2027,Data!$J:$J,"PLANNED") -> 15466.2 | D72: =SUMIFS(Data!$K:$K,Data!$A:$A,2027,Data!$J:$J,"UNPLANNED") -> 0 | E72: =IFERROR(D72/B72,0) -> 0 | F72: =IFERROR(B72/B71-1,0) -> -0.27969685

Sheet Data Quality
A1: Data Quality: turnaround-cadence & double-count flags (review only)
A2: Auto-flagged from the source each build; nothing is dropped. Verify against the source. Turnarounds run on ~a 5-year cycle.
A4: Planned turnaround again within <5yr (CDU & FCC; planned->planned only -- unplanned never resets the cycle)
A5: Plant | B5: Unit | C5: Class | D5: Prev TA | E5: Next TA | F5: Gap yr | G5: kbd prev | H5: kbd next
A6: Robinson Refinery | B6: Crude (Sweet & Sour) Plant | C6: CDU | D6: 2025 | E6: 2026 | F6: 1 | G6: 72 | H6: 598
A7: Norco Refinery | B7: DU-5 (Distilling Unit) (Sw | C7: CDU | D7: 2023 | E7: 2027 | F7: 4 | G7: 442 | H7: 394
A8: Joliet Refinery | B8: Crude | C8: CDU | D8: 2026 | E8: 2027 | F8: 1 | G8: 68 | H8: 322
A9: Wood River Refinery | B9: DU-2 Distilling Unit (Swee | C9: CDU | D9: 2025 | E9: 2026 | F9: 1 | G9: 36 | H9: 284
A10: Garyville Refinery | B10: Crude 10 A-Train/Sour | C10: CDU | D10: 2025 | E10: 2027 | F10: 2 | G10: 96 | H10: 284
A11: Garyville Refinery | B11: Crude 10 B-Train Sour/Swee | C11: CDU | D11: 2025 | E11: 2027 | F11: 2 | G11: 194 | H11: 284
A12: Martinez Refinery (PBF) | B12: DH Crude | C12: CDU | D12: 2024 | E12: 2027 | F12: 3 | G12: 40 | H12: 270
A13: El Dorado Refinery (HF Sincl | B13: Crude | C13: CDU | D13: 2024 | E13: 2026 | F13: 2 | G13: 151 | H13: 240
A14: Lemont Refinery | B14: Crude Distillation 111 | C14: CDU | D14: 2026 | E14: 2027 | F14: 1 | G14: 112 | H14: 229
A15: Chalmette Refinery | B15: Crude 2 (Sour) | C15: CDU | D15: 2025 | E15: 2026 | F15: 1 | G15: 110 | H15: 221
A16: Chalmette Refinery | B16: Crude 1 (Sweet) | C16: CDU | D16: 2024 | E16: 2027 | F16: 3 | G16: 132 | H16: 220
A17: Lima Refinery | B17: Crude 2 (Sweet) | C17: CDU | D17: 2024 | E17: 2026 | F17: 2 | G17: 91 | H17: 196
... A21: Sweeny Refinery | B21: Heavy Oil Cracker 27-1 | C21: FCC | D21: 2025 | E21: 2027 | F21: 2 | G21: 85 | H21: 158
A22: 202 CDU/FCC planned-pairs are <=4yr apart and reach 2026+ (top 16 by size shown). 'kbd' = day-weighted kbd-months that year. A short gap can be real minor maintenance, not a full turnaround -- check magnitude.
A24: Unit-months summing to >100% of nameplate (overlap / double-count)
A25: Year | B25: Mon | C25: Plant | D25: Unit | E25: Class | F25: Σ kbd | G25: Nameplate | H25: Ratio | I25: Type
A26: 2026 | B26: 2 | C26: Baytown Refinery | D26: Pipe Still 3 (PS-3) | E26: CDU | F26: 192.1 | G26: 115 | H26: 1.67 | I26: PLANNED+UNPLANNED
A27: 2026 | B27: 4 | C27: Port Arthur Refinery ( | D27: FCCU 1241 | E27: FCC | F27: 155 | G27: 80 | H27: 1.94 | I27: UNPLANNED
A28: 2026 | B28: 5 | C28: Toledo Refinery (PBF) | D28: FCCU | E28: FCC | F28: 93.9 | G28: 82 | H28: 1.14 | I28: UNPLANNED
A29: 2026 | B29: 11 | C29: El Dorado Refinery (HF | D29: Reformer CRU 1 | E29: Reformer | F29: 15 | G29: 7.5 | H29: 2 | I29: PLANNED
A30: 2026 | B30: 4 | C30: Port Arthur Refinery ( | D30: AVU 146 (Crude Still) | E30: CDU | F30: 217 | G30: 210 | H30: 1.03 | I30: UNPLANNED
A31: 2026 | B31: 3 | C31: Port Arthur Refinery ( | D31: Hydrocracker 942 | E31: Hydrocracker | F31: 50.8 | G31: 45 | H31: 1.13 | I31: PLANNED+UNPLANNED
A32: 6 focus unit-months in 2026-2027 exceed nameplate (~184 excess kbd-months) -- small vs the totals, but each is an overlap or a duplicate record (or one event logged as both planned and unplanned).

Sheet Data
A1: Data: Snowflake golden record (paste refreshes here; Focus/PADD auto-derive)
A2: Update = paste OUTAGE_YEAR/MONTH->A,B; PLANT/OPERATOR->D,E; UNIT_CATEGORY->H; UNIT_NAME->I; OUTAGE_TYPE->J; CAP_OFFLINE_ADJUSTED_KBD->K; OFFLINE_CAPACITY->L; PAD_DIST->M. Rest auto-fills.
A4: year | B4: monthnum | C4: month | D4: plant | E4: operator | F4: padd | G4: focus | H4: unit_cat | I4: unit_name | J4: type | K4: cap_kbd | L4: cap_raw | M4: pad_dist
A5: 2023 | B5: 1 | C5: Jan | D5: Alliance Refinery | E5: PHILLIPS 66 | F5: =IF($M5="PADD I","PADD 1",IF($M5="PADD II","PADD 2",IF($M5="PADD III","PADD 3",IF($M5="PADD IV","PADD 4",IF($M5="PADD V","PADD 5",""))))) -> PADD 3 | G5: =IF(AND($H5="ATMOS DISTILLATION",ISNUMBER(SEARCH("VPS",$I5))=FALSE,LEFT($I5,6)<>"VACUUM"),"CDU",IF($H5="FLUID CAT CRACKING","FCC",IF(OR($H5="HYDROCRACKING",$H5="RESID_HYDROCRACKING"),"Hydrocracker",IF($H5="REFORMING","Reformer","")))) -> CDU | H5: ATMOS DISTILLATION | I5: Crude 191 | J5: PLANNED | K5: 269.14 | L5: 269.14 | M5: PADD III
A6: 2023 | B6: 1 | C6: Jan | D6: Toledo Refinery (Cenovus) | E6: CENOVUS ENERGY INCORPORATED | F6: =IF($M6="PADD I","PADD 1",IF($M6="PADD II","PADD 2",IF($M6="PADD III","PADD 3",IF($M6="PADD IV","PADD 4",IF($M6="PADD V","PADD 5",""))))) -> PADD 2 | G6: =IF(AND($H6="ATMOS DISTILLATION",ISNUMBER(SEARCH("VPS",$I6))=FALSE,LEFT($I6,6)<>"VACUUM"),"CDU",IF($H6="FLUID CAT CRACKING","FCC",IF(OR($H6="HYDROCRACKING",$H6="RESID_HYDROCRACKING"),"Hydrocracker",IF($H6="REFORMING","Reformer","")))) -> CDU | H6: ATMOS DISTILLATION | I6: Crude 1 (Sour) | J6: UNPLANNED | K6: 110 | L6: 110 | M6: PADD II
A7: 2023 | B7: 1 | C7: Jan | D7: Alliance Refinery | E7: PHILLIPS 66 | F7: =IF($M7="PADD I","PADD 1",IF($M7="PADD II","PADD 2",IF($M7="PADD III","PADD 3",IF($M7="PADD IV","PADD 4",IF($M7="PADD V","PADD 5",""))))) -> PADD 3 | G7: =IF(AND($H7="ATMOS DISTILLATION",ISNUMBER(SEARCH("VPS",$I7))=FALSE,LEFT($I7,6)<>"VACUUM"),"CDU",IF($H7="FLUID CAT CRACKING","FCC",IF(OR($H7="HYDROCRACKING",$H7="RESID_HYDROCRACKING"),"Hydrocracker",IF($H7="REFORMING","Reformer","")))) -> FCC | H7: FLUID CAT CRACKING | I7: FCCU 1291 | J7: PLANNED | K7: 104 | L7: 104 | M7: PADD III
A8: 2023 | B8: 1 | C8: Jan | D8: Alliance Refinery | E8: PHILLIPS 66 | F8: =IF($M8="PADD I","PADD 1",IF($M8="PADD II","PADD 2",IF($M8="PADD III","PADD 3",IF($M8="PADD IV","PADD 4",IF($M8="PADD V","PADD 5",""))))) -> PADD 3 | G8: =IF(AND($H8="ATMOS DISTILLATION",ISNUMBER(SEARCH("VPS",$I8))=FALSE,LEFT($I8,6)<>"VACUUM"),"CDU",IF($H8="FLUID CAT CRACKING","FCC",IF(OR($H8="HYDROCRACKING",$H8="RESID_HYDROCRACKING"),"Hydrocracker",IF($H8="REFORMING","Reformer","")))) | H8: VACUUM DISTILLATION | I8: Vacuum | J8: PLANNED | K8: 103 | L8: 103 | M8: PADD III
A9: 2023 | B9: 1 | C9: Jan | D9: Baton Rouge Refinery | E9: EXXONMOBIL CORPORATION | F9: =IF($M9="PADD I","PADD 1",IF($M9="PADD II","PADD 2",IF($M9="PADD III","PADD 3",IF($M9="PADD IV","PADD 4",IF($M9="PADD V","PADD 5",""))))) -> PADD 3 | G9: =IF(AND($H9="ATMOS DISTILLATION",ISNUMBER(SEARCH("VPS",$I9))=FALSE,LEFT($I9,6)<>"VACUUM"),"CDU",IF($H9="FLUID CAT CRACKING","FCC",IF(OR($H9="HYDROCRACKING",$H9="RESID_HYDROCRACKING"),"Hydrocracker",IF($H9="REFORMING","Reformer","")))) -> CDU | H9: ATMOS DISTILLATION | I9: PSLA 10 (Pipestill Sour) | J9: PLANNED | K9: 100.8 | L9: 210 | M9: PADD III
A10: 2023 | B10: 1 | C10: Jan | D10: Beaumont Refinery | E10: EXXONMOBIL CORPORATION | F10: =IF($M10="PADD I","PADD 1",IF($M10="PADD II","PADD 2",IF($M10="PADD III","PADD 3",IF($M10="PADD IV","PADD 4",IF($M10="PADD V","PADD 5",""))))) -> PADD 3 | G10: =IF(AND($H10="ATMOS DISTILLATION",ISNUMBER(SEARCH("VPS",$I10))=FALSE,LEFT($I10,6)<>"VACUUM"),"CDU",IF($H10="FLUID CAT CRACKING","FCC",IF(OR($H10="HYDROCRACKING",$H10="RESID_HYDROCRACKING"),"Hydrocracker",IF($H10="REFORMING","Reformer","")))) -> FCC | H10: FLUID CAT CRACKING | I10: FCCU | J10: PLANNED | K10: 92.4 | L10: 120 | M10: PADD III
A11: 2023 | B11: 1 | C11: Jan | D11: Toledo Refinery (PBF) | E11: TOLEDO REFINING COMPANY LLC | F11: =IF($M11="PADD I","PADD 1",IF($M11="PADD II","PADD 2",IF($M11="PADD III","PADD 3",IF($M11="PADD IV","PADD 4",IF($M11="PADD V","PADD 5",""))))) -> PADD 2 | G11: =IF(AND($H11="ATMOS DISTILLATION",ISNUMBER(SEARCH("VPS",$I11))=FALSE,LEFT($I11,6)<>"VACUUM"),"CDU",IF($H11="FLUID CAT CRACKING","FCC",IF(OR($H11="HYDROCRACKING",$H11="RESID_HYDROCRACKING"),"Hydrocracker",IF($H11="REFORMING","Reformer","")))) -> CDU | H11: ATMOS DISTILLATION | I11: Crude 3 (Sweet) | J11: PLANNED | K11: 88 | L11: 88 | M11: PADD II
A12: 2023 | B12: 1 | C12: Jan | D12: Martinez Refinery (PBF) | E12: MARTINEZ REFINING COMPANY LLC | F12: =IF($M12="PADD I","PADD 1",IF($M12="PADD II","PADD 2",IF($M12="PADD III","PADD 3",IF($M12="PADD IV","PADD 4",IF($M12="PADD V","PADD 5",""))))) -> PADD 5 | G12: =IF(AND($H12="ATMOS DISTILLATION",ISNUMBER(SEARCH("VPS",$I12))=FALSE,LEFT($I12,6)<>"VACUUM"),"CDU",IF($H12="FLUID CAT CRACKING","FCC",IF(OR($H12="HYDROCRACKING",$H12="RESID_HYDROCRACKING"),"Hydrocracker",IF($H12="REFORMING","Reformer","")))) -> CDU | H12: ATMOS DISTILLATION | I12: DH Crude | J12: PLANNED | K12: 80.6 | L12: 155 | M12: PADD V
A13: 2023 | B13: 1 | C13: Jan | D13: Toledo Refinery (PBF) | E13: TOLEDO REFINING COMPANY LLC | F13: =IF($M13="PADD I","PADD 1",IF($M13="PADD II","PADD 2",IF($M13="PADD III","PADD 3",IF($M13="PADD IV","PADD 4",IF($M13="PADD V","PADD 5",""))))) -> PADD 2 | G13: =IF(AND($H13="ATMOS DISTILLATION",ISNUMBER(SEARCH("VPS",$I13))=FALSE,LEFT($I13,6)<>"VACUUM"),"CDU",IF($H13="FLUID CAT CRACKING","FCC",IF(OR($H13="HYDROCRACKING",$H13="RESID_HYDROCRACKING"),"Hydrocracker",IF($H13="REFORMING","Reformer","")))) -> FCC | H13: FLUID CAT CRACKING | I13: FCCU | J13: PLANNED | K13: 79 | L13: 79 | M13: PADD II
A14: 2023 | B14: 1 | C14: Jan | D14: Galveston Bay Refinery (GBR) | E14: MARATHON PETROLEUM CORPORATION | F14: =IF($M14="PADD I","PADD 1",IF($M14="PADD II","PADD 2",IF($M14="PADD III","PADD 3",IF($M14="PADD IV","PADD 4",IF($M14="PADD V","PADD 5",""))))) -> PADD 3 | G14: =IF(AND($H14="ATMOS DISTILLATION",ISNUMBER(SEARCH("VPS",$I14))=FALSE,LEFT($I14,6)<>"VACUUM"),"CDU",IF($H14="FLUID CAT CRACKING","FCC",IF(OR($H14="HYDROCRACKING",$H14="RESID_HYDROCRACKING"),"Hydrocracker",IF($H14="REFORMING","Reformer","")))) -> CDU | H14: ATMOS DISTILLATION | I14: Pipestill 3A | J14: PLANNED | K14: 78.4 | L14: 245 | M14: PADD III
A15: 2023 | B15: 1 | C15: Jan | D15: Pascagoula Refinery | E15: CHEVRON CORPORATION | F15: =IF($M15="PADD I","PADD 1",IF($M15="PADD II","PADD 2",IF($M15="PADD III","PADD 3",IF($M15="PADD IV","PADD 4",IF($M15="PADD V","PADD 5",""))))) -> PADD 3 | G15: =IF(AND($H15="ATMOS DISTILLATION",ISNUMBER(SEARCH("VPS",$I15))=FALSE,LEFT($I15,6)<>"VACUUM"),"CDU",IF($H15="FLUID CAT CRACKING","FCC",IF(OR($H15="HYDROCRACKING",$H15="RESID_HYDROCRACKING"),"Hydrocracker",IF($H15="REFORMING","Reformer","")))) -> CDU | H15: ATMOS DISTILLATION | I15: Crude 1 (11 Plant) | J15: UNPLANNED | K15: 68.25 | L15: 175 | M15: PADD III
A16: 2023 | B16: 1 | C16: Jan | D16: Alliance Refinery | E16: PHILLIPS 66 | F16: =IF($M16="PADD I","PADD 1",IF($M16="PADD II","PADD 2",IF($M16="PADD III","PADD 3",IF($M16="PADD IV","PADD 4",IF($M16="PADD V","PADD 5",""))))) -> PADD 3 | G16: =IF(AND($H16="ATMOS DISTILLATION",ISNUMBER(SEARCH("VPS",$I16))=FALSE,LEFT($I16,6)<>"VACUUM"),"CDU",IF($H16="FLUID CAT CRACKING","FCC",IF(OR($H16="HYDROCRACKING",$H16="RESID_HYDROCRACKING"),"Hydrocracker",IF($H16="REFORMING","Reformer","")))) | H16: HYDROTREATING | I16: Gulfiner 293 (Furnace Oil) | J16: PLANNED | K16: 65.4 | L16: 65.4 | M16: PADD III
... A8827: 2027 | B8827: 12 | C8827: Dec | D8827: Anacortes Refinery | E8827: MARATHON PETROLEUM CORPORATION | F8827: =IF($M8827="PADD I","PADD 1",IF($M8827="PADD II","PADD 2",IF($M8827="PADD III","PADD 3",IF($M8827="PADD IV","PADD 4",IF($M8827="PADD V","PADD 5",""))))) -> PADD 5 | G8827: =IF(AND($H8827="ATMOS DISTILLATION",ISNUMBER(SEARCH("VPS",$I8827))=FALSE,LEFT($I8827,6)<>"VACUUM"),"CDU",IF($H8827="FLUID CAT CRACKING","FCC",IF(OR($H8827="HYDROCRACKING",$H8827="RESID_HYDROCRACKING"),"Hydrocracker",IF($H8827="REFORMING","Reformer","")))) | H8827: ISOMERIZATION | I8827: Isomerization C4 | J8827: PLANNED | K8827: 3.5 | L8827: 3.5 | M8827: PADD V
F8828: =IF($M8828="PADD I","PADD 1",IF($M8828="PADD II","PADD 2",IF($M8828="PADD III","PADD 3",IF($M8828="PADD IV","PADD 4",IF($M8828="PADD V","PADD 5",""))))) | G8828: =IF(AND($H8828="ATMOS DISTILLATION",ISNUMBER(SEARCH("VPS",$I8828))=FALSE,LEFT($I8828,6)<>"VACUUM"),"CDU",IF($H8828="FLUID CAT CRACKING","FCC",IF(OR($H8828="HYDROCRACKING",$H8828="RESID_HYDROCRACKING"),"Hydrocracker",IF($H8828="REFORMING","Reformer",""))))
F8829: =IF($M8829="PADD I","PADD 1",IF($M8829="PADD II","PADD 2",IF($M8829="PADD III","PADD 3",IF($M8829="PADD IV","PADD 4",IF($M8829="PADD V","PADD 5",""))))) | G8829: =IF(AND($H8829="ATMOS DISTILLATION",ISNUMBER(SEARCH("VPS",$I8829))=FALSE,LEFT($I8829,6)<>"VACUUM"),"CDU",IF($H8829="FLUID CAT CRACKING","FCC",IF(OR($H8829="HYDROCRACKING",$H8829="RESID_HYDROCRACKING"),"Hydrocracker",IF($H8829="REFORMING","Reformer",""))))
F8830: =IF($M8830="PADD I","PADD 1",IF($M8830="PADD II","PADD 2",IF($M8830="PADD III","PADD 3",IF($M8830="PADD IV","PADD 4",IF($M8830="PADD V","PADD 5",""))))) | G8830: =IF(AND($H8830="ATMOS DISTILLATION",ISNUMBER(SEARCH("VPS",$I8830))=FALSE,LEFT($I8830,6)<>"VACUUM"),"CDU",IF($H8830="FLUID CAT CRACKING","FCC",IF(OR($H8830="HYDROCRACKING",$H8830="RESID_HYDROCRACKING"),"Hydrocracker",IF($H8830="REFORMING","Reformer",""))))
F8831: =IF($M8831="PADD I","PADD 1",IF($M8831="PADD II","PADD 2",IF($M8831="PADD III","PADD 3",IF($M8831="PADD IV","PADD 4",IF($M8831="PADD V","PADD 5",""))))) | G8831: =IF(AND($H8831="ATMOS DISTILLATION",ISNUMBER(SEARCH("VPS",$I8831))=FALSE,LEFT($I8831,6)<>"VACUUM"),"CDU",IF($H8831="FLUID CAT CRACKING","FCC",IF(OR($H8831="HYDROCRACKING",$H8831="RESID_HYDROCRACKING"),"Hydrocracker",IF($H8831="REFORMING","Reformer",""))))
F8832: =IF($M8832="PADD I","PADD 1",IF($M8832="PADD II","PADD 2",IF($M8832="PADD III","PADD 3",IF($M8832="PADD IV","PADD 4",IF($M8832="PADD V","PADD 5",""))))) | G8832: =IF(AND($H8832="ATMOS DISTILLATION",ISNUMBER(SEARCH("VPS",$I8832))=FALSE,LEFT($I8832,6)<>"VACUUM"),"CDU",IF($H8832="FLUID CAT CRACKING","FCC",IF(OR($H8832="HYDROCRACKING",$H8832="RESID_HYDROCRACKING"),"Hydrocracker",IF($H8832="REFORMING","Reformer",""))))
F8833: =IF($M8833="PADD I","PADD 1",IF($M8833="PADD II","PADD 2",IF($M8833="PADD III","PADD 3",IF($M8833="PADD IV","PADD 4",IF($M8833="PADD V","PADD 5",""))))) | G8833: =IF(AND($H8833="ATMOS DISTILLATION",ISNUMBER(SEARCH("VPS",$I8833))=FALSE,LEFT($I8833,6)<>"VACUUM"),"CDU",IF($H8833="FLUID CAT CRACKING","FCC",IF(OR($H8833="HYDROCRACKING",$H8833="RESID_HYDROCRACKING"),"Hydrocracker",IF($H8833="REFORMING","Reformer",""))))
F8834: =IF($M8834="PADD I","PADD 1",IF($M8834="PADD II","PADD 2",IF($M8834="PADD III","PADD 3",IF($M8834="PADD IV","PADD 4",IF($M8834="PADD V","PADD 5",""))))) | G8834: =IF(AND($H8834="ATMOS DISTILLATION",ISNUMBER(SEARCH("VPS",$I8834))=FALSE,LEFT($I8834,6)<>"VACUUM"),"CDU",IF($H8834="FLUID CAT CRACKING","FCC",IF(OR($H8834="HYDROCRACKING",$H8834="RESID_HYDROCRACKING"),"Hydrocracker",IF($H8834="REFORMING","Reformer",""))))
F8835: =IF($M8835="PADD I","PADD 1",IF($M8835="PADD II","PADD 2",IF($M8835="PADD III","PADD 3",IF($M8835="PADD IV","PADD 4",IF($M8835="PADD V","PADD 5",""))))) | G8835: =IF(AND($H8835="ATMOS DISTILLATION",ISNUMBER(SEARCH("VPS",$I8835))=FALSE,LEFT($I8835,6)<>"VACUUM"),"CDU",IF($H8835="FLUID CAT CRACKING","FCC",IF(OR($H8835="HYDROCRACKING",$H8835="RESID_HYDROCRACKING"),"Hydrocracker",IF($H8835="REFORMING","Reformer",""))))
F8836: =IF($M8836="PADD I","PADD 1",IF($M8836="PADD II","PADD 2",IF($M8836="PADD III","PADD 3",IF($M8836="PADD IV","PADD 4",IF($M8836="PADD V","PADD 5",""))))) | G8836: =IF(AND($H8836="ATMOS DISTILLATION",ISNUMBER(SEARCH("VPS",$I8836))=FALSE,LEFT($I8836,6)<>"VACUUM"),"CDU",IF($H8836="FLUID CAT CRACKING","FCC",IF(OR($H8836="HYDROCRACKING",$H8836="RESID_HYDROCRACKING"),"Hydrocracker",IF($H8836="REFORMING","Reformer",""))))
F8837: =IF($M8837="PADD I","PADD 1",IF($M8837="PADD II","PADD 2",IF($M8837="PADD III","PADD 3",IF($M8837="PADD IV","PADD 4",IF($M8837="PADD V","PADD 5",""))))) | G8837: =IF(AND($H8837="ATMOS DISTILLATION",ISNUMBER(SEARCH("VPS",$I8837))=FALSE,LEFT($I8837,6)<>"VACUUM"),"CDU",IF($H8837="FLUID CAT CRACKING","FCC",IF(OR($H8837="HYDROCRACKING",$H8837="RESID_HYDROCRACKING"),"Hydrocracker",IF($H8837="REFORMING","Reformer",""))))
F8838: =IF($M8838="PADD I","PADD 1",IF($M8838="PADD II","PADD 2",IF($M8838="PADD III","PADD 3",IF($M8838="PADD IV","PADD 4",IF($M8838="PADD V","PADD 5",""))))) | G8838: =IF(AND($H8838="ATMOS DISTILLATION",ISNUMBER(SEARCH("VPS",$I8838))=FALSE,LEFT($I8838,6)<>"VACUUM"),"CDU",IF($H8838="FLUID CAT CRACKING","FCC",IF(OR($H8838="HYDROCRACKING",$H8838="RESID_HYDROCRACKING"),"Hydrocracker",IF($H8838="REFORMING","Reformer",""))))
F8839: =IF($M8839="PADD I","PADD 1",IF($M8839="PADD II","PADD 2",IF($M8839="PADD III","PADD 3",IF($M8839="PADD IV","PADD 4",IF($M8839="PADD V","PADD 5",""))))) | G8839: =IF(AND($H8839="ATMOS DISTILLATION",ISNUMBER(SEARCH("VPS",$I8839))=FALSE,LEFT($I8839,6)<>"VACUUM"),"CDU",IF($H8839="FLUID CAT CRACKING","FCC",IF(OR($H8839="HYDROCRACKING",$H8839="RESID_HYDROCRACKING"),"Hydrocracker",IF($H8839="REFORMING","Reformer",""))))
... F14827: =IF($M14827="PADD I","PADD 1",IF($M14827="PADD II","PADD 2",IF($M14827="PADD III","PADD 3",IF($M14827="PADD IV","PADD 4",IF($M14827="PADD V","PADD 5",""))))) | G14827: =IF(AND($H14827="ATMOS DISTILLATION",ISNUMBER(SEARCH("VPS",$I14827))=FALSE,LEFT($I14827,6)<>"VACUUM"),"CDU",IF($H14827="FLUID CAT CRACKING","FCC",IF(OR($H14827="HYDROCRACKING",$H14827="RESID_HYDROCRACKING"),"Hydrocracker",IF($H14827="REFORMING","Reformer",""))))
